Workbook

Sheet Описание
A1: РАСЧЁТЫ К ОТЧЁТУ О НИР
A3: Рабочая книга | B3: Сравнительная оценка электротрактора JINMA YL254ET (ЭТ) и дизельного аналога JINMA JM-254 (Д) по результатам полевых испытаний 15.09–15.10.2026
A4: Назначение | B4: Расчёт единичных показателей обеих машин, нормированных разностей, весов (МАИ + энтропийный метод) и комплексного показателя I для 16 исследованных режимов; пересчёт при изменении исходных данных
A5: Как пользоваться | B5: Изменяйте только ячейки с синим шрифтом на жёлтом фоне на листах «Исходные» и «Веса». Все остальные значения пересчитываются формулами
A6: Ключевые рычаги | B6: S_task (сменное задание; 0 — полная смена), T_year_h (годовая загрузка), c_D и c_el (цены), l_charge_km (удалённость зарядки), P_ch_ac (мощность зарядки), цены машин
A7: Цвета | B7: синий шрифт — исходные данные; чёрный — формулы; зелёный — ссылки на другие листы; жёлтая заливка — изменяемые ячейки
A8: Лист «Исходные» | B8: исходные данные и допущения с источниками и диапазонами вариации (именованные ячейки)
A9: Лист «Проходы» | B9: результаты учётных проходов (значения из журналов CAN 1 Гц и полевых журналов) и расчётные показатели проходов (формулы); буксование — по ГОСТ 7057: δ = 1 − N0/N (N — число оборотов двигателя хода на учётной делянке)
A10: Лист «Опыт_режимы» | B10: средние по повторностям, стандартные отклонения, доверительные интервалы (формулы AVERAGEIFS и т. п.)
A11: Лист «Модели» | B11: коэффициенты моделей: сопротивление передвижению, k = k0 + ε·v² (ЛИНЕЙН), A = A0 + Av·v + Aa·a (ЛИНЕЙН), кривая буксования δ(φ)
A12: Лист «Энергетика» | B12: мощности ЭТ и Д, буксование, запас мощности, допустимость режимов, часовой расход топлива Д (ASAE D497.7)
A13: Лист «Смена» | B13: модель смены: развороты, автономность, подзарядки (до трёх циклов), сменная выработка, энергия, полученная из сети, расход топлива на 1 га
A14: Лист «Экономика» | B14: удельные прямые и совокупные затраты (ГОСТ 34393-2018, ASAE D497.7)
... A19: Проверка | B19: при исходных данных по умолчанию значения комплексного показателя совпадают с отчётом (таблица 5.6, сценарий 1); расхождение собственного вектора МАИ и метода геометрического среднего < 0,001

Sheet Исходные
A1: Обозначение (имя) | B1: Параметр | C1: Значение | D1: Ед. | E1: Статус, источник | F1: Мин. | G1: Макс.
A2: m_ET | B2: Масса ЭТ | C2: 1300 | D2: кг | E2: паспорт изготовителя
A3: m_D | B3: Масса Д | C3: 1140 | D3: кг | E3: TractorData.com
A4: g | B4: Ускорение свободного падения | C4: 9.81 | D4: м/с² | E4: константа
A5: E_bat_kWh | B5: Энергоёмкость батареи | C5: 23.35 | D5: кВт·ч | E5: 304 А·ч × 76,8 В; подтверждено опытом
A6: SOC_max | B6: SOC после зарядки | C6: 98 | D6: % | E6: опыт
A7: SOC_min | B7: Нижняя граница SOC | C7: 30 | D7: % | E7: порог предупреждения BMS (код 61)
A8: P_el_lim | B8: Предельная мощность от батареи | C8: 17.5 | D8: кВт | E8: опыт (17,3–17,5 кВт)
A9: P_mot_1h | B9: Часовая мощность двигателя хода | C9: 12 | D9: кВт | E9: паспорт
A10: P_aux | B10: Собственное потребление систем | C10: 0.18 | D10: кВт | E10: опыт
A11: eta_ep | B11: КПД тягового электропривода | C11: 0.88 | D11: – | E11: допущение | F11: 0.83 | G11: 0.92
A12: eta_tr | B12: КПД трансмиссии | C12: 0.88 | D12: – | E12: допущение | F12: 0.85 | G12: 0.91
A13: P_hyd_idle_D | B13: Потери гидронасоса Д на холостом ходу | C13: 0.15 | D13: кВт | E13: допущение
A14: P_e_nom_D | B14: Номинальная мощность двигателя Д | C14: 18.4 | D14: кВт | E14: паспорт
A15: k_pto_D | B15: Отношение P_ВОМ/P_е для Д | C15: 0.9 | D15: – | E15: допущение | F15: 0.85 | G15: 0.92
A16: k_D | B16: Поправка расхода топлива к ASAE D497.7 | C16: 1 | D16: – | E16: допущение (1,0 — в пользу Д) | F16: 1 | G16: 1.2
A17: sfc_a | B17: ASAE D497.7: коэффициент a | C17: 0.22 | D17: л/(кВт·ч) | E17: ASAE D497.7
A18: sfc_b | B18: ASAE D497.7: коэффициент b | C18: 0.096 | D18: л/(кВт·ч) | E18: ASAE D497.7
A19: LHV_D | B19: Теплота сгорания ДТ | C19: 35.9 | D19: МДж/л | E19: справочное
A20: tank_D | B20: Топливный бак Д | C20: 22 | D20: л | E20: TractorData.com
A21: t_refuel_h | B21: Время дозаправки | C21: 0.15 | D21: ч | E21: допущение
A22: P_ch_ac | B22: Мощность зарядного устройства | C22: 3.5 | D22: кВт | E22: допущение: разъём 16 А, 230 В
A23: eta_ch | B23: КПД зарядного устройства | C23: 0.92 | D23: – | E23: допущение | F23: 0.88 | G23: 0.95
A24: eta_bat | B24: КПД батареи (энергетический) | C24: 0.95 | D24: – | E24: допущение | F24: 0.92 | G24: 0.97
A25: T_shift_h | B25: Продолжительность смены | C25: 8 | D25: ч | E25: принято
A26: tau_svc | B26: Доля смены на работу и переезды | C26: 0.92 | D26: – | E26: допущение
A27: L_run_m | B27: Длина гона | C27: 300 | D27: м | E27: принято
A28: l_charge_km | B28: Удалённость места зарядки | C28: 1 | D28: км | E28: принято
A29: v_transp_kmh | B29: Скорость переезда | C29: 15.4 | D29: км/ч | E29: опыт
A30: P_transp_kW | B30: Мощность при переезде | C30: 6.3 | D30: кВт | E30: опыт
A31: usd_kzt | B31: Курс доллара США | C31: 452.12 | D31: тг | E31: НБРК, 18.10.2026
A32: price_ET_usd | B32: Цена ЭТ (FOB) | C32: 13300 | D32: $ | E32: Made-in-China, Jiangsu Yueda
A33: price_D_usd | B33: Цена Д (FOB) | C33: 5050 | D33: $ | E33: Made-in-China, Jinma
A34: k_landed | B34: Коэффициент «FOB → цена у дилера» | C34: 1.467 | D34: – | E34: 1,10 × 1,16 (НДС) × 1,15 | F34: 1.3 | G34: 1.65
A35: c_el | B35: Цена электроэнергии с НДС | C35: 45.59 | D35: тг/(кВт·ч) | E35: ЭнергоСбыт АЖК с 12.09.2026 | F35: 39.3 | G35: 55
A36: c_D | B36: Цена дизельного топлива | C36: 345 | D36: тг/л | E36: средняя розничная, сент.–окт. 2026 | F36: 300 | G36: 400
A37: wage_month | B37: Средняя зарплата в сельском хозяйстве | C37: 365262 | D37: тг/мес | E37: БНС АСПиР РК, II кв. 2026
A38: h_month | B38: Рабочих часов в месяце | C38: 166 | D38: ч | E38: принято
A39: k_soc | B39: Коэффициент начислений на ФОТ | C39: 1.15 | D39: – | E39: допущение
A40: T_year_h | B40: Годовая загрузка | C40: 600 | D40: ч/год | E40: допущение | F40: 300 | G40: 1000
A41: life_y | B41: Срок службы | C41: 10 | D41: лет | E41: допущение
A42: r_disc | B42: Реальная ставка дисконтирования | C42: 0.05 | D42: – | E42: допущение | F42: 0 | G42: 0.1
A43: salvage | B43: Остаточная стоимость | C43: 0.2 | D43: доля | E43: допущение
A44: ASAE_RF1 | B44: ASAE D497.7: RF1 (колёсные тракторы) | C44: 0.007 | D44: – | E44: ASAE D497.7
A45: ASAE_RF2 | B45: ASAE D497.7: RF2 | C45: 2 | D45: – | E45: ASAE D497.7
A46: k_RM_ET | B46: Доля затрат на ремонт и ТО ЭТ от Д | C46: 0.6 | D46: – | E46: допущение | F46: 0.4 | G46: 1
A47: bat_usd_kWh | B47: Стоимость замены батареи | C47: 200 | D47: $/(кВт·ч) | E47: 2,5 × BNEF-2025 LFP | F47: 100 | G47: 300
A48: bat_cycles | B48: Цикловой ресурс батареи | C48: 3000 | D48: циклов | E48: допущение
A49: bat_cal_y | B49: Календарный ресурс батареи | C49: 10 | D49: лет | E49: допущение
A50: EF_grid | B50: Коэффициент выбросов CO2 энергосистемы РК | C50: 0.606 | D50: кг/(кВт·ч) | E50: IEA-2025 (через ABB) | F50: 0.45 | G50: 1
A51: EF_D | B51: Коэффициент выбросов CO2 при сжигании ДТ | C51: 2.68 | D51: кг/л | E51: IPCC 2006
A52: PEF_el | B52: Коэффициент первичной энергии электроэнергии | C52: 2.5 | D52: – | E52: Директива 2012/27/ЕС | F52: 2.1 | G52: 3
A53: PEF_D | B53: Коэффициент первичной энергии ДТ | C53: 1.15 | D53: – | E53: JEC WTW v5
A54: slip_max | B54: Допустимое буксование (номинальное тяговое усилие 4К4) | C54: 0.16 | D54: – | E54: ГОСТ 27021-86
A55: S_task | B55: Сменное задание (0 — полная смена: задание = выработке Д) | C55: 0 | D55: га/смену | E55: сценарий
A56: alpha_w | B56: Доля экспертных весов в итоговых | C56: 0.5 | D56: – | E56: методика (0,5)
A58: Производные величины
A59: E_use | B59: Используемый запас энергии, кВт·ч | C59: =E_bat_kWh*(SOC_max-SOC_min)/100 -> 15.878
A60: T_av | B60: Время смены на работу и переезды, ч | C60: =T_shift_h*tau_svc -> 7.36
A61: t_tr | B61: Время переезда в одну сторону, ч | C61: =l_charge_km/v_transp_kmh -> 0.064935065
A62: E_tr | B62: Энергия переезда ЭТ в одну сторону, кВт·ч | C62: =P_transp_kW*t_tr -> 0.40909091
A63: t_ch | B63: Время полной подзарядки, ч | C63: =E_use/(eta_ch*eta_bat*P_ch_ac) -> 5.1905852
A64: P_pto_nom | B64: Номинальная мощность ВОМ Д, кВт | C64: =k_pto_D*P_e_nom_D -> 16.56
A65: wage_h | B65: Стоимость часа работы тракториста, тг/ч | C65: =wage_month/h_month*k_soc -> 2530.4295
A66: price_ET | B66: Цена ЭТ у дилера, тг | C66: =price_ET_usd*usd_kzt*k_landed -> 8821358.5
A67: price_D | B67: Цена Д у дилера, тг | C67: =price_D_usd*usd_kzt*k_landed -> 3349463.2
A68: T_life | B68: Наработка за срок службы, ч | C68: =T_year_h*life_y -> 6000
A69: rm_h_D | B69: Средние затраты на ремонт и ТО Д, тг/ч | C69: =ASAE_RF1*price_D*(T_life/1000)^ASAE_RF2/T_life -> 140.67745
A70: k_CRF | B70: Коэффициент возврата капитала | C70: =IF(r_disc=0,1/life_y,r_disc*(1+r_disc)^life_y/((1+r_disc)^life_y-1)) -> 0.12950457
A71: k_SFF | B71: Коэффициент фонда возмещения | C71: =IF(r_disc=0,1/life_y,r_disc/((1+r_disc)^life_y-1)) -> 0.079504575
A72: C_bat | B72: Стоимость замены батареи, тг | C72: =bat_usd_kWh*E_bat_kWh*usd_kzt -> 2111400.4
A73: Q_turn | B73: Расход топлива Д на развороте, л/ч | C73: =k_D*(sfc_a*(eta_ep*(turn_P-P_aux)+P_hyd_idle_D)+sfc_b*P_pto_nom) -> 2.1682086
A74: Q_tr | B74: Расход топлива Д на переезде, л/ч | C74: =k_D*(sfc_a*(eta_ep*(P_transp_kW-P_aux)*m_D/m_ET+P_hyd_idle_D)+sfc_b*P_pto_nom) -> 2.6617665

Sheet Проходы
A1: Машина | B1: Сессия | C1: Проход | D1: Блок | E1: Вид | F1: a_пл, м | G1: v_пл, км/ч | H1: Диапазон | I1: n, с | J1: P̄, кВт | K1: s_P, кВт | L1: N, об | M1: v, км/ч | N1: a, м | O1: s_a, м | P1: B, м | Q1: n_ВОМ, мин⁻¹ | R1: W0, га/ч | S1: e, кВт·ч/га | T1: δ | U1: e_V, кДж/м³ | V1: v², м²/с² | W1: F_к, Н | X1: R, Н | Y1: k, кН/м² | Z1: φ | AA1: A, кДж/м³ | AB1: (P−P_aux)/v, кВт·с/м
A2: культиватор | B2: C | C2: 0 | E2: холостой | F2: 0 | G2: 4.5 | H2: L | I2: 80 | J2: 3.1968 | K2: 0.075 | L2: 3288.233 | M2: 4.472 | Q2: 0 | T2: =IF(E2="холостой","",IFERROR(1-AVERAGEIFS($L:$L,$B:$B,B2,$H:$H,H2,$E:$E,"холостой")/L2,"")) | V2: =(M2/3.6)^2 -> 1.543116 | W2: =eta_ep*eta_tr*(J2-P_aux)*1000/(M2/3.6) -> 1880.6699
A3: культиватор | B3: C | C3: 0 | E3: холостой | F3: 0 | G3: 4.5 | H3: L | I3: 80 | J3: 3.1963 | K3: 0.0752 | L3: 3289.433 | M3: 4.489 | Q3: 0 | T3: =IF(E3="холостой","",IFERROR(1-AVERAGEIFS($L:$L,$B:$B,B3,$H:$H,H3,$E:$E,"холостой")/L3,"")) | V3: =(M3/3.6)^2 -> 1.5548704 | W3: =eta_ep*eta_tr*(J3-P_aux)*1000/(M3/3.6) -> 1873.2372
A4: культиватор | B4: C | C4: 0 | E4: холостой | F4: 0 | G4: 4.5 | H4: L | I4: 80 | J4: 3.1981 | K4: 0.075 | L4: 3289.95 | M4: 4.515 | Q4: 0 | T4: =IF(E4="холостой","",IFERROR(1-AVERAGEIFS($L:$L,$B:$B,B4,$H:$H,H4,$E:$E,"холостой")/L4,"")) | V4: =(M4/3.6)^2 -> 1.572934 | W4: =eta_ep*eta_tr*(J4-P_aux)*1000/(M4/3.6) -> 1863.5614
A5: культиватор | B5: C | C5: 0 | E5: холостой | F5: 0 | G5: 4.5 | H5: L | I5: 80 | J5: 3.1988 | K5: 0.073 | L5: 3289.267 | M5: 4.539 | Q5: 0 | T5: =IF(E5="холостой","",IFERROR(1-AVERAGEIFS($L:$L,$B:$B,B5,$H:$H,H5,$E:$E,"холостой")/L5,"")) | V5: =(M5/3.6)^2 -> 1.5897007 | W5: =eta_ep*eta_tr*(J5-P_aux)*1000/(M5/3.6) -> 1854.1378
A6: культиватор | B6: C | C6: 1 | D6: 1 | E6: рабочий | F6: 0.11 | G6: 5.4 | H6: L | I6: 67 | J6: 15.2588 | K6: 0.5465 | L6: 3659.583 | M6: 5.409 | N6: 0.1068 | O6: 0.0047 | P6: 1.204 | Q6: 0 | R6: =IF(P6="","",0.1*P6*M6) -> 0.6512436 | S6: =IF(R6="","",J6/R6) -> 23.430249 | T6: =IF(E6="холостой","",IFERROR(1-AVERAGEIFS($L:$L,$B:$B,B6,$H:$H,H6,$E:$E,"холостой")/L6,"")) -> 0.1012034 | U6: =IF(R6="","",3.6*J6/(P6*N6*M6)) -> 78.978369 | V6: =(M6/3.6)^2 -> 2.2575063 | W6: =eta_ep*eta_tr*(J6-P_aux)*1000*(1-T6)/(M6/3.6) -> 6985.2035 | X6: =W6-f_roll*m_ET*g -> 5117.3019 | Y6: =X6/(P6*N6)/1000 -> 39.796356 | Z6: =X6/(m_ET*g) -> 0.4012626
A7: культиватор | B7: C | C7: 2 | D7: 1 | E7: рабочий | F7: 0.08 | G7: 5.4 | H7: L | I7: 66 | J7: 11.6538 | K7: 0.5561 | L7: 3482.2 | M7: 5.403 | N7: 0.0774 | O7: 0.0047 | P7: 1.208 | Q7: 0 | R7: =IF(P7="","",0.1*P7*M7) -> 0.6526824 | S7: =IF(R7="","",J7/R7) -> 17.855239 | T7: =IF(E7="холостой","",IFERROR(1-AVERAGEIFS($L:$L,$B:$B,B7,$H:$H,H7,$E:$E,"холостой")/L7,"")) -> 0.055418773 | U7: =IF(R7="","",3.6*J7/(P7*N7*M7)) -> 83.047622 | V7: =(M7/3.6)^2 -> 2.2525007 | W7: =eta_ep*eta_tr*(J7-P_aux)*1000*(1-T7)/(M7/3.6) -> 5592.1584 | X7: =W7-f_roll*m_ET*g -> 3724.2568 | Y7: =X7/(P7*N7)/1000 -> 39.831964 | Z7: =X7/(m_ET*g) -> 0.29202986
A8: культиватор | B8: C | C8: 3 | D8: 1 | E8: рабочий | F8: 0.14 | G8: 4.5 | H8: L | I8: 80 | J8: 15.7265 | K8: 0.4797 | L8: 3814.133 | M8: 4.452 | N8: 0.1388 | O8: 0.0052 | P8: 1.19 | Q8: 0 | R8: =IF(P8="","",0.1*P8*M8) -> 0.529788 | S8: =IF(R8="","",J8/R8) -> 29.684515 | T8: =IF(E8="холостой","",IFERROR(1-AVERAGEIFS($L:$L,$B:$B,B8,$H:$H,H8,$E:$E,"холостой")/L8,"")) -> 0.13762295 | U8: =IF(R8="","",3.6*J8/(P8*N8*M8)) -> 76.991538 | V8: =(M8/3.6)^2 -> 1.5293444 | W8: =eta_ep*eta_tr*(J8-P_aux)*1000*(1-T8)/(M8/3.6) -> 8395.4216 | X8: =W8-f_roll*m_ET*g -> 6527.52 | Y8: =X8/(P8*N8)/1000 -> 39.519531 | Z8: =X8/(m_ET*g) -> 0.51184192
A9: культиватор | B9: C | C9: 4 | D9: 1 | E9: рабочий | F9: 0.11 | G9: 4.5 | H9: L | I9: 79 | J9: 11.9966 | K9: 0.582 | L9: 3590.317 | M9: 4.547 | N9: 0.1076 | O9: 0.006 | P9: 1.185 | Q9: 0 | R9: =IF(P9="","",0.1*P9*M9) -> 0.5388195 | S9: =IF(R9="","",J9/R9) -> 22.264599 | T9: =IF(E9="холостой","",IFERROR(1-AVERAGEIFS($L:$L,$B:$B,B9,$H:$H,H9,$E:$E,"холостой")/L9,"")) -> 0.083863417 | U9: =IF(R9="","",3.6*J9/(P9*N9*M9)) -> 74.491223 | V9: =(M9/3.6)^2 -> 1.5953093 | W9: =eta_ep*eta_tr*(J9-P_aux)*1000*(1-T9)/(M9/3.6) -> 6637.3642 | X9: =W9-f_roll*m_ET*g -> 4769.4627 | Y9: =X9/(P9*N9)/1000 -> 37.40579 | Z9: =X9/(m_ET*g) -> 0.37398751
A10: культиватор | B10: C | C10: 5 | D10: 1 | E10: рабочий | F10: 0.11 | G10: 3.6 | H10: L | I10: 100 | J10: 10.0252 | K10: 0.375 | L10: 3622.767 | M10: 3.572 | N10: 0.1121 | O10: 0.0048 | P10: 1.207 | Q10: 0 | R10: =IF(P10="","",0.1*P10*M10) -> 0.4311404 | S10: =IF(R10="","",J10/R10) -> 23.25275 | T10: =IF(E10="холостой","",IFERROR(1-AVERAGEIFS($L:$L,$B:$B,B10,$H:$H,H10,$E:$E,"холостой")/L10,"")) -> 0.092069473 | U10: =IF(R10="","",3.6*J10/(P10*N10*M10)) -> 74.674309 | V10: =(M10/3.6)^2 -> 0.98450494 | W10: =eta_ep*eta_tr*(J10-P_aux)*1000*(1-T10)/(M10/3.6) -> 6976.4351 | X10: =W10-f_roll*m_ET*g -> 5108.5335 | Y10: =X10/(P10*N10)/1000 -> 37.755773 | Z10: =X10/(m_ET*g) -> 0.40057504
A11: культиватор | B11: C | C11: 6 | D11: 1 | E11: рабочий | F11: 0.08 | G11: 4.5 | H11: L | I11: 80 | J11: 9.1676 | K11: 0.3946 | L11: 3509.4 | M11: 4.564 | N11: 0.0794 | O11: 0.006 | P11: 1.191 | Q11: 0 | R11: =IF(P11="","",0.1*P11*M11) -> 0.5435724 | S11: =IF(R11="","",J11/R11) -> 16.865463 | T11: =IF(E11="холостой","",IFERROR(1-AVERAGEIFS($L:$L,$B:$B,B11,$H:$H,H11,$E:$E,"холостой")/L11,"")) -> 0.062739856 | U11: =IF(R11="","",3.6*J11/(P11*N11*M11)) -> 76.468093 | V11: =(M11/3.6)^2 -> 1.6072605 | W11: =eta_ep*eta_tr*(J11-P_aux)*1000*(1-T11)/(M11/3.6) -> 5145.4824 | X11: =W11-f_roll*m_ET*g -> 3277.5808 | Y11: =X11/(P11*N11)/1000 -> 34.659408 | Z11: =X11/(m_ET*g) -> 0.25700469
A12: культиватор | B12: C | C12: 7 | D12: 1 | E12: рабочий | F12: 0.08 | G12: 3.6 | H12: L | I12: 100 | J12: 7.483 | K12: 0.2448 | L12: 3501.467 | M12: 3.63 | N12: 0.0772 | O12: 0.0049 | P12: 1.205 | Q12: 0 | R12: =IF(P12="","",0.1*P12*M12) -> 0.437415 | S12: =IF(R12="","",J12/R12) -> 17.107324 | T12: =IF(E12="холостой","",IFERROR(1-AVERAGEIFS($L:$L,$B:$B,B12,$H:$H,H12,$E:$E,"холостой")/L12,"")) -> 0.060616379 | U12: =IF(R12="","",3.6*J12/(P12*N12*M12)) -> 79.775085 | V12: =(M12/3.6)^2 -> 1.0167361 | W12: =eta_ep*eta_tr*(J12-P_aux)*1000*(1-T12)/(M12/3.6) -> 5268.7247 | X12: =W12-f_roll*m_ET*g -> 3400.8231 | Y12: =X12/(P12*N12)/1000 -> 36.55777 | Z12: =X12/(m_ET*g) -> 0.26666848
A13: культиватор | B13: C | C13: 8 | D13: 1 | E13: рабочий | F13: 0.14 | G13: 3.6 | H13: L | I13: 100 | J13: 11.9499 | K13: 0.4091 | L13: 3791.433 | M13: 3.581 | N13: 0.1382 | O13: 0.0052 | P13: 1.187 | Q13: 0 | R13: =IF(P13="","",0.1*P13*M13) -> 0.4250647 | S13: =IF(R13="","",J13/R13) -> 28.113132 | T13: =IF(E13="холостой","",IFERROR(1-AVERAGEIFS($L:$L,$B:$B,B13,$H:$H,H13,$E:$E,"холостой")/L13,"")) -> 0.13245975 | U13: =IF(R13="","",3.6*J13/(P13*N13*M13)) -> 73.232471 | V13: =(M13/3.6)^2 -> 0.9894723 | W13: =eta_ep*eta_tr*(J13-P_aux)*1000*(1-T13)/(M13/3.6) -> 7949.2459 | X13: =W13-f_roll*m_ET*g -> 6081.3443 | Y13: =X13/(P13*N13)/1000 -> 37.071558 | Z13: =X13/(m_ET*g) -> 0.47685598
A14: культиватор | B14: C | C14: 9 | D14: 2 | E14: рабочий | F14: 0.08 | G14: 5.4 | H14: L | I14: 67 | J14: 12.0397 | K14: 0.3817 | L14: 3534.25 | M14: 5.407 | N14: 0.0807 | O14: 0.0053 | P14: 1.195 | Q14: 0 | R14: =IF(P14="","",0.1*P14*M14) -> 0.6461365 | S14: =IF(R14="","",J14/R14) -> 18.633369 | T14: =IF(E14="холостой","",IFERROR(1-AVERAGEIFS($L:$L,$B:$B,B14,$H:$H,H14,$E:$E,"холостой")/L14,"")) -> 0.069329914 | U14: =IF(R14="","",3.6*J14/(P14*N14*M14)) -> 83.122837 | V14: =(M14/3.6)^2 -> 2.2558371 | W14: =eta_ep*eta_tr*(J14-P_aux)*1000*(1-T14)/(M14/3.6) -> 5690.8997 | X14: =W14-f_roll*m_ET*g -> 3822.9982 | Y14: =X14/(P14*N14)/1000 -> 39.642647 | Z14: =X14/(m_ET*g) -> 0.29977246
A15: культиватор | B15: C | C15: 10 | D15: 2 | E15: рабочий | F15: 0.08 | G15: 4.5 | H15: L | I15: 80 | J15: 9.4895 | K15: 0.4175 | L15: 3509.967 | M15: 4.511 | N15: 0.0789 | O15: 0.0053 | P15: 1.198 | Q15: 0 | R15: =IF(P15="","",0.1*P15*M15) -> 0.5404178 | S15: =IF(R15="","",J15/R15) -> 17.559562 | T15: =IF(E15="холостой","",IFERROR(1-AVERAGEIFS($L:$L,$B:$B,B15,$H:$H,H15,$E:$E,"холостой")/L15,"")) -> 0.062891261 | U15: =IF(R15="","",3.6*J15/(P15*N15*M15)) -> 80.119676 | V15: =(M15/3.6)^2 -> 1.5701482 | W15: =eta_ep*eta_tr*(J15-P_aux)*1000*(1-T15)/(M15/3.6) -> 5391.5218 | X15: =W15-f_roll*m_ET*g -> 3523.6202 | Y15: =X15/(P15*N15)/1000 -> 37.278229 | Z15: =X15/(m_ET*g) -> 0.27629736
A16: культиватор | B16: C | C16: 11 | D16: 2 | E16: рабочий | F16: 0.08 | G16: 3.6 | H16: L | I16: 100 | J16: 7.6455 | K16: 0.2684 | L16: 3502.617 | M16: 3.591 | N16: 0.081 | O16: 0.0049 | P16: 1.197 | Q16: 0 | R16: =IF(P16="","",0.1*P16*M16) -> 0.4298427 | S16: =IF(R16="","",J16/R16) -> 17.786739 | T16: =IF(E16="холостой","",IFERROR(1-AVERAGEIFS($L:$L,$B:$B,B16,$H:$H,H16,$E:$E,"холостой")/L16,"")) -> 0.060924803 | U16: =IF(R16="","",3.6*J16/(P16*N16*M16)) -> 79.052174 | V16: =(M16/3.6)^2 -> 0.99500625 | W16: =eta_ep*eta_tr*(J16-P_aux)*1000*(1-T16)/(M16/3.6) -> 5442.6663 | X16: =W16-f_roll*m_ET*g -> 3574.7648 | Y16: =X16/(P16*N16)/1000 -> 36.869589 | Z16: =X16/(m_ET*g) -> 0.28030775
A17: культиватор | B17: C | C17: 12 | D17: 2 | E17: рабочий | F17: 0.14 | G17: 3.6 | H17: L | I17: 100 | J17: 12.2488 | K17: 0.4212 | L17: 3790.533 | M17: 3.581 | N17: 0.1414 | O17: 0.0046 | P17: 1.205 | Q17: 0 | R17: =IF(P17="","",0.1*P17*M17) -> 0.4315105 | S17: =IF(R17="","",J17/R17) -> 28.385868 | T17: =IF(E17="холостой","",IFERROR(1-AVERAGEIFS($L:$L,$B:$B,B17,$H:$H,H17,$E:$E,"холостой")/L17,"")) -> 0.13225376 | U17: =IF(R17="","",3.6*J17/(P17*N17*M17)) -> 72.269536 | V17: =(M17/3.6)^2 -> 0.9894723 | W17: =eta_ep*eta_tr*(J17-P_aux)*1000*(1-T17)/(M17/3.6) -> 8153.0547 | X17: =W17-f_roll*m_ET*g -> 6285.1531 | Y17: =X17/(P17*N17)/1000 -> 36.887515 | Z17: =X17/(m_ET*g) -> 0.49283722
... A29: культиватор | B29: C | C29: 24 | D29: 3 | E29: рабочий | F29: 0.08 | G29: 5.4 | H29: L | I29: 66 | J29: 11.5041 | K29: 0.4169 | L29: 3481.983 | M29: 5.435 | N29: 0.0788 | O29: 0.0057 | P29: 1.206 | Q29: 0 | R29: =IF(P29="","",0.1*P29*M29) -> 0.655461 | S29: =IF(R29="","",J29/R29) -> 17.551159 | T29: =IF(E29="холостой","",IFERROR(1-AVERAGEIFS($L:$L,$B:$B,B29,$H:$H,H29,$E:$E,"холостой")/L29,"")) -> 0.055359906 | U29: =IF(R29="","",3.6*J29/(P29*N29*M29)) -> 80.182958 | V29: =(M29/3.6)^2 -> 2.2792612 | W29: =eta_ep*eta_tr*(J29-P_aux)*1000*(1-T29)/(M29/3.6) -> 5487.043 | X29: =W29-f_roll*m_ET*g -> 3619.1415 | Y29: =X29/(P29*N29)/1000 -> 38.083077 | Z29: =X29/(m_ET*g) -> 0.28378746
A30: фреза | B30: T1 | C30: 0 | E30: холостой | F30: 0 | G30: 2.7 | H30: П2 | I30: 133 | J30: 1.7092 | K30: 0.0564 | L30: 8444.817 | M30: 2.694 | Q30: 0 | T30: =IF(E30="холостой","",IFERROR(1-AVERAGEIFS($L:$L,$B:$B,B30,$H:$H,H30,$E:$E,"холостой")/L30,"")) | V30: =(M30/3.6)^2 -> 0.56000278 | AB30: =(J30-P_aux)/(M30/3.6) -> 2.0434744
A31: фреза | B31: T1 | C31: 0 | E31: холостой | F31: 0 | G31: 2.7 | H31: П2 | I31: 133 | J31: 1.7095 | K31: 0.0576 | L31: 8445.033 | M31: 2.7 | Q31: 0 | T31: =IF(E31="холостой","",IFERROR(1-AVERAGEIFS($L:$L,$B:$B,B31,$H:$H,H31,$E:$E,"холостой")/L31,"")) | V31: =(M31/3.6)^2 -> 0.5625 | AB31: =(J31-P_aux)/(M31/3.6) -> 2.0393333
A32: фреза | B32: T1 | C32: 0 | E32: холостой | F32: 0 | G32: 2.7 | H32: П2 | I32: 133 | J32: 1.7086 | K32: 0.0581 | L32: 8445.283 | M32: 2.709 | Q32: 0 | T32: =IF(E32="холостой","",IFERROR(1-AVERAGEIFS($L:$L,$B:$B,B32,$H:$H,H32,$E:$E,"холостой")/L32,"")) | V32: =(M32/3.6)^2 -> 0.56625625 | AB32: =(J32-P_aux)/(M32/3.6) -> 2.0313621
A33: фреза | B33: T1 | C33: 0 | E33: холостой | F33: 0 | G33: 2.7 | H33: П2 | I33: 133 | J33: 1.7092 | K33: 0.057 | L33: 8445.683 | M33: 2.701 | Q33: 0 | T33: =IF(E33="холостой","",IFERROR(1-AVERAGEIFS($L:$L,$B:$B,B33,$H:$H,H33,$E:$E,"холостой")/L33,"")) | V33: =(M33/3.6)^2 -> 0.56291674 | AB33: =(J33-P_aux)/(M33/3.6) -> 2.0381785
A34: фреза | B34: T2 | C34: 0 | E34: холостой | F34: 0 | G34: 2.7 | H34: П2 | I34: 133 | J34: 1.7389 | K34: 0.038 | L34: 8445.233 | M34: 2.693 | Q34: 0 | T34: =IF(E34="холостой","",IFERROR(1-AVERAGEIFS($L:$L,$B:$B,B34,$H:$H,H34,$E:$E,"холостой")/L34,"")) | V34: =(M34/3.6)^2 -> 0.55958711 | AB34: =(J34-P_aux)/(M34/3.6) -> 2.0839361
A35: фреза | B35: T2 | C35: 0 | E35: холостой | F35: 0 | G35: 2.7 | H35: П2 | I35: 133 | J35: 1.7414 | K35: 0.039 | L35: 8443.667 | M35: 2.711 | Q35: 0 | T35: =IF(E35="холостой","",IFERROR(1-AVERAGEIFS($L:$L,$B:$B,B35,$H:$H,H35,$E:$E,"холостой")/L35,"")) | V35: =(M35/3.6)^2 -> 0.56709267 | AB35: =(J35-P_aux)/(M35/3.6) -> 2.0734194
A36: фреза | B36: T2 | C36: 0 | E36: холостой | F36: 0 | G36: 2.7 | H36: П2 | I36: 133 | J36: 1.7388 | K36: 0.039 | L36: 8444.867 | M36: 2.695 | Q36: 0 | T36: =IF(E36="холостой","",IFERROR(1-AVERAGEIFS($L:$L,$B:$B,B36,$H:$H,H36,$E:$E,"холостой")/L36,"")) | V36: =(M36/3.6)^2 -> 0.5604186 | AB36: =(J36-P_aux)/(M36/3.6) -> 2.082256
A37: фреза | B37: T2 | C37: 0 | E37: холостой | F37: 0 | G37: 2.7 | H37: П2 | I37: 133 | J37: 1.738 | K37: 0.039 | L37: 8444.533 | M37: 2.699 | Q37: 0 | T37: =IF(E37="холостой","",IFERROR(1-AVERAGEIFS($L:$L,$B:$B,B37,$H:$H,H37,$E:$E,"холостой")/L37,"")) | V37: =(M37/3.6)^2 -> 0.56208341 | AB37: =(J37-P_aux)/(M37/3.6) -> 2.078103
A38: фреза | B38: T1 | C38: 1 | D38: 1 | E38: рабочий | F38: 0.12 | G38: 2.7 | H38: П2 | I38: 134 | J38: 12.9278 | K38: 0.2612 | L38: 8480.05 | M38: 2.697 | N38: 0.1197 | O38: 0.005 | P38: 1.232 | Q38: 540 | R38: =IF(P38="","",0.1*P38*M38) -> 0.3322704 | S38: =IF(R38="","",J38/R38) -> 38.907468 | T38: =IF(E38="холостой","",IFERROR(1-AVERAGEIFS($L:$L,$B:$B,B38,$H:$H,H38,$E:$E,"холостой")/L38,"")) -> 0.0041091739 | U38: =IF(R38="","",3.6*J38/(P38*N38*M38)) -> 117.01494 | V38: =(M38/3.6)^2 -> 0.56125069 | AA38: =(J38-P_aux-c_move*M38/3.6-P_rot0)/(P38*N38*M38/3.6) -> 92.543951
A39: фреза | B39: T1 | C39: 2 | D39: 1 | E39: рабочий | F39: 0.08 | G39: 2.7 | H39: П2 | I39: 134 | J39: 10.0222 | K39: 0.2657 | L39: 8479.65 | M39: 2.689 | N39: 0.0833 | O39: 0.0041 | P39: 1.255 | Q39: 539.97 | R39: =IF(P39="","",0.1*P39*M39) -> 0.3374695 | S39: =IF(R39="","",J39/R39) -> 29.698091 | T39: =IF(E39="холостой","",IFERROR(1-AVERAGEIFS($L:$L,$B:$B,B39,$H:$H,H39,$E:$E,"холостой")/L39,"")) -> 0.004062196 | U39: =IF(R39="","",3.6*J39/(P39*N39*M39)) -> 128.34709 | V39: =(M39/3.6)^2 -> 0.557926 | AA39: =(J39-P_aux-c_move*M39/3.6-P_rot0)/(P39*N39*M39/3.6) -> 93.78323
A40: фреза | B40: T1 | C40: 3 | D40: 1 | E40: рабочий | F40: 0.16 | G40: 1.8 | H40: П1 | I40: 200 | J40: 12.6134 | K40: 0.2903 | L40: 12655.533 | M40: 1.797 | N40: 0.1603 | O40: 0.0047 | P40: 1.245 | Q40: 539.93 | R40: =IF(P40="","",0.1*P40*M40) -> 0.2237265 | S40: =IF(R40="","",J40/R40) -> 56.378659 | T40: =IF(E40="холостой","",IFERROR(1-AVERAGEIFS($L:$L,$B:$B,B40,$H:$H,H40,$E:$E,"холостой")/L40,"")) | U40: =IF(R40="","",3.6*J40/(P40*N40*M40)) -> 126.61458 | V40: =(M40/3.6)^2 -> 0.24916736 | AA40: =(J40-P_aux-c_move*M40/3.6-P_rot0)/(P40*N40*M40/3.6) -> 104.64255
A41: фреза | B41: T1 | C41: 4 | D41: 1 | E41: рабочий | F41: 0.08 | G41: 3.6 | H41: П3 | I41: 100 | J41: 11.8202 | K41: 0.2779 | L41: 6327.833 | M41: 3.577 | N41: 0.0821 | O41: 0.0047 | P41: 1.253 | Q41: 539.99 | R41: =IF(P41="","",0.1*P41*M41) -> 0.4481981 | S41: =IF(R41="","",J41/R41) -> 26.372713 | T41: =IF(E41="холостой","",IFERROR(1-AVERAGEIFS($L:$L,$B:$B,B41,$H:$H,H41,$E:$E,"холостой")/L41,"")) | U41: =IF(R41="","",3.6*J41/(P41*N41*M41)) -> 115.64162 | V41: =(M41/3.6)^2 -> 0.98726304 | AA41: =(J41-P_aux-c_move*M41/3.6-P_rot0)/(P41*N41*M41/3.6) -> 84.268199
A42: фреза | B42: T1 | C42: 5 | D42: 1 | E42: рабочий | F42: 0.12 | G42: 1.8 | H42: П1 | I42: 201 | J42: 9.9765 | K42: 0.2525 | L42: 12720.317 | M42: 1.791 | N42: 0.119 | O42: 0.0036 | P42: 1.247 | Q42: 539.97 | R42: =IF(P42="","",0.1*P42*M42) -> 0.2233377 | S42: =IF(R42="","",J42/R42) -> 44.670022 | T42: =IF(E42="холостой","",IFERROR(1-AVERAGEIFS($L:$L,$B:$B,B42,$H:$H,H42,$E:$E,"холостой")/L42,"")) | U42: =IF(R42="","",3.6*J42/(P42*N42*M42)) -> 135.1362 | V42: =(M42/3.6)^2 -> 0.24750625 | AA42: =(J42-P_aux-c_move*M42/3.6-P_rot0)/(P42*N42*M42/3.6) -> 105.53354
A43: фреза | B43: T1 | C43: 6 | D43: 1 | E43: рабочий | F43: 0.08 | G43: 1.8 | H43: П1 | I43: 201 | J43: 7.1492 | K43: 0.1728 | L43: 12719.533 | M43: 1.788 | N43: 0.0768 | O43: 0.0035 | P43: 1.266 | Q43: 539.98 | R43: =IF(P43="","",0.1*P43*M43) -> 0.2263608 | S43: =IF(R43="","",J43/R43) -> 31.583207 | T43: =IF(E43="холостой","",IFERROR(1-AVERAGEIFS($L:$L,$B:$B,B43,$H:$H,H43,$E:$E,"холостой")/L43,"")) | U43: =IF(R43="","",3.6*J43/(P43*N43*M43)) -> 148.04628 | V43: =(M43/3.6)^2 -> 0.24667778 | AA43: =(J43-P_aux-c_move*M43/3.6-P_rot0)/(P43*N43*M43/3.6) -> 102.82569
A44: фреза | B44: T1 | C44: 7 | D44: 1 | E44: рабочий | F44: 0.12 | G44: 3.6 | H44: П3 | I44: 100 | J44: 16.6278 | K44: 0.6554 | L44: 6270.867 | M44: 3.578 | N44: 0.122 | O44: 0.0045 | P44: 1.251 | Q44: 535.1 | R44: =IF(P44="","",0.1*P44*M44) -> 0.4476078 | S44: =IF(R44="","",J44/R44) -> 37.148146 | T44: =IF(E44="холостой","",IFERROR(1-AVERAGEIFS($L:$L,$B:$B,B44,$H:$H,H44,$E:$E,"холостой")/L44,"")) | U44: =IF(R44="","",3.6*J44/(P44*N44*M44)) -> 109.61748 | V44: =(M44/3.6)^2 -> 0.98781512 | AA44: =(J44-P_aux-c_move*M44/3.6-P_rot0)/(P44*N44*M44/3.6) -> 88.4731
A45: фреза | B45: T1 | C45: 8 | D45: 1 | E45: рабочий | F45: 0.16 | G45: 2.7 | H45: П2 | I45: 134 | J45: 16.2409 | K45: 0.5248 | L45: 8421.917 | M45: 2.681 | N45: 0.1581 | O45: 0.0022 | P45: 1.24 | Q45: 536.27 | R45: =IF(P45="","",0.1*P45*M45) -> 0.332444 | S45: =IF(R45="","",J45/R45) -> 48.85304 | T45: =IF(E45="холостой","",IFERROR(1-AVERAGEIFS($L:$L,$B:$B,B45,$H:$H,H45,$E:$E,"холостой")/L45,"")) -> -0.0027650474 | U45: =IF(R45="","",3.6*J45/(P45*N45*M45)) -> 111.24032 | V45: =(M45/3.6)^2 -> 0.55461119 | AA45: =(J45-P_aux-c_move*M45/3.6-P_rot0)/(P45*N45*M45/3.6) -> 92.785293
A46: фреза | B46: T1 | C46: 9 | D46: 2 | E46: рабочий | F46: 0.12 | G46: 1.8 | H46: П1 | I46: 201 | J46: 9.9434 | K46: 0.2385 | L46: 12720.283 | M46: 1.787 | N46: 0.1186 | O46: 0.0043 | P46: 1.249 | Q46: 540 | R46: =IF(P46="","",0.1*P46*M46) -> 0.2231963 | S46: =IF(R46="","",J46/R46) -> 44.550022 | T46: =IF(E46="холостой","",IFERROR(1-AVERAGEIFS($L:$L,$B:$B,B46,$H:$H,H46,$E:$E,"холостой")/L46,"")) | U46: =IF(R46="","",3.6*J46/(P46*N46*M46)) -> 135.22772 | V46: =(M46/3.6)^2 -> 0.24640193 | AA46: =(J46-P_aux-c_move*M46/3.6-P_rot0)/(P46*N46*M46/3.6) -> 105.53751
A47: фреза | B47: T1 | C47: 10 | D47: 2 | E47: рабочий | F47: 0.08 | G47: 3.6 | H47: П3 | I47: 100 | J47: 12.2048 | K47: 0.3449 | L47: 6328.85 | M47: 3.593 | N47: 0.0825 | O47: 0.0045 | P47: 1.246 | Q47: 540.05 | R47: =IF(P47="","",0.1*P47*M47) -> 0.4476878 | S47: =IF(R47="","",J47/R47) -> 27.261855 | T47: =IF(E47="холостой","",IFERROR(1-AVERAGEIFS($L:$L,$B:$B,B47,$H:$H,H47,$E:$E,"холостой")/L47,"")) | U47: =IF(R47="","",3.6*J47/(P47*N47*M47)) -> 118.96082 | V47: =(M47/3.6)^2 -> 0.99611489 | AA47: =(J47-P_aux-c_move*M47/3.6-P_rot0)/(P47*N47*M47/3.6) -> 87.614744
A48: фреза | B48: T1 | C48: 11 | D48: 2 | E48: рабочий | F48: 0.08 | G48: 1.8 | H48: П1 | I48: 201 | J48: 7.3719 | K48: 0.2891 | L48: 12721.383 | M48: 1.789 | N48: 0.0785 | O48: 0.0041 | P48: 1.218 | Q48: 540.06 | R48: =IF(P48="","",0.1*P48*M48) -> 0.2179002 | S48: =IF(R48="","",J48/R48) -> 33.831543 | T48: =IF(E48="холостой","",IFERROR(1-AVERAGEIFS($L:$L,$B:$B,B48,$H:$H,H48,$E:$E,"холостой")/L48,"")) | U48: =IF(R48="","",3.6*J48/(P48*N48*M48)) -> 155.15103 | V48: =(M48/3.6)^2 -> 0.24695378 | AA48: =(J48-P_aux-c_move*M48/3.6-P_rot0)/(P48*N48*M48/3.6) -> 109.1799
A49: фреза | B49: T1 | C49: 12 | D49: 2 | E49: рабочий | F49: 0.16 | G49: 2.7 | H49: П2 | I49: 133 | J49: 16.3447 | K49: 0.5072 | L49: 8388.6 | M49: 2.689 | N49: 0.159 | O49: 0.0047 | P49: 1.264 | Q49: 538.23 | R49: =IF(P49="","",0.1*P49*M49) -> 0.3398896 | S49: =IF(R49="","",J49/R49) -> 48.088262 | T49: =IF(E49="холостой","",IFERROR(1-AVERAGEIFS($L:$L,$B:$B,B49,$H:$H,H49,$E:$E,"холостой")/L49,"")) -> -0.0067477291 | U49: =IF(R49="","",3.6*J49/(P49*N49*M49)) -> 108.87908 | V49: =(M49/3.6)^2 -> 0.557926 | AA49: =(J49-P_aux-c_move*M49/3.6-P_rot0)/(P49*N49*M49/3.6) -> 90.90003
... A61: фреза | B61: T2 | C61: 25 | D61: 3 | E61: рабочий | F61: 0.12 | G61: 1.8 | H61: П1 | I61: 201 | J61: 9.8814 | K61: 0.3387 | L61: 12720.933 | M61: 1.794 | N61: 0.1196 | O61: 0.0043 | P61: 1.254 | Q61: 540.01 | R61: =IF(P61="","",0.1*P61*M61) -> 0.2249676 | S61: =IF(R61="","",J61/R61) -> 43.923658 | T61: =IF(E61="холостой","",IFERROR(1-AVERAGEIFS($L:$L,$B:$B,B61,$H:$H,H61,$E:$E,"холостой")/L61,"")) | U61: =IF(R61="","",3.6*J61/(P61*N61*M61)) -> 132.21168 | V61: =(M61/3.6)^2 -> 0.24833611 | AA61: =(J61-P_aux-c_move*M61/3.6-P_rot0)/(P61*N61*M61/3.6) -> 102.94797

Sheet Модели
A1: Имя | B1: Коэффициент | C1: Значение | D1: Ед. | E1: Формула / способ определения
A2: f_roll | B2: Коэффициент сопротивления передвижению | C2: =AVERAGE(Проходы!W2:W5)/(m_ET*g) -> 0.14646762 | D2: – | E2: по холостым проходам с культиватором (F_к/G)
A3: k_0 | B3: k0 – удельное сопротивление при v → 0 | C3: =INDEX(LINEST(Проходы!Y6:Y29,Проходы!V6:V29),1,2)*1000 -> 34579.423 | D3: Н/м² | E3: ЛИНЕЙН(k; v²)
A4: eps | B4: ε – скоростной коэффициент | C4: =INDEX(LINEST(Проходы!Y6:Y29,Проходы!V6:V29),1,1)*1000 -> 1989.1759 | D4: Н·с²/м⁴ | E4: ЛИНЕЙН(k; v²)
A5: R2_k | B5: R² модели k | C5: =INDEX(LINEST(Проходы!Y6:Y29,Проходы!V6:V29,TRUE(),TRUE()),3,1) -> 0.41971559 | D5: – | E5: ЛИНЕЙН, статистика
A6: phi_max | B6: φ_max кривой буксования | C6: 0.821404 | D6: – | E6: нелинейный МНК (Python, scipy.curve_fit); значение
A7: k_slip | B7: k_δ кривой буксования | C7: 6.745697 | D7: – | E7: нелинейный МНК (Python); значение
A8: c_move | B8: Удельная мощность передвижения с фрезой | C8: =AVERAGE(Проходы!AB30:AB37) -> 2.0587579 | D8: кВт·с/м | E8: (P − P_aux)/v по холостым проходам с фрезой на П2
A9: P_rot0 | B9: Мощность холостого вращения ротора сверх P_aux | C9: 0.9812 | D9: кВт | E9: опыт: холостое вращение ротора, ВОМ 540
A10: A_0 | B10: A0 | C10: =INDEX(LINEST(Проходы!AA38:AA61,Проходы!M38:N61),1,3) -> 125.55065 | D10: кДж/м³ | E10: ЛИНЕЙН(A; v, a)
A11: A_v | B11: Av | C11: =INDEX(LINEST(Проходы!AA38:AA61,Проходы!M38:N61),1,2) -> -10.273753 | D11: кДж/(м³·км/ч) | E11: ЛИНЕЙН(A; v, a)
A12: A_a | B12: Aa | C12: =INDEX(LINEST(Проходы!AA38:AA61,Проходы!M38:N61),1,1) -> -28.225668 | D12: кДж/(м³·м) | E12: ЛИНЕЙН(A; v, a)
A13: slip_till_meas | B13: Буксование с фрезой (среднее по проходам на П2) | C13: =AVERAGE(Проходы!T38:T61) -> 0.001754916 | D13: – | E13: справочно; δ = 1 − N0/N
A14: slip_till | B14: Буксование с фрезой, принятое в расчёте | C14: 0 | D14: – | E14: принято 0 (измеренное значение пренебрежимо мало)
A15: cv_P | B15: Коэффициент вариации мощности (медиана) | C15: 0.032418 | D15: – | E15: медиана s_P/P̄ по рабочим проходам
A16: turn_t | B16: Продолжительность разворота | C16: 32.194 | D16: с | E16: опыт
A17: turn_P | B17: Мощность на развороте | C17: 2.9974 | D17: кВт | E17: опыт

Sheet Опыт_режимы
A1: Машина | B1: a, м | C1: v, км/ч | D1: n | E1: P̄, кВт | F1: s_P | G1: Δ0,95 P | H1: e, кВт·ч/га | I1: s_e | J1: Δ0,95 e | K1: δ | L1: W0, га/ч
A2: культиватор | B2: 0.08 | C2: 3.6 | D2: =COUNTIFS(Проходы!$A$6:$A$61,$A2,Проходы!$F$6:$F$61,$B2,Проходы!$G$6:$G$61,$C2,Проходы!$E$6:$E$61,"рабочий") -> 3 | E2: =AVERAGEIFS(Проходы!$J$6:$J$61,Проходы!$A$6:$A$61,$A2,Проходы!$F$6:$F$61,$B2,Проходы!$G$6:$G$61,$C2,Проходы!$E$6:$E$61,"рабочий") -> 7.4258 | F2: =SQRT(SUMPRODUCT((Проходы!$A$6:$A$61=$A2)*(Проходы!$F$6:$F$61=$B2)*(Проходы!$G$6:$G$61=$C2)*(Проходы!$E$6:$E$61="рабочий")*(Проходы!$J$6:$J$61-E2)^2)/(D2-1)) -> 0.25319315 | G2: =TINV(0.05,D2-1)*F2/SQRT(D2) -> 0.62896665 | H2: =AVERAGEIFS(Проходы!$S$6:$S$61,Проходы!$A$6:$A$61,$A2,Проходы!$F$6:$F$61,$B2,Проходы!$G$6:$G$61,$C2,Проходы!$E$6:$E$61,"рабочий") -> 17.135508 | I2: =SQRT(SUMPRODUCT((Проходы!$A$6:$A$61=$A2)*(Проходы!$F$6:$F$61=$B2)*(Проходы!$G$6:$G$61=$C2)*(Проходы!$E$6:$E$61="рабочий")*(Проходы!$S$6:$S$61-H2)^2)/(D2-1)) -> 0.63760636 | J2: =TINV(0.05,D2-1)*I2/SQRT(D2) -> 1.583902 | K2: =IFERROR(AVERAGEIFS(Проходы!$T$6:$T$61,Проходы!$A$6:$A$61,$A2,Проходы!$F$6:$F$61,$B2,Проходы!$G$6:$G$61,$C2,Проходы!$E$6:$E$61,"рабочий"),"–") -> 0.060768364 | L2: =AVERAGEIFS(Проходы!$R$6:$R$61,Проходы!$A$6:$A$61,$A2,Проходы!$F$6:$F$61,$B2,Проходы!$G$6:$G$61,$C2,Проходы!$E$6:$E$61,"рабочий") -> 0.43339913
A3: культиватор | B3: 0.08 | C3: 4.5 | D3: =COUNTIFS(Проходы!$A$6:$A$61,$A3,Проходы!$F$6:$F$61,$B3,Проходы!$G$6:$G$61,$C3,Проходы!$E$6:$E$61,"рабочий") -> 3 | E3: =AVERAGEIFS(Проходы!$J$6:$J$61,Проходы!$A$6:$A$61,$A3,Проходы!$F$6:$F$61,$B3,Проходы!$G$6:$G$61,$C3,Проходы!$E$6:$E$61,"рабочий") -> 9.3814333 | F3: =SQRT(SUMPRODUCT((Проходы!$A$6:$A$61=$A3)*(Проходы!$F$6:$F$61=$B3)*(Проходы!$G$6:$G$61=$C3)*(Проходы!$E$6:$E$61="рабочий")*(Проходы!$J$6:$J$61-E3)^2)/(D3-1)) -> 0.18518867 | G3: =TINV(0.05,D3-1)*F3/SQRT(D3) -> 0.46003416 | H3: =AVERAGEIFS(Проходы!$S$6:$S$61,Проходы!$A$6:$A$61,$A3,Проходы!$F$6:$F$61,$B3,Проходы!$G$6:$G$61,$C3,Проходы!$E$6:$E$61,"рабочий") -> 17.305814 | I3: =SQRT(SUMPRODUCT((Проходы!$A$6:$A$61=$A3)*(Проходы!$F$6:$F$61=$B3)*(Проходы!$G$6:$G$61=$C3)*(Проходы!$E$6:$E$61="рабочий")*(Проходы!$S$6:$S$61-H3)^2)/(D3-1)) -> 0.38283058 | J3: =TINV(0.05,D3-1)*I3/SQRT(D3) -> 0.95100388 | K3: =IFERROR(AVERAGEIFS(Проходы!$T$6:$T$61,Проходы!$A$6:$A$61,$A3,Проходы!$F$6:$F$61,$B3,Проходы!$G$6:$G$61,$C3,Проходы!$E$6:$E$61,"рабочий"),"–") -> 0.062676065 | L3: =AVERAGEIFS(Проходы!$R$6:$R$61,Проходы!$A$6:$A$61,$A3,Проходы!$F$6:$F$61,$B3,Проходы!$G$6:$G$61,$C3,Проходы!$E$6:$E$61,"рабочий") -> 0.54211697
A4: культиватор | B4: 0.08 | C4: 5.4 | D4: =COUNTIFS(Проходы!$A$6:$A$61,$A4,Проходы!$F$6:$F$61,$B4,Проходы!$G$6:$G$61,$C4,Проходы!$E$6:$E$61,"рабочий") -> 3 | E4: =AVERAGEIFS(Проходы!$J$6:$J$61,Проходы!$A$6:$A$61,$A4,Проходы!$F$6:$F$61,$B4,Проходы!$G$6:$G$61,$C4,Проходы!$E$6:$E$61,"рабочий") -> 11.732533 | F4: =SQRT(SUMPRODUCT((Проходы!$A$6:$A$61=$A4)*(Проходы!$F$6:$F$61=$B4)*(Проходы!$G$6:$G$61=$C4)*(Проходы!$E$6:$E$61="рабочий")*(Проходы!$J$6:$J$61-E4)^2)/(D4-1)) -> 0.27634407 | G4: =TINV(0.05,D4-1)*F4/SQRT(D4) -> 0.68647672 | H4: =AVERAGEIFS(Проходы!$S$6:$S$61,Проходы!$A$6:$A$61,$A4,Проходы!$F$6:$F$61,$B4,Проходы!$G$6:$G$61,$C4,Проходы!$E$6:$E$61,"рабочий") -> 18.013256 | I4: =SQRT(SUMPRODUCT((Проходы!$A$6:$A$61=$A4)*(Проходы!$F$6:$F$61=$B4)*(Проходы!$G$6:$G$61=$C4)*(Проходы!$E$6:$E$61="рабочий")*(Проходы!$S$6:$S$61-H4)^2)/(D4-1)) -> 0.55814152 | J4: =TINV(0.05,D4-1)*I4/SQRT(D4) -> 1.3865004 | K4: =IFERROR(AVERAGEIFS(Проходы!$T$6:$T$61,Проходы!$A$6:$A$61,$A4,Проходы!$F$6:$F$61,$B4,Проходы!$G$6:$G$61,$C4,Проходы!$E$6:$E$61,"рабочий"),"–") -> 0.060036198 | L4: =AVERAGEIFS(Проходы!$R$6:$R$61,Проходы!$A$6:$A$61,$A4,Проходы!$F$6:$F$61,$B4,Проходы!$G$6:$G$61,$C4,Проходы!$E$6:$E$61,"рабочий") -> 0.65142663
A5: культиватор | B5: 0.11 | C5: 3.6 | D5: =COUNTIFS(Проходы!$A$6:$A$61,$A5,Проходы!$F$6:$F$61,$B5,Проходы!$G$6:$G$61,$C5,Проходы!$E$6:$E$61,"рабочий") -> 3 | E5: =AVERAGEIFS(Проходы!$J$6:$J$61,Проходы!$A$6:$A$61,$A5,Проходы!$F$6:$F$61,$B5,Проходы!$G$6:$G$61,$C5,Проходы!$E$6:$E$61,"рабочий") -> 9.8331333 | F5: =SQRT(SUMPRODUCT((Проходы!$A$6:$A$61=$A5)*(Проходы!$F$6:$F$61=$B5)*(Проходы!$G$6:$G$61=$C5)*(Проходы!$E$6:$E$61="рабочий")*(Проходы!$J$6:$J$61-E5)^2)/(D5-1)) -> 0.2602061 | G5: =TINV(0.05,D5-1)*F5/SQRT(D5) -> 0.64638778 | H5: =AVERAGEIFS(Проходы!$S$6:$S$61,Проходы!$A$6:$A$61,$A5,Проходы!$F$6:$F$61,$B5,Проходы!$G$6:$G$61,$C5,Проходы!$E$6:$E$61,"рабочий") -> 22.822871 | I5: =SQRT(SUMPRODUCT((Проходы!$A$6:$A$61=$A5)*(Проходы!$F$6:$F$61=$B5)*(Проходы!$G$6:$G$61=$C5)*(Проходы!$E$6:$E$61="рабочий")*(Проходы!$S$6:$S$61-H5)^2)/(D5-1)) -> 0.64793217 | J5: =TINV(0.05,D5-1)*I5/SQRT(D5) -> 1.6095527 | K5: =IFERROR(AVERAGEIFS(Проходы!$T$6:$T$61,Проходы!$A$6:$A$61,$A5,Проходы!$F$6:$F$61,$B5,Проходы!$G$6:$G$61,$C5,Проходы!$E$6:$E$61,"рабочий"),"–") -> 0.095196294 | L5: =AVERAGEIFS(Проходы!$R$6:$R$61,Проходы!$A$6:$A$61,$A5,Проходы!$F$6:$F$61,$B5,Проходы!$G$6:$G$61,$C5,Проходы!$E$6:$E$61,"рабочий") -> 0.43086237
A6: культиватор | B6: 0.11 | C6: 4.5 | D6: =COUNTIFS(Проходы!$A$6:$A$61,$A6,Проходы!$F$6:$F$61,$B6,Проходы!$G$6:$G$61,$C6,Проходы!$E$6:$E$61,"рабочий") -> 3 | E6: =AVERAGEIFS(Проходы!$J$6:$J$61,Проходы!$A$6:$A$61,$A6,Проходы!$F$6:$F$61,$B6,Проходы!$G$6:$G$61,$C6,Проходы!$E$6:$E$61,"рабочий") -> 12.0427 | F6: =SQRT(SUMPRODUCT((Проходы!$A$6:$A$61=$A6)*(Проходы!$F$6:$F$61=$B6)*(Проходы!$G$6:$G$61=$C6)*(Проходы!$E$6:$E$61="рабочий")*(Проходы!$J$6:$J$61-E6)^2)/(D6-1)) -> 0.043372918 | G6: =TINV(0.05,D6-1)*F6/SQRT(D6) -> 0.1077443 | H6: =AVERAGEIFS(Проходы!$S$6:$S$61,Проходы!$A$6:$A$61,$A6,Проходы!$F$6:$F$61,$B6,Проходы!$G$6:$G$61,$C6,Проходы!$E$6:$E$61,"рабочий") -> 22.354677 | I6: =SQRT(SUMPRODUCT((Проходы!$A$6:$A$61=$A6)*(Проходы!$F$6:$F$61=$B6)*(Проходы!$G$6:$G$61=$C6)*(Проходы!$E$6:$E$61="рабочий")*(Проходы!$S$6:$S$61-H6)^2)/(D6-1)) -> 0.11939176 | J6: =TINV(0.05,D6-1)*I6/SQRT(D6) -> 0.29658558 | K6: =IFERROR(AVERAGEIFS(Проходы!$T$6:$T$61,Проходы!$A$6:$A$61,$A6,Проходы!$F$6:$F$61,$B6,Проходы!$G$6:$G$61,$C6,Проходы!$E$6:$E$61,"рабочий"),"–") -> 0.087651443 | L6: =AVERAGEIFS(Проходы!$R$6:$R$61,Проходы!$A$6:$A$61,$A6,Проходы!$F$6:$F$61,$B6,Проходы!$G$6:$G$61,$C6,Проходы!$E$6:$E$61,"рабочий") -> 0.53871863
A7: культиватор | B7: 0.11 | C7: 5.4 | D7: =COUNTIFS(Проходы!$A$6:$A$61,$A7,Проходы!$F$6:$F$61,$B7,Проходы!$G$6:$G$61,$C7,Проходы!$E$6:$E$61,"рабочий") -> 3 | E7: =AVERAGEIFS(Проходы!$J$6:$J$61,Проходы!$A$6:$A$61,$A7,Проходы!$F$6:$F$61,$B7,Проходы!$G$6:$G$61,$C7,Проходы!$E$6:$E$61,"рабочий") -> 15.426467 | F7: =SQRT(SUMPRODUCT((Проходы!$A$6:$A$61=$A7)*(Проходы!$F$6:$F$61=$B7)*(Проходы!$G$6:$G$61=$C7)*(Проходы!$E$6:$E$61="рабочий")*(Проходы!$J$6:$J$61-E7)^2)/(D7-1)) -> 0.1530893 | G7: =TINV(0.05,D7-1)*F7/SQRT(D7) -> 0.3802949 | H7: =AVERAGEIFS(Проходы!$S$6:$S$61,Проходы!$A$6:$A$61,$A7,Проходы!$F$6:$F$61,$B7,Проходы!$G$6:$G$61,$C7,Проходы!$E$6:$E$61,"рабочий") -> 23.846566 | I7: =SQRT(SUMPRODUCT((Проходы!$A$6:$A$61=$A7)*(Проходы!$F$6:$F$61=$B7)*(Проходы!$G$6:$G$61=$C7)*(Проходы!$E$6:$E$61="рабочий")*(Проходы!$S$6:$S$61-H7)^2)/(D7-1)) -> 0.45081682 | J7: =TINV(0.05,D7-1)*I7/SQRT(D7) -> 1.1198911 | K7: =IFERROR(AVERAGEIFS(Проходы!$T$6:$T$61,Проходы!$A$6:$A$61,$A7,Проходы!$F$6:$F$61,$B7,Проходы!$G$6:$G$61,$C7,Проходы!$E$6:$E$61,"рабочий"),"–") -> 0.10290011 | L7: =AVERAGEIFS(Проходы!$R$6:$R$61,Проходы!$A$6:$A$61,$A7,Проходы!$F$6:$F$61,$B7,Проходы!$G$6:$G$61,$C7,Проходы!$E$6:$E$61,"рабочий") -> 0.646982
A8: культиватор | B8: 0.14 | C8: 3.6 | D8: =COUNTIFS(Проходы!$A$6:$A$61,$A8,Проходы!$F$6:$F$61,$B8,Проходы!$G$6:$G$61,$C8,Проходы!$E$6:$E$61,"рабочий") -> 3 | E8: =AVERAGEIFS(Проходы!$J$6:$J$61,Проходы!$A$6:$A$61,$A8,Проходы!$F$6:$F$61,$B8,Проходы!$G$6:$G$61,$C8,Проходы!$E$6:$E$61,"рабочий") -> 12.0999 | F8: =SQRT(SUMPRODUCT((Проходы!$A$6:$A$61=$A8)*(Проходы!$F$6:$F$61=$B8)*(Проходы!$G$6:$G$61=$C8)*(Проходы!$E$6:$E$61="рабочий")*(Проходы!$J$6:$J$61-E8)^2)/(D8-1)) -> 0.14945304 | G8: =TINV(0.05,D8-1)*F8/SQRT(D8) -> 0.37126192 | H8: =AVERAGEIFS(Проходы!$S$6:$S$61,Проходы!$A$6:$A$61,$A8,Проходы!$F$6:$F$61,$B8,Проходы!$G$6:$G$61,$C8,Проходы!$E$6:$E$61,"рабочий") -> 28.103137 | I8: =SQRT(SUMPRODUCT((Проходы!$A$6:$A$61=$A8)*(Проходы!$F$6:$F$61=$B8)*(Проходы!$G$6:$G$61=$C8)*(Проходы!$E$6:$E$61="рабочий")*(Проходы!$S$6:$S$61-H8)^2)/(D8-1)) -> 0.28785801 | J8: =TINV(0.05,D8-1)*I8/SQRT(D8) -> 0.71507893 | K8: =IFERROR(AVERAGEIFS(Проходы!$T$6:$T$61,Проходы!$A$6:$A$61,$A8,Проходы!$F$6:$F$61,$B8,Проходы!$G$6:$G$61,$C8,Проходы!$E$6:$E$61,"рабочий"),"–") -> 0.13243943 | L8: =AVERAGEIFS(Проходы!$R$6:$R$61,Проходы!$A$6:$A$61,$A8,Проходы!$F$6:$F$61,$B8,Проходы!$G$6:$G$61,$C8,Проходы!$E$6:$E$61,"рабочий") -> 0.43056667
A9: культиватор | B9: 0.14 | C9: 4.5 | D9: =COUNTIFS(Проходы!$A$6:$A$61,$A9,Проходы!$F$6:$F$61,$B9,Проходы!$G$6:$G$61,$C9,Проходы!$E$6:$E$61,"рабочий") -> 3 | E9: =AVERAGEIFS(Проходы!$J$6:$J$61,Проходы!$A$6:$A$61,$A9,Проходы!$F$6:$F$61,$B9,Проходы!$G$6:$G$61,$C9,Проходы!$E$6:$E$61,"рабочий") -> 15.5144 | F9: =SQRT(SUMPRODUCT((Проходы!$A$6:$A$61=$A9)*(Проходы!$F$6:$F$61=$B9)*(Проходы!$G$6:$G$61=$C9)*(Проходы!$E$6:$E$61="рабочий")*(Проходы!$J$6:$J$61-E9)^2)/(D9-1)) -> 0.54814269 | G9: =TINV(0.05,D9-1)*F9/SQRT(D9) -> 1.3616619 | H9: =AVERAGEIFS(Проходы!$S$6:$S$61,Проходы!$A$6:$A$61,$A9,Проходы!$F$6:$F$61,$B9,Проходы!$G$6:$G$61,$C9,Проходы!$E$6:$E$61,"рабочий") -> 29.047224 | I9: =SQRT(SUMPRODUCT((Проходы!$A$6:$A$61=$A9)*(Проходы!$F$6:$F$61=$B9)*(Проходы!$G$6:$G$61=$C9)*(Проходы!$E$6:$E$61="рабочий")*(Проходы!$S$6:$S$61-H9)^2)/(D9-1)) -> 1.4389659 | J9: =TINV(0.05,D9-1)*I9/SQRT(D9) -> 3.5745894 | K9: =IFERROR(AVERAGEIFS(Проходы!$T$6:$T$61,Проходы!$A$6:$A$61,$A9,Проходы!$F$6:$F$61,$B9,Проходы!$G$6:$G$61,$C9,Проходы!$E$6:$E$61,"рабочий"),"–") -> 0.13719373 | L9: =AVERAGEIFS(Проходы!$R$6:$R$61,Проходы!$A$6:$A$61,$A9,Проходы!$F$6:$F$61,$B9,Проходы!$G$6:$G$61,$C9,Проходы!$E$6:$E$61,"рабочий") -> 0.53436867
A10: фреза | B10: 0.08 | C10: 1.8 | D10: =COUNTIFS(Проходы!$A$6:$A$61,$A10,Проходы!$F$6:$F$61,$B10,Проходы!$G$6:$G$61,$C10,Проходы!$E$6:$E$61,"рабочий") -> 3 | E10: =AVERAGEIFS(Проходы!$J$6:$J$61,Проходы!$A$6:$A$61,$A10,Проходы!$F$6:$F$61,$B10,Проходы!$G$6:$G$61,$C10,Проходы!$E$6:$E$61,"рабочий") -> 7.3030333 | F10: =SQRT(SUMPRODUCT((Проходы!$A$6:$A$61=$A10)*(Проходы!$F$6:$F$61=$B10)*(Проходы!$G$6:$G$61=$C10)*(Проходы!$E$6:$E$61="рабочий")*(Проходы!$J$6:$J$61-E10)^2)/(D10-1)) -> 0.13346656 | G10: =TINV(0.05,D10-1)*F10/SQRT(D10) -> 0.33154932 | H10: =AVERAGEIFS(Проходы!$S$6:$S$61,Проходы!$A$6:$A$61,$A10,Проходы!$F$6:$F$61,$B10,Проходы!$G$6:$G$61,$C10,Проходы!$E$6:$E$61,"рабочий") -> 32.779661 | I10: =SQRT(SUMPRODUCT((Проходы!$A$6:$A$61=$A10)*(Проходы!$F$6:$F$61=$B10)*(Проходы!$G$6:$G$61=$C10)*(Проходы!$E$6:$E$61="рабочий")*(Проходы!$S$6:$S$61-H10)^2)/(D10-1)) -> 1.1311186 | J10: =TINV(0.05,D10-1)*I10/SQRT(D10) -> 2.8098544 | K10: =IFERROR(AVERAGEIFS(Проходы!$T$6:$T$61,Проходы!$A$6:$A$61,$A10,Проходы!$F$6:$F$61,$B10,Проходы!$G$6:$G$61,$C10,Проходы!$E$6:$E$61,"рабочий"),"–") -> – | L10: =AVERAGEIFS(Проходы!$R$6:$R$61,Проходы!$A$6:$A$61,$A10,Проходы!$F$6:$F$61,$B10,Проходы!$G$6:$G$61,$C10,Проходы!$E$6:$E$61,"рабочий") -> 0.222885
A11: фреза | B11: 0.08 | C11: 2.7 | D11: =COUNTIFS(Проходы!$A$6:$A$61,$A11,Проходы!$F$6:$F$61,$B11,Проходы!$G$6:$G$61,$C11,Проходы!$E$6:$E$61,"рабочий") -> 3 | E11: =AVERAGEIFS(Проходы!$J$6:$J$61,Проходы!$A$6:$A$61,$A11,Проходы!$F$6:$F$61,$B11,Проходы!$G$6:$G$61,$C11,Проходы!$E$6:$E$61,"рабочий") -> 9.7834333 | F11: =SQRT(SUMPRODUCT((Проходы!$A$6:$A$61=$A11)*(Проходы!$F$6:$F$61=$B11)*(Проходы!$G$6:$G$61=$C11)*(Проходы!$E$6:$E$61="рабочий")*(Проходы!$J$6:$J$61-E11)^2)/(D11-1)) -> 0.20759061 | G11: =TINV(0.05,D11-1)*F11/SQRT(D11) -> 0.51568367 | H11: =AVERAGEIFS(Проходы!$S$6:$S$61,Проходы!$A$6:$A$61,$A11,Проходы!$F$6:$F$61,$B11,Проходы!$G$6:$G$61,$C11,Проходы!$E$6:$E$61,"рабочий") -> 29.151814 | I11: =SQRT(SUMPRODUCT((Проходы!$A$6:$A$61=$A11)*(Проходы!$F$6:$F$61=$B11)*(Проходы!$G$6:$G$61=$C11)*(Проходы!$E$6:$E$61="рабочий")*(Проходы!$S$6:$S$61-H11)^2)/(D11-1)) -> 0.48027074 | J11: =TINV(0.05,D11-1)*I11/SQRT(D11) -> 1.1930586 | K11: =IFERROR(AVERAGEIFS(Проходы!$T$6:$T$61,Проходы!$A$6:$A$61,$A11,Проходы!$F$6:$F$61,$B11,Проходы!$G$6:$G$61,$C11,Проходы!$E$6:$E$61,"рабочий"),"–") -> 0.0041012486 | L11: =AVERAGEIFS(Проходы!$R$6:$R$61,Проходы!$A$6:$A$61,$A11,Проходы!$F$6:$F$61,$B11,Проходы!$G$6:$G$61,$C11,Проходы!$E$6:$E$61,"рабочий") -> 0.33558587
A12: фреза | B12: 0.08 | C12: 3.6 | D12: =COUNTIFS(Проходы!$A$6:$A$61,$A12,Проходы!$F$6:$F$61,$B12,Проходы!$G$6:$G$61,$C12,Проходы!$E$6:$E$61,"рабочий") -> 3 | E12: =AVERAGEIFS(Проходы!$J$6:$J$61,Проходы!$A$6:$A$61,$A12,Проходы!$F$6:$F$61,$B12,Проходы!$G$6:$G$61,$C12,Проходы!$E$6:$E$61,"рабочий") -> 11.939833 | F12: =SQRT(SUMPRODUCT((Проходы!$A$6:$A$61=$A12)*(Проходы!$F$6:$F$61=$B12)*(Проходы!$G$6:$G$61=$C12)*(Проходы!$E$6:$E$61="рабочий")*(Проходы!$J$6:$J$61-E12)^2)/(D12-1)) -> 0.22982738 | G12: =TINV(0.05,D12-1)*F12/SQRT(D12) -> 0.57092286 | H12: =AVERAGEIFS(Проходы!$S$6:$S$61,Проходы!$A$6:$A$61,$A12,Проходы!$F$6:$F$61,$B12,Проходы!$G$6:$G$61,$C12,Проходы!$E$6:$E$61,"рабочий") -> 26.720254 | I12: =SQRT(SUMPRODUCT((Проходы!$A$6:$A$61=$A12)*(Проходы!$F$6:$F$61=$B12)*(Проходы!$G$6:$G$61=$C12)*(Проходы!$E$6:$E$61="рабочий")*(Проходы!$S$6:$S$61-H12)^2)/(D12-1)) -> 0.47527698 | J12: =TINV(0.05,D12-1)*I12/SQRT(D12) -> 1.1806535 | K12: =IFERROR(AVERAGEIFS(Проходы!$T$6:$T$61,Проходы!$A$6:$A$61,$A12,Проходы!$F$6:$F$61,$B12,Проходы!$G$6:$G$61,$C12,Проходы!$E$6:$E$61,"рабочий"),"–") -> – | L12: =AVERAGEIFS(Проходы!$R$6:$R$61,Проходы!$A$6:$A$61,$A12,Проходы!$F$6:$F$61,$B12,Проходы!$G$6:$G$61,$C12,Проходы!$E$6:$E$61,"рабочий") -> 0.44684063
A13: фреза | B13: 0.12 | C13: 1.8 | D13: =COUNTIFS(Проходы!$A$6:$A$61,$A13,Проходы!$F$6:$F$61,$B13,Проходы!$G$6:$G$61,$C13,Проходы!$E$6:$E$61,"рабочий") -> 3 | E13: =AVERAGEIFS(Проходы!$J$6:$J$61,Проходы!$A$6:$A$61,$A13,Проходы!$F$6:$F$61,$B13,Проходы!$G$6:$G$61,$C13,Проходы!$E$6:$E$61,"рабочий") -> 9.9337667 | F13: =SQRT(SUMPRODUCT((Проходы!$A$6:$A$61=$A13)*(Проходы!$F$6:$F$61=$B13)*(Проходы!$G$6:$G$61=$C13)*(Проходы!$E$6:$E$61="рабочий")*(Проходы!$J$6:$J$61-E13)^2)/(D13-1)) -> 0.048276323 | G13: =TINV(0.05,D13-1)*F13/SQRT(D13) -> 0.11992503 | H13: =AVERAGEIFS(Проходы!$S$6:$S$61,Проходы!$A$6:$A$61,$A13,Проходы!$F$6:$F$61,$B13,Проходы!$G$6:$G$61,$C13,Проходы!$E$6:$E$61,"рабочий") -> 44.381234 | I13: =SQRT(SUMPRODUCT((Проходы!$A$6:$A$61=$A13)*(Проходы!$F$6:$F$61=$B13)*(Проходы!$G$6:$G$61=$C13)*(Проходы!$E$6:$E$61="рабочий")*(Проходы!$S$6:$S$61-H13)^2)/(D13-1)) -> 0.40078881 | J13: =TINV(0.05,D13-1)*I13/SQRT(D13) -> 0.9956146 | K13: =IFERROR(AVERAGEIFS(Проходы!$T$6:$T$61,Проходы!$A$6:$A$61,$A13,Проходы!$F$6:$F$61,$B13,Проходы!$G$6:$G$61,$C13,Проходы!$E$6:$E$61,"рабочий"),"–") -> – | L13: =AVERAGEIFS(Проходы!$R$6:$R$61,Проходы!$A$6:$A$61,$A13,Проходы!$F$6:$F$61,$B13,Проходы!$G$6:$G$61,$C13,Проходы!$E$6:$E$61,"рабочий") -> 0.22383387
... A17: фреза | B17: 0.16 | C17: 2.7 | D17: =COUNTIFS(Проходы!$A$6:$A$61,$A17,Проходы!$F$6:$F$61,$B17,Проходы!$G$6:$G$61,$C17,Проходы!$E$6:$E$61,"рабочий") -> 3 | E17: =AVERAGEIFS(Проходы!$J$6:$J$61,Проходы!$A$6:$A$61,$A17,Проходы!$F$6:$F$61,$B17,Проходы!$G$6:$G$61,$C17,Проходы!$E$6:$E$61,"рабочий") -> 16.266967 | F17: =SQRT(SUMPRODUCT((Проходы!$A$6:$A$61=$A17)*(Проходы!$F$6:$F$61=$B17)*(Проходы!$G$6:$G$61=$C17)*(Проходы!$E$6:$E$61="рабочий")*(Проходы!$J$6:$J$61-E17)^2)/(D17-1)) -> 0.068525129 | G17: =TINV(0.05,D17-1)*F17/SQRT(D17) -> 0.17022586 | H17: =AVERAGEIFS(Проходы!$S$6:$S$61,Проходы!$A$6:$A$61,$A17,Проходы!$F$6:$F$61,$B17,Проходы!$G$6:$G$61,$C17,Проходы!$E$6:$E$61,"рабочий") -> 48.361859 | I17: =SQRT(SUMPRODUCT((Проходы!$A$6:$A$61=$A17)*(Проходы!$F$6:$F$61=$B17)*(Проходы!$G$6:$G$61=$C17)*(Проходы!$E$6:$E$61="рабочий")*(Проходы!$S$6:$S$61-H17)^2)/(D17-1)) -> 0.42629623 | J17: =TINV(0.05,D17-1)*I17/SQRT(D17) -> 1.0589785 | K17: =IFERROR(AVERAGEIFS(Проходы!$T$6:$T$61,Проходы!$A$6:$A$61,$A17,Проходы!$F$6:$F$61,$B17,Проходы!$G$6:$G$61,$C17,Проходы!$E$6:$E$61,"рабочий"),"–") -> -0.0028157309 | L17: =AVERAGEIFS(Проходы!$R$6:$R$61,Проходы!$A$6:$A$61,$A17,Проходы!$F$6:$F$61,$B17,Проходы!$G$6:$G$61,$C17,Проходы!$E$6:$E$61,"рабочий") -> 0.33638

Sheet Энергетика
A1: Машина | B1: a, м | C1: v, км/ч | D1: B, м | E1: v, м/с | F1: A, кДж/м³ (фреза) | G1: R, Н | H1: φ ЭТ | I1: δ ЭТ | J1: φ Д | K1: δ Д | L1: P_эл ЭТ, кВт | M1: P_вх ЭТ, кВт | N1: P_вх Д, кВт | O1: Запас мощности ЭТ | P1: Запас мощности Д | Q1: Допустим ЭТ | R1: Допустим Д | S1: Длительный ЭТ | T1: Q Д, л/ч | U1: X Д
A2: =Опыт_режимы!A2 -> культиватор | B2: =Опыт_режимы!B2 -> 0.08 | C2: =Опыт_режимы!C2 -> 3.6 | D2: =IF(A2="культиватор",1.2,1.25) -> 1.2 | E2: =C2/3.6 -> 1 | F2: =IF(A2="культиватор","",A_0+A_v*C2+A_a*B2) | G2: =IF(A2="культиватор",D2*B2*(k_0+eps*E2^2),"") -> 3510.5855 | H2: =IF(A2="культиватор",G2/(m_ET*g),"") -> 0.27527527 | I2: =IF(A2="культиватор",-LN(1-H2/phi_max)/k_slip,slip_till) -> 0.060506771 | J2: =IF(A2="культиватор",G2/(m_D*g),"") -> 0.31391039 | K2: =IF(A2="культиватор",-LN(1-J2/phi_max)/k_slip,slip_till) -> 0.071383424 | L2: =IF(A2="культиватор",P_aux+M2/eta_ep,P_aux+c_move*E2+P_rot0+F2*D2*B2*E2) -> 7.5726667 | M2: =IF(A2="культиватор",(G2+f_roll*m_ET*g)*E2/(1-I2)/eta_tr/1000,eta_ep*(L2-P_aux)) -> 6.5055467 | N2: =IF(A2="культиватор",(G2+f_roll*m_D*g)*E2/(1-K2)/eta_tr/1000,eta_ep*(c_move*E2*m_D/m_ET+P_rot0+F2*D2*B2*E2))+P_hyd_idle_D -> 6.4504175 | O2: =1-L2*(1+2*cv_P)/P_el_lim -> 0.53922011 | P2: =1-N2*(1+2*cv_P)/P_pto_nom -> 0.58522725 | Q2: =AND(O2>=0,I2<=slip_max) -> TRUE | R2: =AND(P2>=0,K2<=slip_max) -> TRUE | S2: =AND(Q2,M2<=P_mot_1h) -> TRUE | T2: =k_D*(sfc_a*N2+sfc_b*P_pto_nom) -> 3.0088518 | U2: =N2/P_pto_nom -> 0.38951796
A3: =Опыт_режимы!A3 -> культиватор | B3: =Опыт_режимы!B3 -> 0.08 | C3: =Опыт_режимы!C3 -> 4.5 | D3: =IF(A3="культиватор",1.2,1.25) -> 1.2 | E3: =C3/3.6 -> 1.25 | F3: =IF(A3="культиватор","",A_0+A_v*C3+A_a*B3) | G3: =IF(A3="культиватор",D3*B3*(k_0+eps*E3^2),"") -> 3618.001 | H3: =IF(A3="культиватор",G3/(m_ET*g),"") -> 0.28369803 | I3: =IF(A3="культиватор",-LN(1-H3/phi_max)/k_slip,slip_till) -> 0.062810882 | J3: =IF(A3="культиватор",G3/(m_D*g),"") -> 0.3235153 | K3: =IF(A3="культиватор",-LN(1-J3/phi_max)/k_slip,slip_till) -> 0.074215979 | L3: =IF(A3="культиватор",P_aux+M3/eta_ep,P_aux+c_move*E3+P_rot0+F3*D3*B3*E3) -> 9.6285577 | M3: =IF(A3="культиватор",(G3+f_roll*m_ET*g)*E3/(1-I3)/eta_tr/1000,eta_ep*(L3-P_aux)) -> 8.3147308 | N3: =IF(A3="культиватор",(G3+f_roll*m_D*g)*E3/(1-K3)/eta_tr/1000,eta_ep*(c_move*E3*m_D/m_ET+P_rot0+F3*D3*B3*E3))+P_hyd_idle_D -> 8.2144284 | O3: =1-L3*(1+2*cv_P)/P_el_lim -> 0.41412372 | P3: =1-N3*(1+2*cv_P)/P_pto_nom -> 0.47179836 | Q3: =AND(O3>=0,I3<=slip_max) -> TRUE | R3: =AND(P3>=0,K3<=slip_max) -> TRUE | S3: =AND(Q3,M3<=P_mot_1h) -> TRUE | T3: =k_D*(sfc_a*N3+sfc_b*P_pto_nom) -> 3.3969343 | U3: =N3/P_pto_nom -> 0.49604036
A4: =Опыт_режимы!A4 -> культиватор | B4: =Опыт_режимы!B4 -> 0.08 | C4: =Опыт_режимы!C4 -> 5.4 | D4: =IF(A4="культиватор",1.2,1.25) -> 1.2 | E4: =C4/3.6 -> 1.5 | F4: =IF(A4="культиватор","",A_0+A_v*C4+A_a*B4) | G4: =IF(A4="культиватор",D4*B4*(k_0+eps*E4^2),"") -> 3749.2866 | H4: =IF(A4="культиватор",G4/(m_ET*g),"") -> 0.29399252 | I4: =IF(A4="культиватор",-LN(1-H4/phi_max)/k_slip,slip_till) -> 0.065676538 | J4: =IF(A4="культиватор",G4/(m_D*g),"") -> 0.33525462 | K4: =IF(A4="культиватор",-LN(1-J4/phi_max)/k_slip,slip_till) -> 0.077753142 | L4: =IF(A4="культиватор",P_aux+M4/eta_ep,P_aux+c_move*E4+P_rot0+F4*D4*B4*E4) -> 11.825218 | M4: =IF(A4="культиватор",(G4+f_roll*m_ET*g)*E4/(1-I4)/eta_tr/1000,eta_ep*(L4-P_aux)) -> 10.247792 | N4: =IF(A4="культиватор",(G4+f_roll*m_D*g)*E4/(1-K4)/eta_tr/1000,eta_ep*(c_move*E4*m_D/m_ET+P_rot0+F4*D4*B4*E4))+P_hyd_idle_D -> 10.107079 | O4: =1-L4*(1+2*cv_P)/P_el_lim -> 0.28046183 | P4: =1-N4*(1+2*cv_P)/P_pto_nom -> 0.35009772 | Q4: =AND(O4>=0,I4<=slip_max) -> TRUE | R4: =AND(P4>=0,K4<=slip_max) -> TRUE | S4: =AND(Q4,M4<=P_mot_1h) -> TRUE | T4: =k_D*(sfc_a*N4+sfc_b*P_pto_nom) -> 3.8133174 | U4: =N4/P_pto_nom -> 0.61033087
A5: =Опыт_режимы!A5 -> культиватор | B5: =Опыт_режимы!B5 -> 0.11 | C5: =Опыт_режимы!C5 -> 3.6 | D5: =IF(A5="культиватор",1.2,1.25) -> 1.2 | E5: =C5/3.6 -> 1 | F5: =IF(A5="культиватор","",A_0+A_v*C5+A_a*B5) | G5: =IF(A5="культиватор",D5*B5*(k_0+eps*E5^2),"") -> 4827.055 | H5: =IF(A5="культиватор",G5/(m_ET*g),"") -> 0.37850349 | I5: =IF(A5="культиватор",-LN(1-H5/phi_max)/k_slip,slip_till) -> 0.091565024 | J5: =IF(A5="культиватор",G5/(m_D*g),"") -> 0.43162679 | K5: =IF(A5="культиватор",-LN(1-J5/phi_max)/k_slip,slip_till) -> 0.11050596 | L5: =IF(A5="культиватор",P_aux+M5/eta_ep,P_aux+c_move*E5+P_rot0+F5*D5*B5*E5) -> 9.6967481 | M5: =IF(A5="культиватор",(G5+f_roll*m_ET*g)*E5/(1-I5)/eta_tr/1000,eta_ep*(L5-P_aux)) -> 8.3747383 | N5: =IF(A5="культиватор",(G5+f_roll*m_D*g)*E5/(1-K5)/eta_tr/1000,eta_ep*(c_move*E5*m_D/m_ET+P_rot0+F5*D5*B5*E5))+P_hyd_idle_D -> 8.4093698 | O5: =1-L5*(1+2*cv_P)/P_el_lim -> 0.40997449 | P5: =1-N5*(1+2*cv_P)/P_pto_nom -> 0.4592633 | Q5: =AND(O5>=0,I5<=slip_max) -> TRUE | R5: =AND(P5>=0,K5<=slip_max) -> TRUE | S5: =AND(Q5,M5<=P_mot_1h) -> TRUE | T5: =k_D*(sfc_a*N5+sfc_b*P_pto_nom) -> 3.4398214 | U5: =N5/P_pto_nom -> 0.50781219
A6: =Опыт_режимы!A6 -> культиватор | B6: =Опыт_режимы!B6 -> 0.11 | C6: =Опыт_режимы!C6 -> 4.5 | D6: =IF(A6="культиватор",1.2,1.25) -> 1.2 | E6: =C6/3.6 -> 1.25 | F6: =IF(A6="культиватор","",A_0+A_v*C6+A_a*B6) | G6: =IF(A6="культиватор",D6*B6*(k_0+eps*E6^2),"") -> 4974.7513 | H6: =IF(A6="культиватор",G6/(m_ET*g),"") -> 0.39008479 | I6: =IF(A6="культиватор",-LN(1-H6/phi_max)/k_slip,slip_till) -> 0.095492968 | J6: =IF(A6="культиватор",G6/(m_D*g),"") -> 0.44483353 | K6: =IF(A6="культиватор",-LN(1-J6/phi_max)/k_slip,slip_till) -> 0.11561591 | L6: =IF(A6="культиватор",P_aux+M6/eta_ep,P_aux+c_move*E6+P_rot0+F6*D6*B6*E6) -> 12.391169 | M6: =IF(A6="культиватор",(G6+f_roll*m_ET*g)*E6/(1-I6)/eta_tr/1000,eta_ep*(L6-P_aux)) -> 10.745828 | N6: =IF(A6="культиватор",(G6+f_roll*m_D*g)*E6/(1-K6)/eta_tr/1000,eta_ep*(c_move*E6*m_D/m_ET+P_rot0+F6*D6*B6*E6))+P_hyd_idle_D -> 10.771088 | O6: =1-L6*(1+2*cv_P)/P_el_lim -> 0.246025 | P6: =1-N6*(1+2*cv_P)/P_pto_nom -> 0.30740084 | Q6: =AND(O6>=0,I6<=slip_max) -> TRUE | R6: =AND(P6>=0,K6<=slip_max) -> TRUE | S6: =AND(Q6,M6<=P_mot_1h) -> TRUE | T6: =k_D*(sfc_a*N6+sfc_b*P_pto_nom) -> 3.9593993 | U6: =N6/P_pto_nom -> 0.65042801
A7: =Опыт_режимы!A7 -> культиватор | B7: =Опыт_режимы!B7 -> 0.11 | C7: =Опыт_режимы!C7 -> 5.4 | D7: =IF(A7="культиватор",1.2,1.25) -> 1.2 | E7: =C7/3.6 -> 1.5 | F7: =IF(A7="культиватор","",A_0+A_v*C7+A_a*B7) | G7: =IF(A7="культиватор",D7*B7*(k_0+eps*E7^2),"") -> 5155.269 | H7: =IF(A7="культиватор",G7/(m_ET*g),"") -> 0.40423971 | I7: =IF(A7="культиватор",-LN(1-H7/phi_max)/k_slip,slip_till) -> 0.10043958 | J7: =IF(A7="культиватор",G7/(m_D*g),"") -> 0.46097511 | K7: =IF(A7="культиватор",-LN(1-J7/phi_max)/k_slip,slip_till) -> 0.12211049 | L7: =IF(A7="культиватор",P_aux+M7/eta_ep,P_aux+c_move*E7+P_rot0+F7*D7*B7*E7) -> 15.302681 | M7: =IF(A7="культиватор",(G7+f_roll*m_ET*g)*E7/(1-I7)/eta_tr/1000,eta_ep*(L7-P_aux)) -> 13.307959 | N7: =IF(A7="культиватор",(G7+f_roll*m_D*g)*E7/(1-K7)/eta_tr/1000,eta_ep*(c_move*E7*m_D/m_ET+P_rot0+F7*D7*B7*E7))+P_hyd_idle_D -> 13.340095 | O7: =1-L7*(1+2*cv_P)/P_el_lim -> 0.068865962 | P7: =1-N7*(1+2*cv_P)/P_pto_nom -> 0.14220933 | Q7: =AND(O7>=0,I7<=slip_max) -> TRUE | R7: =AND(P7>=0,K7<=slip_max) -> TRUE | S7: =AND(Q7,M7<=P_mot_1h) -> FALSE | T7: =k_D*(sfc_a*N7+sfc_b*P_pto_nom) -> 4.5245809 | U7: =N7/P_pto_nom -> 0.8055613
A8: =Опыт_режимы!A8 -> культиватор | B8: =Опыт_режимы!B8 -> 0.14 | C8: =Опыт_режимы!C8 -> 3.6 | D8: =IF(A8="культиватор",1.2,1.25) -> 1.2 | E8: =C8/3.6 -> 1 | F8: =IF(A8="культиватор","",A_0+A_v*C8+A_a*B8) | G8: =IF(A8="культиватор",D8*B8*(k_0+eps*E8^2),"") -> 6143.5245 | H8: =IF(A8="культиватор",G8/(m_ET*g),"") -> 0.48173171 | I8: =IF(A8="культиватор",-LN(1-H8/phi_max)/k_slip,slip_till) -> 0.13090327 | J8: =IF(A8="культиватор",G8/(m_D*g),"") -> 0.54934318 | K8: =IF(A8="культиватор",-LN(1-J8/phi_max)/k_slip,slip_till) -> 0.16380656 | L8: =IF(A8="культиватор",P_aux+M8/eta_ep,P_aux+c_move*E8+P_rot0+F8*D8*B8*E8) -> 12.083546 | M8: =IF(A8="культиватор",(G8+f_roll*m_ET*g)*E8/(1-I8)/eta_tr/1000,eta_ep*(L8-P_aux)) -> 10.475121 | N8: =IF(A8="культиватор",(G8+f_roll*m_D*g)*E8/(1-K8)/eta_tr/1000,eta_ep*(c_move*E8*m_D/m_ET+P_rot0+F8*D8*B8*E8))+P_hyd_idle_D -> 10.724884 | O8: =1-L8*(1+2*cv_P)/P_el_lim -> 0.26474313 | P8: =1-N8*(1+2*cv_P)/P_pto_nom -> 0.31037184 | Q8: =AND(O8>=0,I8<=slip_max) -> TRUE | R8: =AND(P8>=0,K8<=slip_max) -> FALSE | S8: =AND(Q8,M8<=P_mot_1h) -> TRUE | T8: =k_D*(sfc_a*N8+sfc_b*P_pto_nom) -> 3.9492344 | U8: =N8/P_pto_nom -> 0.6476379
A9: =Опыт_режимы!A9 -> культиватор | B9: =Опыт_режимы!B9 -> 0.14 | C9: =Опыт_режимы!C9 -> 4.5 | D9: =IF(A9="культиватор",1.2,1.25) -> 1.2 | E9: =C9/3.6 -> 1.25 | F9: =IF(A9="культиватор","",A_0+A_v*C9+A_a*B9) | G9: =IF(A9="культиватор",D9*B9*(k_0+eps*E9^2),"") -> 6331.5017 | H9: =IF(A9="культиватор",G9/(m_ET*g),"") -> 0.49647155 | I9: =IF(A9="культиватор",-LN(1-H9/phi_max)/k_slip,slip_till) -> 0.1374799 | J9: =IF(A9="культиватор",G9/(m_D*g),"") -> 0.56615177 | K9: =IF(A9="культиватор",-LN(1-J9/phi_max)/k_slip,slip_till) -> 0.1732605 | L9: =IF(A9="культиватор",P_aux+M9/eta_ep,P_aux+c_move*E9+P_rot0+F9*D9*B9*E9) -> 15.524675 | M9: =IF(A9="культиватор",(G9+f_roll*m_ET*g)*E9/(1-I9)/eta_tr/1000,eta_ep*(L9-P_aux)) -> 13.503314 | N9: =IF(A9="культиватор",(G9+f_roll*m_D*g)*E9/(1-K9)/eta_tr/1000,eta_ep*(c_move*E9*m_D/m_ET+P_rot0+F9*D9*B9*E9))+P_hyd_idle_D -> 13.842733 | O9: =1-L9*(1+2*cv_P)/P_el_lim -> 0.055358134 | P9: =1-N9*(1+2*cv_P)/P_pto_nom -> 0.10988885 | Q9: =AND(O9>=0,I9<=slip_max) -> TRUE | R9: =AND(P9>=0,K9<=slip_max) -> FALSE | S9: =AND(Q9,M9<=P_mot_1h) -> FALSE | T9: =k_D*(sfc_a*N9+sfc_b*P_pto_nom) -> 4.6351613 | U9: =N9/P_pto_nom -> 0.83591384
A10: =Опыт_режимы!A10 -> фреза | B10: =Опыт_режимы!B10 -> 0.08 | C10: =Опыт_режимы!C10 -> 1.8 | D10: =IF(A10="культиватор",1.2,1.25) -> 1.25 | E10: =C10/3.6 -> 0.5 | F10: =IF(A10="культиватор","",A_0+A_v*C10+A_a*B10) -> 104.79984 | G10: =IF(A10="культиватор",D10*B10*(k_0+eps*E10^2),"") | H10: =IF(A10="культиватор",G10/(m_ET*g),"") | I10: =IF(A10="культиватор",-LN(1-H10/phi_max)/k_slip,slip_till) -> 0 | J10: =IF(A10="культиватор",G10/(m_D*g),"") | K10: =IF(A10="культиватор",-LN(1-J10/phi_max)/k_slip,slip_till) -> 0 | L10: =IF(A10="культиватор",P_aux+M10/eta_ep,P_aux+c_move*E10+P_rot0+F10*D10*B10*E10) -> 7.4305709 | M10: =IF(A10="культиватор",(G10+f_roll*m_ET*g)*E10/(1-I10)/eta_tr/1000,eta_ep*(L10-P_aux)) -> 6.3805024 | N10: =IF(A10="культиватор",(G10+f_roll*m_D*g)*E10/(1-K10)/eta_tr/1000,eta_ep*(c_move*E10*m_D/m_ET+P_rot0+F10*D10*B10*E10))+P_hyd_idle_D -> 6.4190127 | O10: =1-L10*(1+2*cv_P)/P_el_lim -> 0.54786632 | P10: =1-N10*(1+2*cv_P)/P_pto_nom -> 0.58724663 | Q10: =AND(O10>=0,I10<=slip_max) -> TRUE | R10: =AND(P10>=0,K10<=slip_max) -> TRUE | S10: =AND(Q10,M10<=P_mot_1h) -> TRUE | T10: =k_D*(sfc_a*N10+sfc_b*P_pto_nom) -> 3.0019428 | U10: =N10/P_pto_nom -> 0.38762154
A11: =Опыт_режимы!A11 -> фреза | B11: =Опыт_режимы!B11 -> 0.08 | C11: =Опыт_режимы!C11 -> 2.7 | D11: =IF(A11="культиватор",1.2,1.25) -> 1.25 | E11: =C11/3.6 -> 0.75 | F11: =IF(A11="культиватор","",A_0+A_v*C11+A_a*B11) -> 95.553462 | G11: =IF(A11="культиватор",D11*B11*(k_0+eps*E11^2),"") | H11: =IF(A11="культиватор",G11/(m_ET*g),"") | I11: =IF(A11="культиватор",-LN(1-H11/phi_max)/k_slip,slip_till) -> 0 | J11: =IF(A11="культиватор",G11/(m_D*g),"") | K11: =IF(A11="культиватор",-LN(1-J11/phi_max)/k_slip,slip_till) -> 0 | L11: =IF(A11="культиватор",P_aux+M11/eta_ep,P_aux+c_move*E11+P_rot0+F11*D11*B11*E11) -> 9.871778 | M11: =IF(A11="культиватор",(G11+f_roll*m_ET*g)*E11/(1-I11)/eta_tr/1000,eta_ep*(L11-P_aux)) -> 8.5287647 | N11: =IF(A11="культиватор",(G11+f_roll*m_D*g)*E11/(1-K11)/eta_tr/1000,eta_ep*(c_move*E11*m_D/m_ET+P_rot0+F11*D11*B11*E11))+P_hyd_idle_D -> 8.5115302 | O11: =1-L11*(1+2*cv_P)/P_el_lim -> 0.39932431 | P11: =1-N11*(1+2*cv_P)/P_pto_nom -> 0.45269422 | Q11: =AND(O11>=0,I11<=slip_max) -> TRUE | R11: =AND(P11>=0,K11<=slip_max) -> TRUE | S11: =AND(Q11,M11<=P_mot_1h) -> TRUE | T11: =k_D*(sfc_a*N11+sfc_b*P_pto_nom) -> 3.4622966 | U11: =N11/P_pto_nom -> 0.51398129
A12: =Опыт_режимы!A12 -> фреза | B12: =Опыт_режимы!B12 -> 0.08 | C12: =Опыт_режимы!C12 -> 3.6 | D12: =IF(A12="культиватор",1.2,1.25) -> 1.25 | E12: =C12/3.6 -> 1 | F12: =IF(A12="культиватор","",A_0+A_v*C12+A_a*B12) -> 86.307084 | G12: =IF(A12="культиватор",D12*B12*(k_0+eps*E12^2),"") | H12: =IF(A12="культиватор",G12/(m_ET*g),"") | I12: =IF(A12="культиватор",-LN(1-H12/phi_max)/k_slip,slip_till) -> 0 | J12: =IF(A12="культиватор",G12/(m_D*g),"") | K12: =IF(A12="культиватор",-LN(1-J12/phi_max)/k_slip,slip_till) -> 0 | L12: =IF(A12="культиватор",P_aux+M12/eta_ep,P_aux+c_move*E12+P_rot0+F12*D12*B12*E12) -> 11.850666 | M12: =IF(A12="культиватор",(G12+f_roll*m_ET*g)*E12/(1-I12)/eta_tr/1000,eta_ep*(L12-P_aux)) -> 10.270186 | N12: =IF(A12="культиватор",(G12+f_roll*m_D*g)*E12/(1-K12)/eta_tr/1000,eta_ep*(c_move*E12*m_D/m_ET+P_rot0+F12*D12*B12*E12))+P_hyd_idle_D -> 10.197207 | O12: =1-L12*(1+2*cv_P)/P_el_lim -> 0.27891337 | P12: =1-N12*(1+2*cv_P)/P_pto_nom -> 0.34430235 | Q12: =AND(O12>=0,I12<=slip_max) -> TRUE | R12: =AND(P12>=0,K12<=slip_max) -> TRUE | S12: =AND(Q12,M12<=P_mot_1h) -> TRUE | T12: =k_D*(sfc_a*N12+sfc_b*P_pto_nom) -> 3.8331455 | U12: =N12/P_pto_nom -> 0.61577337
A13: =Опыт_режимы!A13 -> фреза | B13: =Опыт_режимы!B13 -> 0.12 | C13: =Опыт_режимы!C13 -> 1.8 | D13: =IF(A13="культиватор",1.2,1.25) -> 1.25 | E13: =C13/3.6 -> 0.5 | F13: =IF(A13="культиватор","",A_0+A_v*C13+A_a*B13) -> 103.67081 | G13: =IF(A13="культиватор",D13*B13*(k_0+eps*E13^2),"") | H13: =IF(A13="культиватор",G13/(m_ET*g),"") | I13: =IF(A13="культиватор",-LN(1-H13/phi_max)/k_slip,slip_till) -> 0 | J13: =IF(A13="культиватор",G13/(m_D*g),"") | K13: =IF(A13="культиватор",-LN(1-J13/phi_max)/k_slip,slip_till) -> 0 | L13: =IF(A13="культиватор",P_aux+M13/eta_ep,P_aux+c_move*E13+P_rot0+F13*D13*B13*E13) -> 9.9658899 | M13: =IF(A13="культиватор",(G13+f_roll*m_ET*g)*E13/(1-I13)/eta_tr/1000,eta_ep*(L13-P_aux)) -> 8.6115831 | N13: =IF(A13="культиватор",(G13+f_roll*m_D*g)*E13/(1-K13)/eta_tr/1000,eta_ep*(c_move*E13*m_D/m_ET+P_rot0+F13*D13*B13*E13))+P_hyd_idle_D -> 8.6500934 | O13: =1-L13*(1+2*cv_P)/P_el_lim -> 0.39359781 | P13: =1-N13*(1+2*cv_P)/P_pto_nom -> 0.44378437 | Q13: =AND(O13>=0,I13<=slip_max) -> TRUE | R13: =AND(P13>=0,K13<=slip_max) -> TRUE | S13: =AND(Q13,M13<=P_mot_1h) -> TRUE | T13: =k_D*(sfc_a*N13+sfc_b*P_pto_nom) -> 3.4927806 | U13: =N13/P_pto_nom -> 0.52234864
... A17: =Опыт_режимы!A17 -> фреза | B17: =Опыт_режимы!B17 -> 0.16 | C17: =Опыт_режимы!C17 -> 2.7 | D17: =IF(A17="культиватор",1.2,1.25) -> 1.25 | E17: =C17/3.6 -> 0.75 | F17: =IF(A17="культиватор","",A_0+A_v*C17+A_a*B17) -> 93.295408 | G17: =IF(A17="культиватор",D17*B17*(k_0+eps*E17^2),"") | H17: =IF(A17="культиватор",G17/(m_ET*g),"") | I17: =IF(A17="культиватор",-LN(1-H17/phi_max)/k_slip,slip_till) -> 0 | J17: =IF(A17="культиватор",G17/(m_D*g),"") | K17: =IF(A17="культиватор",-LN(1-J17/phi_max)/k_slip,slip_till) -> 0 | L17: =IF(A17="культиватор",P_aux+M17/eta_ep,P_aux+c_move*E17+P_rot0+F17*D17*B17*E17) -> 16.69958 | M17: =IF(A17="культиватор",(G17+f_roll*m_ET*g)*E17/(1-I17)/eta_tr/1000,eta_ep*(L17-P_aux)) -> 14.53723 | N17: =IF(A17="культиватор",(G17+f_roll*m_D*g)*E17/(1-K17)/eta_tr/1000,eta_ep*(c_move*E17*m_D/m_ET+P_rot0+F17*D17*B17*E17))+P_hyd_idle_D -> 14.519996 | O17: =1-L17*(1+2*cv_P)/P_el_lim -> -0.016132205 | P17: =1-N17*(1+2*cv_P)/P_pto_nom -> 0.066339732 | Q17: =AND(O17>=0,I17<=slip_max) -> FALSE | R17: =AND(P17>=0,K17<=slip_max) -> TRUE | S17: =AND(Q17,M17<=P_mot_1h) -> FALSE | T17: =k_D*(sfc_a*N17+sfc_b*P_pto_nom) -> 4.784159 | U17: =N17/P_pto_nom -> 0.87681133

Sheet Смена
A1: Режим | B1: W0, га/ч | C1: n_пов, 1/га | D1: t_га, ч/га | E1: e_акб, кВт·ч/га | F1: Мощность цикла, кВт | G1: t_авт ЭТ, ч | H1: A_зар, га | I1: Работа на зарядке, ч | J1: w1, ч | K1: Подзаряд. 1 | L1: w2, ч | M1: Подзаряд. 2 | N1: w3, ч | O1: Подзарядок | P1: S_см ЭТ, га | Q1: e_сеть, кВт·ч/га | R1: q0, л/га | S1: Q_ср, л/ч | T1: t_авт Д, ч | U1: Дозаправок | V1: S_см Д, га | W1: q, л/га | X1: A_бак, га
A2: =Энергетика!A2&" "&Энергетика!B2&"×"&Энергетика!C2 -> культиватор 0.08×3.6 | B2: =0.1*Энергетика!D2*Энергетика!C2 -> 0.432 | C2: =10000/(Энергетика!D2*L_run_m) -> 27.777778 | D2: =1/B2+C2*turn_t/3600 -> 2.5632253 | E2: =Энергетика!L2/B2+C2*turn_P*turn_t/3600 -> 18.273907 | F2: =E2/D2 -> 7.1292627 | G2: =E_use/F2 -> 2.2271588 | H2: =G2/D2 -> 0.86888919 | I2: =(E_use-2*E_tr)/F2 -> 2.1123949 | J2: =MAX(0,MIN(I2,T_av-2*t_tr)) -> 2.1123949 | K2: =AND(T_av-(t_tr+J2)-t_tr>0.000001,T_av-(t_tr+J2)-2*t_tr-t_ch>=0.25) -> FALSE | L2: =IF(K2,MAX(0,MIN(I2,T_av-(t_tr+J2+2*t_tr+t_ch)-t_tr)),0) -> 0 | M2: =AND(K2,L2>0,T_av-(t_tr+J2+2*t_tr+t_ch+L2)-t_tr>0.000001,T_av-(t_tr+J2+2*t_tr+t_ch+L2)-2*t_tr-t_ch>=0.25) -> FALSE | N2: =IF(M2,MAX(0,MIN(I2,T_av-((t_tr+J2+2*t_tr+t_ch+L2)+2*t_tr+t_ch)-t_tr)),0) -> 0 | O2: =K2*1+M2*1 -> 0 | P2: =(J2+L2+N2)/D2 -> 0.82411596 | Q2: =(E2+E_tr*(2+2*O2)/P2)/(eta_ch*eta_bat) -> 22.044286 | R2: =Энергетика!T2/B2+C2*turn_t/3600*Q_turn -> 7.5035406 | S2: =R2/D2 -> 2.9273824 | T2: =tank_D/S2 -> 7.5152464 | U2: =MAX(0,((T_av-2*t_tr)*S2+2*t_tr*Q_tr)/tank_D-1) -> 0 | V2: =(T_av-2*t_tr-U2*t_refuel_h)/D2 -> 2.8207157 | W2: =R2+2*t_tr*Q_tr/V2 -> 7.6260925 | X2: =T2/D2 -> 2.9319492
A3: =Энергетика!A3&" "&Энергетика!B3&"×"&Энергетика!C3 -> культиватор 0.08×4.5 | B3: =0.1*Энергетика!D3*Энергетика!C3 -> 0.54 | C3: =10000/(Энергетика!D3*L_run_m) -> 27.777778 | D3: =1/B3+C3*turn_t/3600 -> 2.1002623 | E3: =Энергетика!L3/B3+C3*turn_P*turn_t/3600 -> 18.575248 | F3: =E3/D3 -> 8.8442513 | G3: =E_use/F3 -> 1.7952905 | H3: =G3/D3 -> 0.85479343 | I3: =(E_use-2*E_tr)/F3 -> 1.7027804 | J3: =MAX(0,MIN(I3,T_av-2*t_tr)) -> 1.7027804 | K3: =AND(T_av-(t_tr+J3)-t_tr>0.000001,T_av-(t_tr+J3)-2*t_tr-t_ch>=0.25) -> TRUE | L3: =IF(K3,MAX(0,MIN(I3,T_av-(t_tr+J3+2*t_tr+t_ch)-t_tr)),0) -> 0.20689414 | M3: =AND(K3,L3>0,T_av-(t_tr+J3+2*t_tr+t_ch+L3)-t_tr>0.000001,T_av-(t_tr+J3+2*t_tr+t_ch+L3)-2*t_tr-t_ch>=0.25) -> FALSE | N3: =IF(M3,MAX(0,MIN(I3,T_av-((t_tr+J3+2*t_tr+t_ch+L3)+2*t_tr+t_ch)-t_tr)),0) -> 0 | O3: =K3*1+M3*1 -> 1 | P3: =(J3+L3+N3)/D3 -> 0.90925526 | Q3: =(E3+E_tr*(2+2*O3)/P3)/(eta_ch*eta_bat) -> 23.312268 | R3: =Энергетика!T3/B3+C3*turn_t/3600*Q_turn -> 6.8292248 | S3: =R3/D3 -> 3.2516056 | T3: =tank_D/S3 -> 6.7658883 | U3: =MAX(0,((T_av-2*t_tr)*S3+2*t_tr*Q_tr)/tank_D-1) -> 0.084327936 | V3: =(T_av-2*t_tr-U3*t_refuel_h)/D3 -> 3.4364663 | W3: =R3+2*t_tr*Q_tr/V3 -> 6.9298176 | X3: =T3/D3 -> 3.2214491
A4: =Энергетика!A4&" "&Энергетика!B4&"×"&Энергетика!C4 -> культиватор 0.08×5.4 | B4: =0.1*Энергетика!D4*Энергетика!C4 -> 0.648 | C4: =10000/(Энергетика!D4*L_run_m) -> 27.777778 | D4: =1/B4+C4*turn_t/3600 -> 1.7916204 | E4: =Энергетика!L4/B4+C4*turn_P*turn_t/3600 -> 18.993379 | F4: =E4/D4 -> 10.60123 | G4: =E_use/F4 -> 1.4977508 | H4: =G4/D4 -> 0.83597552 | I4: =(E_use-2*E_tr)/F4 -> 1.4205728 | J4: =MAX(0,MIN(I4,T_av-2*t_tr)) -> 1.4205728 | K4: =AND(T_av-(t_tr+J4)-t_tr>0.000001,T_av-(t_tr+J4)-2*t_tr-t_ch>=0.25) -> TRUE | L4: =IF(K4,MAX(0,MIN(I4,T_av-(t_tr+J4+2*t_tr+t_ch)-t_tr)),0) -> 0.48910182 | M4: =AND(K4,L4>0,T_av-(t_tr+J4+2*t_tr+t_ch+L4)-t_tr>0.000001,T_av-(t_tr+J4+2*t_tr+t_ch+L4)-2*t_tr-t_ch>=0.25) -> FALSE | N4: =IF(M4,MAX(0,MIN(I4,T_av-((t_tr+J4+2*t_tr+t_ch+L4)+2*t_tr+t_ch)-t_tr)),0) -> 0 | O4: =K4*1+M4*1 -> 1 | P4: =(J4+L4+N4)/D4 -> 1.0658924 | Q4: =(E4+E_tr*(2+2*O4)/P4)/(eta_ch*eta_bat) -> 23.488083 | R4: =Энергетика!T4/B4+C4*turn_t/3600*Q_turn -> 6.4233549 | S4: =R4/D4 -> 3.585221 | T4: =tank_D/S4 -> 6.1363024 | U4: =MAX(0,((T_av-2*t_tr)*S4+2*t_tr*Q_tr)/tank_D-1) -> 0.19396805 | V4: =(T_av-2*t_tr-U4*t_refuel_h)/D4 -> 4.019286 | W4: =R4+2*t_tr*Q_tr/V4 -> 6.5093612 | X4: =T4/D4 -> 3.4250015
A5: =Энергетика!A5&" "&Энергетика!B5&"×"&Энергетика!C5 -> культиватор 0.11×3.6 | B5: =0.1*Энергетика!D5*Энергетика!C5 -> 0.432 | C5: =10000/(Энергетика!D5*L_run_m) -> 27.777778 | D5: =1/B5+C5*turn_t/3600 -> 2.5632253 | E5: =Энергетика!L5/B5+C5*turn_P*turn_t/3600 -> 23.190762 | F5: =E5/D5 -> 9.0474925 | G5: =E_use/F5 -> 1.7549614 | H5: =G5/D5 -> 0.68466919 | I5: =(E_use-2*E_tr)/F5 -> 1.6645295 | J5: =MAX(0,MIN(I5,T_av-2*t_tr)) -> 1.6645295 | K5: =AND(T_av-(t_tr+J5)-t_tr>0.000001,T_av-(t_tr+J5)-2*t_tr-t_ch>=0.25) -> TRUE | L5: =IF(K5,MAX(0,MIN(I5,T_av-(t_tr+J5+2*t_tr+t_ch)-t_tr)),0) -> 0.24514508 | M5: =AND(K5,L5>0,T_av-(t_tr+J5+2*t_tr+t_ch+L5)-t_tr>0.000001,T_av-(t_tr+J5+2*t_tr+t_ch+L5)-2*t_tr-t_ch>=0.25) -> FALSE | N5: =IF(M5,MAX(0,MIN(I5,T_av-((t_tr+J5+2*t_tr+t_ch+L5)+2*t_tr+t_ch)-t_tr)),0) -> 0 | O5: =K5*1+M5*1 -> 1 | P5: =(J5+L5+N5)/D5 -> 0.74502798 | Q5: =(E5+E_tr*(2+2*O5)/P5)/(eta_ch*eta_bat) -> 29.047072 | R5: =Энергетика!T5/B5+C5*turn_t/3600*Q_turn -> 8.5011552 | S5: =R5/D5 -> 3.3165852 | T5: =tank_D/S5 -> 6.6333287 | U5: =MAX(0,((T_av-2*t_tr)*S5+2*t_tr*Q_tr)/tank_D-1) -> 0.105683 | V5: =(T_av-2*t_tr-U5*t_refuel_h)/D5 -> 2.8145311 | W5: =R5+2*t_tr*Q_tr/V5 -> 8.6239764 | X5: =T5/D5 -> 2.5878836
A6: =Энергетика!A6&" "&Энергетика!B6&"×"&Энергетика!C6 -> культиватор 0.11×4.5 | B6: =0.1*Энергетика!D6*Энергетика!C6 -> 0.54 | C6: =10000/(Энергетика!D6*L_run_m) -> 27.777778 | D6: =1/B6+C6*turn_t/3600 -> 2.1002623 | E6: =Энергетика!L6/B6+C6*turn_P*turn_t/3600 -> 23.691194 | F6: =E6/D6 -> 11.280112 | G6: =E_use/F6 -> 1.4076101 | H6: =G6/D6 -> 0.67020682 | I6: =(E_use-2*E_tr)/F6 -> 1.335077 | J6: =MAX(0,MIN(I6,T_av-2*t_tr)) -> 1.335077 | K6: =AND(T_av-(t_tr+J6)-t_tr>0.000001,T_av-(t_tr+J6)-2*t_tr-t_ch>=0.25) -> TRUE | L6: =IF(K6,MAX(0,MIN(I6,T_av-(t_tr+J6+2*t_tr+t_ch)-t_tr)),0) -> 0.57459756 | M6: =AND(K6,L6>0,T_av-(t_tr+J6+2*t_tr+t_ch+L6)-t_tr>0.000001,T_av-(t_tr+J6+2*t_tr+t_ch+L6)-2*t_tr-t_ch>=0.25) -> FALSE | N6: =IF(M6,MAX(0,MIN(I6,T_av-((t_tr+J6+2*t_tr+t_ch+L6)+2*t_tr+t_ch)-t_tr)),0) -> 0 | O6: =K6*1+M6*1 -> 1 | P6: =(J6+L6+N6)/D6 -> 0.90925526 | Q6: =(E6+E_tr*(2+2*O6)/P6)/(eta_ch*eta_bat) -> 29.165754 | R6: =Энергетика!T6/B6+C6*turn_t/3600*Q_turn -> 7.8708268 | S6: =R6/D6 -> 3.7475446 | T6: =tank_D/S6 -> 5.8705106 | U6: =MAX(0,((T_av-2*t_tr)*S6+2*t_tr*Q_tr)/tank_D-1) -> 0.24731445 | V6: =(T_av-2*t_tr-U6*t_refuel_h)/D6 -> 3.4248258 | W6: =R6+2*t_tr*Q_tr/V6 -> 7.9717615 | X6: =T6/D6 -> 2.795132
A7: =Энергетика!A7&" "&Энергетика!B7&"×"&Энергетика!C7 -> культиватор 0.11×5.4 | B7: =0.1*Энергетика!D7*Энергетика!C7 -> 0.648 | C7: =10000/(Энергетика!D7*L_run_m) -> 27.777778 | D7: =1/B7+C7*turn_t/3600 -> 1.7916204 | E7: =Энергетика!L7/B7+C7*turn_P*turn_t/3600 -> 24.359834 | F7: =E7/D7 -> 13.596538 | G7: =E_use/F7 -> 1.1677973 | H7: =G7/D7 -> 0.65181068 | I7: =(E_use-2*E_tr)/F7 -> 1.1076215 | J7: =MAX(0,MIN(I7,T_av-2*t_tr)) -> 1.1076215 | K7: =AND(T_av-(t_tr+J7)-t_tr>0.000001,T_av-(t_tr+J7)-2*t_tr-t_ch>=0.25) -> TRUE | L7: =IF(K7,MAX(0,MIN(I7,T_av-(t_tr+J7+2*t_tr+t_ch)-t_tr)),0) -> 0.80205304 | M7: =AND(K7,L7>0,T_av-(t_tr+J7+2*t_tr+t_ch+L7)-t_tr>0.000001,T_av-(t_tr+J7+2*t_tr+t_ch+L7)-2*t_tr-t_ch>=0.25) -> FALSE | N7: =IF(M7,MAX(0,MIN(I7,T_av-((t_tr+J7+2*t_tr+t_ch+L7)+2*t_tr+t_ch)-t_tr)),0) -> 0 | O7: =K7*1+M7*1 -> 1 | P7: =(J7+L7+N7)/D7 -> 1.0658924 | Q7: =(E7+E_tr*(2+2*O7)/P7)/(eta_ch*eta_bat) -> 29.628192 | R7: =Энергетика!T7/B7+C7*turn_t/3600*Q_turn -> 7.5209837 | S7: =R7/D7 -> 4.1978668 | T7: =tank_D/S7 -> 5.240757 | U7: =MAX(0,((T_av-2*t_tr)*S7+2*t_tr*Q_tr)/tank_D-1) -> 0.39530938 | V7: =(T_av-2*t_tr-U7*t_refuel_h)/D7 -> 4.0024291 | W7: =R7+2*t_tr*Q_tr/V7 -> 7.6073523 | X7: =T7/D7 -> 2.9251493
A8: =Энергетика!A8&" "&Энергетика!B8&"×"&Энергетика!C8 -> культиватор 0.14×3.6 | B8: =0.1*Энергетика!D8*Энергетика!C8 -> 0.432 | C8: =10000/(Энергетика!D8*L_run_m) -> 27.777778 | D8: =1/B8+C8*turn_t/3600 -> 2.5632253 | E8: =Энергетика!L8/B8+C8*turn_P*turn_t/3600 -> 28.715758 | F8: =E8/D8 -> 11.202978 | G8: =E_use/F8 -> 1.4173017 | H8: =G8/D8 -> 0.55293682 | I8: =(E_use-2*E_tr)/F8 -> 1.3442691 | J8: =MAX(0,MIN(I8,T_av-2*t_tr)) -> 1.3442691 | K8: =AND(T_av-(t_tr+J8)-t_tr>0.000001,T_av-(t_tr+J8)-2*t_tr-t_ch>=0.25) -> TRUE | L8: =IF(K8,MAX(0,MIN(I8,T_av-(t_tr+J8+2*t_tr+t_ch)-t_tr)),0) -> 0.56540545 | M8: =AND(K8,L8>0,T_av-(t_tr+J8+2*t_tr+t_ch+L8)-t_tr>0.000001,T_av-(t_tr+J8+2*t_tr+t_ch+L8)-2*t_tr-t_ch>=0.25) -> FALSE | N8: =IF(M8,MAX(0,MIN(I8,T_av-((t_tr+J8+2*t_tr+t_ch+L8)+2*t_tr+t_ch)-t_tr)),0) -> 0 | O8: =K8*1+M8*1 -> 1 | P8: =(J8+L8+N8)/D8 -> 0.74502798 | Q8: =(E8+E_tr*(2+2*O8)/P8)/(eta_ch*eta_bat) -> 35.368577 | R8: =Энергетика!T8/B8+C8*turn_t/3600*Q_turn -> 9.6803521 | S8: =R8/D8 -> 3.7766294 | T8: =tank_D/S8 -> 5.8253002 | U8: =MAX(0,((T_av-2*t_tr)*S8+2*t_tr*Q_tr)/tank_D-1) -> 0.25687296 | V8: =(T_av-2*t_tr-U8*t_refuel_h)/D8 -> 2.8056835 | W8: =R8+2*t_tr*Q_tr/V8 -> 9.8035606 | X8: =T8/D8 -> 2.2726446
A9: =Энергетика!A9&" "&Энергетика!B9&"×"&Энергетика!C9 -> культиватор 0.14×4.5 | B9: =0.1*Энергетика!D9*Энергетика!C9 -> 0.54 | C9: =10000/(Энергетика!D9*L_run_m) -> 27.777778 | D9: =1/B9+C9*turn_t/3600 -> 2.1002623 | E9: =Энергетика!L9/B9+C9*turn_P*turn_t/3600 -> 29.493983 | F9: =E9/D9 -> 14.043 | G9: =E_use/F9 -> 1.1306701 | H9: =G9/D9 -> 0.53834708 | I9: =(E_use-2*E_tr)/F9 -> 1.0724075 | J9: =MAX(0,MIN(I9,T_av-2*t_tr)) -> 1.0724075 | K9: =AND(T_av-(t_tr+J9)-t_tr>0.000001,T_av-(t_tr+J9)-2*t_tr-t_ch>=0.25) -> TRUE | L9: =IF(K9,MAX(0,MIN(I9,T_av-(t_tr+J9+2*t_tr+t_ch)-t_tr)),0) -> 0.83726708 | M9: =AND(K9,L9>0,T_av-(t_tr+J9+2*t_tr+t_ch+L9)-t_tr>0.000001,T_av-(t_tr+J9+2*t_tr+t_ch+L9)-2*t_tr-t_ch>=0.25) -> FALSE | N9: =IF(M9,MAX(0,MIN(I9,T_av-((t_tr+J9+2*t_tr+t_ch+L9)+2*t_tr+t_ch)-t_tr)),0) -> 0 | O9: =K9*1+M9*1 -> 1 | P9: =(J9+L9+N9)/D9 -> 0.90925526 | Q9: =(E9+E_tr*(2+2*O9)/P9)/(eta_ch*eta_bat) -> 35.805101 | R9: =Энергетика!T9/B9+C9*turn_t/3600*Q_turn -> 9.1222378 | S9: =R9/D9 -> 4.3433802 | T9: =tank_D/S9 -> 5.0651794 | U9: =MAX(0,((T_av-2*t_tr)*S9+2*t_tr*Q_tr)/tank_D-1) -> 0.44313122 | V9: =(T_av-2*t_tr-U9*t_refuel_h)/D9 -> 3.4108407 | W9: =R9+2*t_tr*Q_tr/V9 -> 9.2235865 | X9: =T9/D9 -> 2.4116889
A10: =Энергетика!A10&" "&Энергетика!B10&"×"&Энергетика!C10 -> фреза 0.08×1.8 | B10: =0.1*Энергетика!D10*Энергетика!C10 -> 0.225 | C10: =10000/(Энергетика!D10*L_run_m) -> 26.666667 | D10: =1/B10+C10*turn_t/3600 -> 4.6829185 | E10: =Энергетика!L10/B10+C10*turn_P*turn_t/3600 -> 33.739562 | F10: =E10/D10 -> 7.204815 | G10: =E_use/F10 -> 2.203804 | H10: =G10/D10 -> 0.47060481 | I10: =(E_use-2*E_tr)/F10 -> 2.0902436 | J10: =MAX(0,MIN(I10,T_av-2*t_tr)) -> 2.0902436 | K10: =AND(T_av-(t_tr+J10)-t_tr>0.000001,T_av-(t_tr+J10)-2*t_tr-t_ch>=0.25) -> FALSE | L10: =IF(K10,MAX(0,MIN(I10,T_av-(t_tr+J10+2*t_tr+t_ch)-t_tr)),0) -> 0 | M10: =AND(K10,L10>0,T_av-(t_tr+J10+2*t_tr+t_ch+L10)-t_tr>0.000001,T_av-(t_tr+J10+2*t_tr+t_ch+L10)-2*t_tr-t_ch>=0.25) -> FALSE | N10: =IF(M10,MAX(0,MIN(I10,T_av-((t_tr+J10+2*t_tr+t_ch+L10)+2*t_tr+t_ch)-t_tr)),0) -> 0 | O10: =K10*1+M10*1 -> 0 | P10: =(J10+L10+N10)/D10 -> 0.44635488 | Q10: =(E10+E_tr*(2+2*O10)/P10)/(eta_ch*eta_bat) -> 40.700906 | R10: =Энергетика!T10/B10+C10*turn_t/3600*Q_turn -> 13.85903 | S10: =R10/D10 -> 2.9594855 | T10: =tank_D/S10 -> 7.4337245 | U10: =MAX(0,((T_av-2*t_tr)*S10+2*t_tr*Q_tr)/tank_D-1) -> 0 | V10: =(T_av-2*t_tr-U10*t_refuel_h)/D10 -> 1.5439367 | W10: =R10+2*t_tr*Q_tr/V10 -> 14.082927 | X10: =T10/D10 -> 1.5874127
A11: =Энергетика!A11&" "&Энергетика!B11&"×"&Энергетика!C11 -> фреза 0.08×2.7 | B11: =0.1*Энергетика!D11*Энергетика!C11 -> 0.3375 | C11: =10000/(Энергетика!D11*L_run_m) -> 26.666667 | D11: =1/B11+C11*turn_t/3600 -> 3.201437 | E11: =Энергетика!L11/B11+C11*turn_P*turn_t/3600 -> 29.964515 | F11: =E11/D11 -> 9.3597077 | G11: =E_use/F11 -> 1.6964205 | H11: =G11/D11 -> 0.52989344 | I11: =(E_use-2*E_tr)/F11 -> 1.6090052 | J11: =MAX(0,MIN(I11,T_av-2*t_tr)) -> 1.6090052 | K11: =AND(T_av-(t_tr+J11)-t_tr>0.000001,T_av-(t_tr+J11)-2*t_tr-t_ch>=0.25) -> TRUE | L11: =IF(K11,MAX(0,MIN(I11,T_av-(t_tr+J11+2*t_tr+t_ch)-t_tr)),0) -> 0.3006694 | M11: =AND(K11,L11>0,T_av-(t_tr+J11+2*t_tr+t_ch+L11)-t_tr>0.000001,T_av-(t_tr+J11+2*t_tr+t_ch+L11)-2*t_tr-t_ch>=0.25) -> FALSE | N11: =IF(M11,MAX(0,MIN(I11,T_av-((t_tr+J11+2*t_tr+t_ch+L11)+2*t_tr+t_ch)-t_tr)),0) -> 0 | O11: =K11*1+M11*1 -> 1 | P11: =(J11+L11+N11)/D11 -> 0.59650543 | Q11: =(E11+E_tr*(2+2*O11)/P11)/(eta_ch*eta_bat) -> 37.423072 | R11: =Энергетика!T11/B11+C11*turn_t/3600*Q_turn -> 10.775718 | S11: =R11/D11 -> 3.3659004 | T11: =tank_D/S11 -> 6.5361411 | U11: =MAX(0,((T_av-2*t_tr)*S11+2*t_tr*Q_tr)/tank_D-1) -> 0.12189005 | V11: =(T_av-2*t_tr-U11*t_refuel_h)/D11 -> 2.2526904 | W11: =R11+2*t_tr*Q_tr/V11 -> 10.929172 | X11: =T11/D11 -> 2.0416272
A12: =Энергетика!A12&" "&Энергетика!B12&"×"&Энергетика!C12 -> фреза 0.08×3.6 | B12: =0.1*Энергетика!D12*Энергетика!C12 -> 0.45 | C12: =10000/(Энергетика!D12*L_run_m) -> 26.666667 | D12: =1/B12+C12*turn_t/3600 -> 2.4606963 | E12: =Энергетика!L12/B12+C12*turn_P*turn_t/3600 -> 27.049616 | F12: =E12/D12 -> 10.992667 | G12: =E_use/F12 -> 1.4444174 | H12: =G12/D12 -> 0.58699539 | I12: =(E_use-2*E_tr)/F12 -> 1.3699876 | J12: =MAX(0,MIN(I12,T_av-2*t_tr)) -> 1.3699876 | K12: =AND(T_av-(t_tr+J12)-t_tr>0.000001,T_av-(t_tr+J12)-2*t_tr-t_ch>=0.25) -> TRUE | L12: =IF(K12,MAX(0,MIN(I12,T_av-(t_tr+J12+2*t_tr+t_ch)-t_tr)),0) -> 0.53968698 | M12: =AND(K12,L12>0,T_av-(t_tr+J12+2*t_tr+t_ch+L12)-t_tr>0.000001,T_av-(t_tr+J12+2*t_tr+t_ch+L12)-2*t_tr-t_ch>=0.25) -> FALSE | N12: =IF(M12,MAX(0,MIN(I12,T_av-((t_tr+J12+2*t_tr+t_ch+L12)+2*t_tr+t_ch)-t_tr)),0) -> 0 | O12: =K12*1+M12*1 -> 1 | P12: =(J12+L12+N12)/D12 -> 0.77607082 | Q12: =(E12+E_tr*(2+2*O12)/P12)/(eta_ch*eta_bat) -> 33.361716 | R12: =Энергетика!T12/B12+C12*turn_t/3600*Q_turn -> 9.0351627 | S12: =R12/D12 -> 3.6717911 | T12: =tank_D/S12 -> 5.9916263 | U12: =MAX(0,((T_av-2*t_tr)*S12+2*t_tr*Q_tr)/tank_D-1) -> 0.22241866 | V12: =(T_av-2*t_tr-U12*t_refuel_h)/D12 -> 2.9246872 | W12: =R12+2*t_tr*Q_tr/V12 -> 9.1533579 | X12: =T12/D12 -> 2.4349312
A13: =Энергетика!A13&" "&Энергетика!B13&"×"&Энергетика!C13 -> фреза 0.12×1.8 | B13: =0.1*Энергетика!D13*Энергетика!C13 -> 0.225 | C13: =10000/(Энергетика!D13*L_run_m) -> 26.666667 | D13: =1/B13+C13*turn_t/3600 -> 4.6829185 | E13: =Энергетика!L13/B13+C13*turn_P*turn_t/3600 -> 45.007646 | F13: =E13/D13 -> 9.6110248 | G13: =E_use/F13 -> 1.6520611 | H13: =G13/D13 -> 0.3527845 | I13: =(E_use-2*E_tr)/F13 -> 1.5669316 | J13: =MAX(0,MIN(I13,T_av-2*t_tr)) -> 1.5669316 | K13: =AND(T_av-(t_tr+J13)-t_tr>0.000001,T_av-(t_tr+J13)-2*t_tr-t_ch>=0.25) -> TRUE | L13: =IF(K13,MAX(0,MIN(I13,T_av-(t_tr+J13+2*t_tr+t_ch)-t_tr)),0) -> 0.34274302 | M13: =AND(K13,L13>0,T_av-(t_tr+J13+2*t_tr+t_ch+L13)-t_tr>0.000001,T_av-(t_tr+J13+2*t_tr+t_ch+L13)-2*t_tr-t_ch>=0.25) -> FALSE | N13: =IF(M13,MAX(0,MIN(I13,T_av-((t_tr+J13+2*t_tr+t_ch+L13)+2*t_tr+t_ch)-t_tr)),0) -> 0 | O13: =K13*1+M13*1 -> 1 | P13: =(J13+L13+N13)/D13 -> 0.40779582 | Q13: =(E13+E_tr*(2+2*O13)/P13)/(eta_ch*eta_bat) -> 56.087356 | R13: =Энергетика!T13/B13+C13*turn_t/3600*Q_turn -> 16.040531 | S13: =R13/D13 -> 3.4253277 | T13: =tank_D/S13 -> 6.4227431 | U13: =MAX(0,((T_av-2*t_tr)*S13+2*t_tr*Q_tr)/tank_D-1) -> 0.14142038 | V13: =(T_av-2*t_tr-U13*t_refuel_h)/D13 -> 1.5394068 | W13: =R13+2*t_tr*Q_tr/V13 -> 16.265087 | X13: =T13/D13 -> 1.3715257
... A17: =Энергетика!A17&" "&Энергетика!B17&"×"&Энергетика!C17 -> фреза 0.16×2.7 | B17: =0.1*Энергетика!D17*Энергетика!C17 -> 0.3375 | C17: =10000/(Энергетика!D17*L_run_m) -> 26.666667 | D17: =1/B17+C17*turn_t/3600 -> 3.201437 | E17: =Энергетика!L17/B17+C17*turn_P*turn_t/3600 -> 50.195038 | F17: =E17/D17 -> 15.678908 | G17: =E_use/F17 -> 1.012698 | H17: =G17/D17 -> 0.31632609 | I17: =(E_use-2*E_tr)/F17 -> 0.96051445 | J17: =MAX(0,MIN(I17,T_av-2*t_tr)) -> 0.96051445 | K17: =AND(T_av-(t_tr+J17)-t_tr>0.000001,T_av-(t_tr+J17)-2*t_tr-t_ch>=0.25) -> TRUE | L17: =IF(K17,MAX(0,MIN(I17,T_av-(t_tr+J17+2*t_tr+t_ch)-t_tr)),0) -> 0.94916013 | M17: =AND(K17,L17>0,T_av-(t_tr+J17+2*t_tr+t_ch+L17)-t_tr>0.000001,T_av-(t_tr+J17+2*t_tr+t_ch+L17)-2*t_tr-t_ch>=0.25) -> FALSE | N17: =IF(M17,MAX(0,MIN(I17,T_av-((t_tr+J17+2*t_tr+t_ch+L17)+2*t_tr+t_ch)-t_tr)),0) -> 0 | O17: =K17*1+M17*1 -> 1 | P17: =(J17+L17+N17)/D17 -> 0.59650543 | Q17: =(E17+E_tr*(2+2*O17)/P17)/(eta_ch*eta_bat) -> 60.570124 | R17: =Энергетика!T17/B17+C17*turn_t/3600*Q_turn -> 14.692348 | S17: =R17/D17 -> 4.5892977 | T17: =tank_D/S17 -> 4.7937618 | U17: =MAX(0,((T_av-2*t_tr)*S17+2*t_tr*Q_tr)/tank_D-1) -> 0.5239501 | V17: =(T_av-2*t_tr-U17*t_refuel_h)/D17 -> 2.2338523 | W17: =R17+2*t_tr*Q_tr/V17 -> 14.847095 | X17: =T17/D17 -> 1.4973781

Sheet Экономика
A1: Режим | B1: Труд ЭТ, тг/га | C1: Труд Д, тг/га | D1: Энергия ЭТ, тг/га | E1: Топливо Д, тг/га | F1: Ремонт ЭТ, тг/га | G1: Ремонт Д, тг/га | H1: A_год, га | I1: Циклов/год | J1: Ресурс батареи, лет | K1: Замен батареи | L1: Капит. ЭТ, тг/га | M1: Капит. Д, тг/га | N1: C_пр ЭТ, тг/га | O1: C_пр Д, тг/га | P1: C_сов ЭТ, тг/га | Q1: C_сов Д, тг/га
A2: =Смена!A2 -> культиватор 0.08×3.6 | B2: =wage_h*(Смена!D2+2*t_tr*(1+Смена!O2)/Смена!P2) -> 6884.8243 | C2: =wage_h*(Смена!D2+2*t_tr/Смена!V2) -> 6602.5659 | D2: =Смена!Q2*c_el -> 1004.999 | E2: =Смена!W2*c_D -> 2631.0019 | F2: =k_RM_ET*rm_h_D*Смена!D2 -> 216.35281 | G2: =rm_h_D*Смена!D2 -> 360.58801 | H2: =T_year_h/Смена!D2 -> 234.08009 | I2: =H2*Смена!E2/E_bat_kWh -> 183.19305 | J2: =MIN(bat_cycles/I2,bat_cal_y) -> 10 | K2: =MAX(0,life_y/J2-1) -> 0 | L2: =(price_ET*(k_CRF-salvage*k_SFF)+C_bat*K2/(1+r_disc)^J2*k_CRF)/H2 -> 4281.1784 | M2: =price_D*(k_CRF-salvage*k_SFF)/H2 -> 1625.5602 | N2: =B2+D2+F2 -> 8106.1761 | O2: =C2+E2+G2 -> 9594.1558 | P2: =N2+L2 -> 12387.355 | Q2: =O2+M2 -> 11219.716
A3: =Смена!A3 -> культиватор 0.08×4.5 | B3: =wage_h*(Смена!D3+2*t_tr*(1+Смена!O3)/Смена!P3) -> 6037.415 | C3: =wage_h*(Смена!D3+2*t_tr/Смена!V3) -> 5410.1952 | D3: =Смена!Q3*c_el -> 1062.8063 | E3: =Смена!W3*c_D -> 2390.7871 | F3: =k_RM_ET*rm_h_D*Смена!D3 -> 177.27574 | G3: =rm_h_D*Смена!D3 -> 295.45956 | H3: =T_year_h/Смена!D3 -> 285.6786 | I3: =H3*Смена!E3/E_bat_kWh -> 227.26128 | J3: =MIN(bat_cycles/I3,bat_cal_y) -> 10 | K3: =MAX(0,life_y/J3-1) -> 0 | L3: =(price_ET*(k_CRF-salvage*k_SFF)+C_bat*K3/(1+r_disc)^J3*k_CRF)/H3 -> 3507.9233 | M3: =price_D*(k_CRF-salvage*k_SFF)/H3 -> 1331.9559 | N3: =B3+D3+F3 -> 7277.4971 | O3: =C3+E3+G3 -> 8096.4419 | P3: =N3+L3 -> 10785.42 | Q3: =O3+M3 -> 9428.3977
A4: =Смена!A4 -> культиватор 0.08×5.4 | B4: =wage_h*(Смена!D4+2*t_tr*(1+Смена!O4)/Смена!P4) -> 5150.1927 | C4: =wage_h*(Смена!D4+2*t_tr/Смена!V4) -> 4615.3317 | D4: =Смена!Q4*c_el -> 1070.8217 | E4: =Смена!W4*c_D -> 2245.7296 | F4: =k_RM_ET*rm_h_D*Смена!D4 -> 151.22436 | G4: =rm_h_D*Смена!D4 -> 252.04059 | H4: =T_year_h/Смена!D4 -> 334.89237 | I4: =H4*Смена!E4/E_bat_kWh -> 272.40847 | J4: =MIN(bat_cycles/I4,bat_cal_y) -> 10 | K4: =MAX(0,life_y/J4-1) -> 0 | L4: =(price_ET*(k_CRF-salvage*k_SFF)+C_bat*K4/(1+r_disc)^J4*k_CRF)/H4 -> 2992.4199 | M4: =price_D*(k_CRF-salvage*k_SFF)/H4 -> 1136.2196 | N4: =B4+D4+F4 -> 6372.2387 | O4: =C4+E4+G4 -> 7113.1019 | P4: =N4+L4 -> 9364.6586 | Q4: =O4+M4 -> 8249.3215
A5: =Смена!A5 -> культиватор 0.11×3.6 | B5: =wage_h*(Смена!D5+2*t_tr*(1+Смена!O5)/Смена!P5) -> 7368.2485 | C5: =wage_h*(Смена!D5+2*t_tr/Смена!V5) -> 6602.8219 | D5: =Смена!Q5*c_el -> 1324.256 | E5: =Смена!W5*c_D -> 2975.2719 | F5: =k_RM_ET*rm_h_D*Смена!D5 -> 216.35281 | G5: =rm_h_D*Смена!D5 -> 360.58801 | H5: =T_year_h/Смена!D5 -> 234.08009 | I5: =H5*Смена!E5/E_bat_kWh -> 232.48375 | J5: =MIN(bat_cycles/I5,bat_cal_y) -> 10 | K5: =MAX(0,life_y/J5-1) -> 0 | L5: =(price_ET*(k_CRF-salvage*k_SFF)+C_bat*K5/(1+r_disc)^J5*k_CRF)/H5 -> 4281.1784 | M5: =price_D*(k_CRF-salvage*k_SFF)/H5 -> 1625.5602 | N5: =B5+D5+F5 -> 8908.8573 | O5: =C5+E5+G5 -> 9938.6818 | P5: =N5+L5 -> 13190.036 | Q5: =O5+M5 -> 11564.242
A6: =Смена!A6 -> культиватор 0.11×4.5 | B6: =wage_h*(Смена!D6+2*t_tr*(1+Смена!O6)/Смена!P6) -> 6037.415 | C6: =wage_h*(Смена!D6+2*t_tr/Смена!V6) -> 5410.5203 | D6: =Смена!Q6*c_el -> 1329.6667 | E6: =Смена!W6*c_D -> 2750.2577 | F6: =k_RM_ET*rm_h_D*Смена!D6 -> 177.27574 | G6: =rm_h_D*Смена!D6 -> 295.45956 | H6: =T_year_h/Смена!D6 -> 285.6786 | I6: =H6*Смена!E6/E_bat_kWh -> 289.85298 | J6: =MIN(bat_cycles/I6,bat_cal_y) -> 10 | K6: =MAX(0,life_y/J6-1) -> 0 | L6: =(price_ET*(k_CRF-salvage*k_SFF)+C_bat*K6/(1+r_disc)^J6*k_CRF)/H6 -> 3507.9233 | M6: =price_D*(k_CRF-salvage*k_SFF)/H6 -> 1331.9559 | N6: =B6+D6+F6 -> 7544.3575 | O6: =C6+E6+G6 -> 8456.2376 | P6: =N6+L6 -> 11052.281 | Q6: =O6+M6 -> 9788.1934
A7: =Смена!A7 -> культиватор 0.11×5.4 | B7: =wage_h*(Смена!D7+2*t_tr*(1+Смена!O7)/Смена!P7) -> 5150.1927 | C7: =wage_h*(Смена!D7+2*t_tr/Смена!V7) -> 4615.676 | D7: =Смена!Q7*c_el -> 1350.7493 | E7: =Смена!W7*c_D -> 2624.5365 | F7: =k_RM_ET*rm_h_D*Смена!D7 -> 151.22436 | G7: =rm_h_D*Смена!D7 -> 252.04059 | H7: =T_year_h/Смена!D7 -> 334.89237 | I7: =H7*Смена!E7/E_bat_kWh -> 349.3757 | J7: =MIN(bat_cycles/I7,bat_cal_y) -> 8.5867448 | K7: =MAX(0,life_y/J7-1) -> 0.16458568 | L7: =(price_ET*(k_CRF-salvage*k_SFF)+C_bat*K7/(1+r_disc)^J7*k_CRF)/H7 -> 3080.8084 | M7: =price_D*(k_CRF-salvage*k_SFF)/H7 -> 1136.2196 | N7: =B7+D7+F7 -> 6652.1663 | O7: =C7+E7+G7 -> 7492.2531 | P7: =N7+L7 -> 9732.9746 | Q7: =O7+M7 -> 8628.4727
A8: =Смена!A8 -> культиватор 0.14×3.6 | B8: =wage_h*(Смена!D8+2*t_tr*(1+Смена!O8)/Смена!P8) -> 7368.2485 | C8: =wage_h*(Смена!D8+2*t_tr/Смена!V8) -> 6603.1901 | D8: =Смена!Q8*c_el -> 1612.4534 | E8: =Смена!W8*c_D -> 3382.2284 | F8: =k_RM_ET*rm_h_D*Смена!D8 -> 216.35281 | G8: =rm_h_D*Смена!D8 -> 360.58801 | H8: =T_year_h/Смена!D8 -> 234.08009 | I8: =H8*Смена!E8/E_bat_kWh -> 287.87097 | J8: =MIN(bat_cycles/I8,bat_cal_y) -> 10 | K8: =MAX(0,life_y/J8-1) -> 0 | L8: =(price_ET*(k_CRF-salvage*k_SFF)+C_bat*K8/(1+r_disc)^J8*k_CRF)/H8 -> 4281.1784 | M8: =price_D*(k_CRF-salvage*k_SFF)/H8 -> 1625.5602 | N8: =B8+D8+F8 -> 9197.0548 | O8: =C8+E8+G8 -> 10346.007 | P8: =N8+L8 -> 13478.233 | Q8: =O8+M8 -> 11971.567
A9: =Смена!A9 -> культиватор 0.14×4.5 | B9: =wage_h*(Смена!D9+2*t_tr*(1+Смена!O9)/Смена!P9) -> 6037.415 | C9: =wage_h*(Смена!D9+2*t_tr/Смена!V9) -> 5410.9137 | D9: =Смена!Q9*c_el -> 1632.3545 | E9: =Смена!W9*c_D -> 3182.1373 | F9: =k_RM_ET*rm_h_D*Смена!D9 -> 177.27574 | G9: =rm_h_D*Смена!D9 -> 295.45956 | H9: =T_year_h/Смена!D9 -> 285.6786 | I9: =H9*Смена!E9/E_bat_kWh -> 360.84796 | J9: =MIN(bat_cycles/I9,bat_cal_y) -> 8.3137508 | K9: =MAX(0,life_y/J9-1) -> 0.20282653 | L9: =(price_ET*(k_CRF-salvage*k_SFF)+C_bat*K9/(1+r_disc)^J9*k_CRF)/H9 -> 3637.3251 | M9: =price_D*(k_CRF-salvage*k_SFF)/H9 -> 1331.9559 | N9: =B9+D9+F9 -> 7847.0453 | O9: =C9+E9+G9 -> 8888.5106 | P9: =N9+L9 -> 11484.37 | Q9: =O9+M9 -> 10220.466
A10: =Смена!A10 -> фреза 0.08×1.8 | B10: =wage_h*(Смена!D10+2*t_tr*(1+Смена!O10)/Смена!P10) -> 12586.042 | C10: =wage_h*(Смена!D10+2*t_tr/Смена!V10) -> 12062.645 | D10: =Смена!Q10*c_el -> 1855.5543 | E10: =Смена!W10*c_D -> 4858.6099 | F10: =k_RM_ET*rm_h_D*Смена!D10 -> 395.26863 | G10: =rm_h_D*Смена!D10 -> 658.78106 | H10: =T_year_h/Смена!D10 -> 128.12523 | I10: =H10*Смена!E10/E_bat_kWh -> 185.13443 | J10: =MIN(bat_cycles/I10,bat_cal_y) -> 10 | K10: =MAX(0,life_y/J10-1) -> 0 | L10: =(price_ET*(k_CRF-salvage*k_SFF)+C_bat*K10/(1+r_disc)^J10*k_CRF)/H10 -> 7821.5558 | M10: =price_D*(k_CRF-salvage*k_SFF)/H10 -> 2969.8389 | N10: =B10+D10+F10 -> 14836.865 | O10: =C10+E10+G10 -> 17580.036 | P10: =N10+L10 -> 22658.42 | Q10: =O10+M10 -> 20549.875
A11: =Смена!A11 -> фреза 0.08×2.7 | B11: =wage_h*(Смена!D11+2*t_tr*(1+Смена!O11)/Смена!P11) -> 9202.8522 | C11: =wage_h*(Смена!D11+2*t_tr/Смена!V11) -> 8246.8929 | D11: =Смена!Q11*c_el -> 1706.1179 | E11: =Смена!W11*c_D -> 3770.5644 | F11: =k_RM_ET*rm_h_D*Смена!D11 -> 270.22201 | G11: =rm_h_D*Смена!D11 -> 450.37001 | H11: =T_year_h/Смена!D11 -> 187.41584 | I11: =H11*Смена!E11/E_bat_kWh -> 240.50641 | J11: =MIN(bat_cycles/I11,bat_cal_y) -> 10 | K11: =MAX(0,life_y/J11-1) -> 0 | L11: =(price_ET*(k_CRF-salvage*k_SFF)+C_bat*K11/(1+r_disc)^J11*k_CRF)/H11 -> 5347.1395 | M11: =price_D*(k_CRF-salvage*k_SFF)/H11 -> 2030.3048 | N11: =B11+D11+F11 -> 11179.192 | O11: =C11+E11+G11 -> 12467.827 | P11: =N11+L11 -> 16526.332 | Q11: =O11+M11 -> 14498.132
A12: =Смена!A12 -> фреза 0.08×3.6 | B12: =wage_h*(Смена!D12+2*t_tr*(1+Смена!O12)/Смена!P12) -> 7073.5186 | C12: =wage_h*(Смена!D12+2*t_tr/Смена!V12) -> 6338.9817 | D12: =Смена!Q12*c_el -> 1520.9606 | E12: =Смена!W12*c_D -> 3157.9085 | F12: =k_RM_ET*rm_h_D*Смена!D12 -> 207.69869 | G12: =rm_h_D*Смена!D12 -> 346.16449 | H12: =T_year_h/Смена!D12 -> 243.83342 | I12: =H12*Смена!E12/E_bat_kWh -> 282.46683 | J12: =MIN(bat_cycles/I12,bat_cal_y) -> 10 | K12: =MAX(0,life_y/J12-1) -> 0 | L12: =(price_ET*(k_CRF-salvage*k_SFF)+C_bat*K12/(1+r_disc)^J12*k_CRF)/H12 -> 4109.9313 | M12: =price_D*(k_CRF-salvage*k_SFF)/H12 -> 1560.5378 | N12: =B12+D12+F12 -> 8802.1779 | O12: =C12+E12+G12 -> 9843.0547 | P12: =N12+L12 -> 12912.109 | Q12: =O12+M12 -> 11403.593
A13: =Смена!A13 -> фреза 0.12×1.8 | B13: =wage_h*(Смена!D13+2*t_tr*(1+Смена!O13)/Смена!P13) -> 13461.52 | C13: =wage_h*(Смена!D13+2*t_tr/Смена!V13) -> 12063.272 | D13: =Смена!Q13*c_el -> 2557.0226 | E13: =Смена!W13*c_D -> 5611.4551 | F13: =k_RM_ET*rm_h_D*Смена!D13 -> 395.26863 | G13: =rm_h_D*Смена!D13 -> 658.78106 | H13: =T_year_h/Смена!D13 -> 128.12523 | I13: =H13*Смена!E13/E_bat_kWh -> 246.96424 | J13: =MIN(bat_cycles/I13,bat_cal_y) -> 10 | K13: =MAX(0,life_y/J13-1) -> 0 | L13: =(price_ET*(k_CRF-salvage*k_SFF)+C_bat*K13/(1+r_disc)^J13*k_CRF)/H13 -> 7821.5558 | M13: =price_D*(k_CRF-salvage*k_SFF)/H13 -> 2969.8389 | N13: =B13+D13+F13 -> 16413.811 | O13: =C13+E13+G13 -> 18333.508 | P13: =N13+L13 -> 24235.367 | Q13: =O13+M13 -> 21303.347
... A17: =Смена!A17 -> фреза 0.16×2.7 | B17: =wage_h*(Смена!D17+2*t_tr*(1+Смена!O17)/Смена!P17) -> 9202.8522 | C17: =wage_h*(Смена!D17+2*t_tr/Смена!V17) -> 8248.1231 | D17: =Смена!Q17*c_el -> 2761.392 | E17: =Смена!W17*c_D -> 5122.2479 | F17: =k_RM_ET*rm_h_D*Смена!D17 -> 270.22201 | G17: =rm_h_D*Смена!D17 -> 450.37001 | H17: =T_year_h/Смена!D17 -> 187.41584 | I17: =H17*Смена!E17/E_bat_kWh -> 402.88416 | J17: =MIN(bat_cycles/I17,bat_cal_y) -> 7.4463092 | K17: =MAX(0,life_y/J17-1) -> 0.34294719 | L17: =(price_ET*(k_CRF-salvage*k_SFF)+C_bat*K17/(1+r_disc)^J17*k_CRF)/H17 -> 5695.0716 | M17: =price_D*(k_CRF-salvage*k_SFF)/H17 -> 2030.3048 | N17: =B17+D17+F17 -> 12234.466 | O17: =C17+E17+G17 -> 13820.741 | P17: =N17+L17 -> 17929.538 | Q17: =O17+M17 -> 15851.046

Sheet Веса
A1: Матрица парных сравнений групп (изменяемая: верхний треугольник; нижний — обратные значения)
A2: Группа | B2: Энергет. | C2: Технолог. | D2: Экономич. | E2: Экологич. | F2: Автономн. | G2: Геом. среднее | H2: Вес w | I2: (A·w)ᵢ/wᵢ
A3: Энергетические | B3: 1 | C3: 0.5 | D3: 0.5 | E3: 2 | F3: 1 | G3: =GEOMEAN(B3:F3) -> 0.87055056 | H3: =G3/SUM($G$3:$G$7) -> 0.15779522 | I3: =SUMPRODUCT(B3:F3,$B$9:$F$9)/H3 -> 5.0101302
A4: Технологические | B4: =1/C3 -> 2 | C4: 1 | D4: 1 | E4: 3 | F4: 2 | G4: =GEOMEAN(B4:F4) -> 1.6437518 | H4: =G4/SUM($G$3:$G$7) -> 0.29794499 | I4: =SUMPRODUCT(B4:F4,$B$9:$F$9)/H4 -> 5.0097489
A5: Экономические | B5: =1/D3 -> 2 | C5: =1/D4 -> 1 | D5: 1 | E5: 3 | F5: 2 | G5: =GEOMEAN(B5:F5) -> 1.6437518 | H5: =G5/SUM($G$3:$G$7) -> 0.29794499 | I5: =SUMPRODUCT(B5:F5,$B$9:$F$9)/H5 -> 5.0097489
A6: Экологические | B6: =1/E3 -> 0.5 | C6: =1/E4 -> 0.33333333 | D6: =1/E5 -> 0.33333333 | E6: 1 | F6: 0.5 | G6: =GEOMEAN(B6:F6) -> 0.48835934 | H6: =G6/SUM($G$3:$G$7) -> 0.088519579 | I6: =SUMPRODUCT(B6:F6,$B$9:$F$9)/H6 -> 5.0265127
A7: Автономность | B7: =1/F3 -> 1 | C7: =1/F4 -> 0.5 | D7: =1/F5 -> 0.5 | E7: =1/F6 -> 2 | F7: 1 | G7: =GEOMEAN(B7:F7) -> 0.87055056 | H7: =G7/SUM($G$3:$G$7) -> 0.15779522 | I7: =SUMPRODUCT(B7:F7,$B$9:$F$9)/H7 -> 5.0101302
A9: wᵀ | B9: =H3 -> 0.15779522 | C9: =H4 -> 0.29794499 | D9: =H5 -> 0.29794499 | E9: =H6 -> 0.088519579 | F9: =H7 -> 0.15779522
A10: λ_max | B10: =AVERAGE(I3:I7) -> 5.0132542
A11: CI | B11: =(B10-5)/4 -> 0.0033135454
A12: CR (RI = 1,12) | B12: =B11/1.12 -> 0.0029585226
A15: Локальные матрицы (внутри групп)
A16: Энергетические | B16: I1 | C16: I2 | D16: Геом. ср. | E16: Лок. вес
A17: I1 | B17: 1 | C17: 0.5 | D17: =GEOMEAN(B17:C17) -> 0.70710678 | E17: =D17/SUM($D$17:$D$18) -> 0.33333333
A18: I2 | B18: =1/C17 -> 2 | C18: 1 | D18: =GEOMEAN(B18:C18) -> 1.4142136 | E18: =D18/SUM($D$17:$D$18) -> 0.66666667
A20: Технологические | B20: I3 | C20: I4 | D20: I5 | E20: Геом. ср. | F20: Лок. вес
A21: I3 | B21: 1 | C21: 3 | D21: 2 | E21: =GEOMEAN(B21:D21) -> 1.8171206 | F21: =E21/SUM($E$21:$E$23) -> 0.53961455
A22: I4 | B22: =1/C21 -> 0.33333333 | C22: 1 | D22: 0.5 | E22: =GEOMEAN(B22:D22) -> 0.55032121 | F22: =E22/SUM($E$21:$E$23) -> 0.16342412
A23: I5 | B23: =1/D21 -> 0.5 | C23: =1/D22 -> 2 | D23: 1 | E23: =GEOMEAN(B23:D23) -> 1 | F23: =E23/SUM($E$21:$E$23) -> 0.29696133
A25: Экономические | B25: I6 | C25: I7 | D25: Геом. ср. | E25: Лок. вес
A26: I6 | B26: 1 | C26: 0.5 | D26: =GEOMEAN(B26:C26) -> 0.70710678 | E26: =D26/SUM($D$26:$D$27) -> 0.33333333
A27: I7 | B27: =1/C26 -> 2 | C27: 1 | D27: =GEOMEAN(B27:C27) -> 1.4142136 | E27: =D27/SUM($D$26:$D$27) -> 0.66666667
A29: Экологические | B29: I8 | C29: I9 | D29: Геом. ср. | E29: Лок. вес
A30: I8 | B30: 1 | C30: 2 | D30: =GEOMEAN(B30:C30) -> 1.4142136 | E30: =D30/SUM($D$30:$D$31) -> 0.66666667
A31: I9 | B31: =1/C30 -> 0.5 | C31: 1 | D31: =GEOMEAN(B31:C31) -> 0.70710678 | E31: =D31/SUM($D$30:$D$31) -> 0.33333333
A33: Автономность | B33: I10 | C33: Геом. ср. | D33: Лок. вес
A34: I10 | B34: 1 | C34: =GEOMEAN(B34:B34) -> 1 | D34: =C34/SUM($C$34:$C$34) -> 1
A37: Итоговые веса
A38: Код | B38: Группа | C38: w МАИ | D38: w энтроп. | E38: w итог
A39: I1 | B39: Энергетические | C39: =$H$3*$E$17 -> 0.052598406 | D39: =Энтропия!B$40 -> 0.089237252 | E39: =(alpha_w*C39+(1-alpha_w)*D39)/(alpha_w*SUM($C$39:$C$48)+(1-alpha_w)*SUM($D$39:$D$48)) -> 0.070917829
A40: I2 | B40: Энергетические | C40: =$H$3*$E$18 -> 0.10519681 | D40: =Энтропия!C$40 -> 0.067220688 | E40: =(alpha_w*C40+(1-alpha_w)*D40)/(alpha_w*SUM($C$39:$C$48)+(1-alpha_w)*SUM($D$39:$D$48)) -> 0.08620875
A41: I3 | B41: Технологические | C41: =$H$4*$F$21 -> 0.16077545 | D41: =Энтропия!D$40 -> 0.14841184 | E41: =(alpha_w*C41+(1-alpha_w)*D41)/(alpha_w*SUM($C$39:$C$48)+(1-alpha_w)*SUM($D$39:$D$48)) -> 0.15459365
A42: I4 | B42: Технологические | C42: =$H$4*$F$22 -> 0.048691398 | D42: =Энтропия!E$40 -> 0.17940887 | E42: =(alpha_w*C42+(1-alpha_w)*D42)/(alpha_w*SUM($C$39:$C$48)+(1-alpha_w)*SUM($D$39:$D$48)) -> 0.11405013
A43: I5 | B43: Технологические | C43: =$H$4*$F$23 -> 0.088478141 | D43: =Энтропия!F$40 -> 0.03235588 | E43: =(alpha_w*C43+(1-alpha_w)*D43)/(alpha_w*SUM($C$39:$C$48)+(1-alpha_w)*SUM($D$39:$D$48)) -> 0.060417011
A44: I6 | B44: Экономические | C44: =$H$5*$E$26 -> 0.099314997 | D44: =Энтропия!G$40 -> 0.077299136 | E44: =(alpha_w*C44+(1-alpha_w)*D44)/(alpha_w*SUM($C$39:$C$48)+(1-alpha_w)*SUM($D$39:$D$48)) -> 0.088307067
A45: I7 | B45: Экономические | C45: =$H$5*$E$27 -> 0.19862999 | D45: =Энтропия!H$40 -> 0.075305843 | E45: =(alpha_w*C45+(1-alpha_w)*D45)/(alpha_w*SUM($C$39:$C$48)+(1-alpha_w)*SUM($D$39:$D$48)) -> 0.13696792
A46: I8 | B46: Экологические | C46: =$H$6*$E$30 -> 0.059013053 | D46: =Энтропия!I$40 -> 0.067856399 | E46: =(alpha_w*C46+(1-alpha_w)*D46)/(alpha_w*SUM($C$39:$C$48)+(1-alpha_w)*SUM($D$39:$D$48)) -> 0.063434726
A47: I9 | B47: Экологические | C47: =$H$6*$E$31 -> 0.029506526 | D47: =Энтропия!J$40 -> 0.16767249 | E47: =(alpha_w*C47+(1-alpha_w)*D47)/(alpha_w*SUM($C$39:$C$48)+(1-alpha_w)*SUM($D$39:$D$48)) -> 0.098589506
A48: I10 | B48: Автономность | C48: =$H$7*$D$34 -> 0.15779522 | D48: =Энтропия!K$40 -> 0.095231611 | E48: =(alpha_w*C48+(1-alpha_w)*D48)/(alpha_w*SUM($C$39:$C$48)+(1-alpha_w)*SUM($D$39:$D$48)) -> 0.12651341

Sheet Показатели
A1: Режим | B1: Допустим ЭТ и Д | C1: S_зад, га | D1: I1 ЭТ | E1: I2 ЭТ | F1: I3 ЭТ | G1: I4 ЭТ | H1: I5 ЭТ | I1: I6 ЭТ | J1: I7 ЭТ | K1: I8 ЭТ | L1: I9 ЭТ | M1: I10 ЭТ | N1: I1 Д | O1: I2 Д | P1: I3 Д | Q1: I4 Д | R1: I5 Д | S1: I6 Д | T1: I7 Д | U1: I8 Д | V1: I9 Д | W1: I10 Д | X1: d I1 | Y1: d I2 | Z1: d I3 | AA1: d I4 | AB1: d I5 | AC1: d I6 | AD1: d I7 | AE1: d I8 | AF1: d I9 | AG1: d I10 | AH1: Комплексный показатель I
A2: =Смена!A2 -> культиватор 0.08×3.6 | B2: =AND(Энергетика!Q2,Энергетика!R2) -> TRUE | C2: =IF(S_task>0,S_task,Смена!V2) -> 2.8207157 | D2: =3.6*Смена!Q2 -> 79.35943 | E2: =3.6*Смена!Q2*PEF_el -> 198.39858 | F2: =MIN(1,Смена!P2/C2) -> 0.29216555 | G2: =100*Энергетика!I2 -> 6.0506771 | H2: =100*Энергетика!O2 -> 53.922011 | I2: =Экономика!N2 -> 8106.1761 | J2: =Экономика!P2 -> 12387.355 | K2: =Смена!Q2*EF_grid -> 13.358837 | L2: =0 -> 0 | M2: =MIN(1,Смена!H2/C2) -> 0.30803856 | N2: =Смена!W2*LHV_D -> 273.77672 | O2: =Смена!W2*LHV_D*PEF_D -> 314.84323 | P2: =MIN(1,Смена!V2/C2) -> 1 | Q2: =100*Энергетика!K2 -> 7.1383424 | R2: =100*Энергетика!P2 -> 58.522725 | S2: =Экономика!O2 -> 9594.1558 | T2: =Экономика!Q2 -> 11219.716 | U2: =Смена!W2*EF_D -> 20.437928 | V2: =Смена!W2*EF_D -> 20.437928 | W2: =MIN(1,Смена!X2/C2) -> 1 | X2: =IF(MAX(ABS(D2),ABS(N2))=0,0,-1*(D2-N2)/MAX(ABS(D2),ABS(N2))) -> 0.71013083 | Y2: =IF(MAX(ABS(E2),ABS(O2))=0,0,-1*(E2-O2)/MAX(ABS(E2),ABS(O2))) -> 0.36984963 | Z2: =IF(MAX(ABS(F2),ABS(P2))=0,0,1*(F2-P2)/MAX(ABS(F2),ABS(P2))) -> -0.70783445 | AA2: =IF(MAX(ABS(G2),ABS(Q2))=0,0,-1*(G2-Q2)/MAX(ABS(G2),ABS(Q2))) -> 0.15236945 | AB2: =IF(MAX(ABS(H2),ABS(R2))=0,0,1*(H2-R2)/MAX(ABS(H2),ABS(R2))) -> -0.07861415 | AC2: =IF(MAX(ABS(I2),ABS(S2))=0,0,-1*(I2-S2)/MAX(ABS(I2),ABS(S2))) -> 0.1550923 | AD2: =IF(MAX(ABS(J2),ABS(T2))=0,0,-1*(J2-T2)/MAX(ABS(J2),ABS(T2))) -> -0.094260522 | AE2: =IF(MAX(ABS(K2),ABS(U2))=0,0,-1*(K2-U2)/MAX(ABS(K2),ABS(U2))) -> 0.34637026 | AF2: =IF(MAX(ABS(L2),ABS(V2))=0,0,-1*(L2-V2)/MAX(ABS(L2),ABS(V2))) -> 1 | AG2: =IF(MAX(ABS(M2),ABS(W2))=0,0,1*(M2-W2)/MAX(ABS(M2),ABS(W2))) -> -0.69196144 | AH2: =IF(B2,Веса!$E$39*X2+Веса!$E$40*Y2+Веса!$E$41*Z2+Веса!$E$42*AA2+Веса!$E$43*AB2+Веса!$E$44*AC2+Веса!$E$45*AD2+Веса!$E$46*AE2+Веса!$E$47*AF2+Веса!$E$48*AG2,"") -> 0.01925071
A3: =Смена!A3 -> культиватор 0.08×4.5 | B3: =AND(Энергетика!Q3,Энергетика!R3) -> TRUE | C3: =IF(S_task>0,S_task,Смена!V3) -> 3.4364663 | D3: =3.6*Смена!Q3 -> 83.924166 | E3: =3.6*Смена!Q3*PEF_el -> 209.81042 | F3: =MIN(1,Смена!P3/C3) -> 0.26459019 | G3: =100*Энергетика!I3 -> 6.2810882 | H3: =100*Энергетика!O3 -> 41.412372 | I3: =Экономика!N3 -> 7277.4971 | J3: =Экономика!P3 -> 10785.42 | K3: =Смена!Q3*EF_grid -> 14.127235 | L3: =0 -> 0 | M3: =MIN(1,Смена!H3/C3) -> 0.24874198 | N3: =Смена!W3*LHV_D -> 248.78045 | O3: =Смена!W3*LHV_D*PEF_D -> 286.09752 | P3: =MIN(1,Смена!V3/C3) -> 1 | Q3: =100*Энергетика!K3 -> 7.4215979 | R3: =100*Энергетика!P3 -> 47.179836 | S3: =Экономика!O3 -> 8096.4419 | T3: =Экономика!Q3 -> 9428.3977 | U3: =Смена!W3*EF_D -> 18.571911 | V3: =Смена!W3*EF_D -> 18.571911 | W3: =MIN(1,Смена!X3/C3) -> 0.93743074 | X3: =IF(MAX(ABS(D3),ABS(N3))=0,0,-1*(D3-N3)/MAX(ABS(D3),ABS(N3))) -> 0.66265771 | Y3: =IF(MAX(ABS(E3),ABS(O3))=0,0,-1*(E3-O3)/MAX(ABS(E3),ABS(O3))) -> 0.26664721 | Z3: =IF(MAX(ABS(F3),ABS(P3))=0,0,1*(F3-P3)/MAX(ABS(F3),ABS(P3))) -> -0.73540981 | AA3: =IF(MAX(ABS(G3),ABS(Q3))=0,0,-1*(G3-Q3)/MAX(ABS(G3),ABS(Q3))) -> 0.1536744 | AB3: =IF(MAX(ABS(H3),ABS(R3))=0,0,1*(H3-R3)/MAX(ABS(H3),ABS(R3))) -> -0.12224426 | AC3: =IF(MAX(ABS(I3),ABS(S3))=0,0,-1*(I3-S3)/MAX(ABS(I3),ABS(S3))) -> 0.10114873 | AD3: =IF(MAX(ABS(J3),ABS(T3))=0,0,-1*(J3-T3)/MAX(ABS(J3),ABS(T3))) -> -0.1258201 | AE3: =IF(MAX(ABS(K3),ABS(U3))=0,0,-1*(K3-U3)/MAX(ABS(K3),ABS(U3))) -> 0.23932252 | AF3: =IF(MAX(ABS(L3),ABS(V3))=0,0,-1*(L3-V3)/MAX(ABS(L3),ABS(V3))) -> 1 | AG3: =IF(MAX(ABS(M3),ABS(W3))=0,0,1*(M3-W3)/MAX(ABS(M3),ABS(W3))) -> -0.73465561 | AH3: =IF(B3,Веса!$E$39*X3+Веса!$E$40*Y3+Веса!$E$41*Z3+Веса!$E$42*AA3+Веса!$E$43*AB3+Веса!$E$44*AC3+Веса!$E$45*AD3+Веса!$E$46*AE3+Веса!$E$47*AF3+Веса!$E$48*AG3,"") -> -0.021041257
A4: =Смена!A4 -> культиватор 0.08×5.4 | B4: =AND(Энергетика!Q4,Энергетика!R4) -> TRUE | C4: =IF(S_task>0,S_task,Смена!V4) -> 4.019286 | D4: =3.6*Смена!Q4 -> 84.557098 | E4: =3.6*Смена!Q4*PEF_el -> 211.39275 | F4: =MIN(1,Смена!P4/C4) -> 0.26519447 | G4: =100*Энергетика!I4 -> 6.5676538 | H4: =100*Энергетика!O4 -> 28.046183 | I4: =Экономика!N4 -> 6372.2387 | J4: =Экономика!P4 -> 9364.6586 | K4: =Смена!Q4*EF_grid -> 14.233778 | L4: =0 -> 0 | M4: =MIN(1,Смена!H4/C4) -> 0.20799105 | N4: =Смена!W4*LHV_D -> 233.68607 | O4: =Смена!W4*LHV_D*PEF_D -> 268.73898 | P4: =MIN(1,Смена!V4/C4) -> 1 | Q4: =100*Энергетика!K4 -> 7.7753142 | R4: =100*Энергетика!P4 -> 35.009772 | S4: =Экономика!O4 -> 7113.1019 | T4: =Экономика!Q4 -> 8249.3215 | U4: =Смена!W4*EF_D -> 17.445088 | V4: =Смена!W4*EF_D -> 17.445088 | W4: =MIN(1,Смена!X4/C4) -> 0.85214177 | X4: =IF(MAX(ABS(D4),ABS(N4))=0,0,-1*(D4-N4)/MAX(ABS(D4),ABS(N4))) -> 0.63815944 | Y4: =IF(MAX(ABS(E4),ABS(O4))=0,0,-1*(E4-O4)/MAX(ABS(E4),ABS(O4))) -> 0.21339008 | Z4: =IF(MAX(ABS(F4),ABS(P4))=0,0,1*(F4-P4)/MAX(ABS(F4),ABS(P4))) -> -0.73480553 | AA4: =IF(MAX(ABS(G4),ABS(Q4))=0,0,-1*(G4-Q4)/MAX(ABS(G4),ABS(Q4))) -> 0.15531982 | AB4: =IF(MAX(ABS(H4),ABS(R4))=0,0,1*(H4-R4)/MAX(ABS(H4),ABS(R4))) -> -0.19890415 | AC4: =IF(MAX(ABS(I4),ABS(S4))=0,0,-1*(I4-S4)/MAX(ABS(I4),ABS(S4))) -> 0.10415472 | AD4: =IF(MAX(ABS(J4),ABS(T4))=0,0,-1*(J4-T4)/MAX(ABS(J4),ABS(T4))) -> -0.11910068 | AE4: =IF(MAX(ABS(K4),ABS(U4))=0,0,-1*(K4-U4)/MAX(ABS(K4),ABS(U4))) -> 0.18408104 | AF4: =IF(MAX(ABS(L4),ABS(V4))=0,0,-1*(L4-V4)/MAX(ABS(L4),ABS(V4))) -> 1 | AG4: =IF(MAX(ABS(M4),ABS(W4))=0,0,1*(M4-W4)/MAX(ABS(M4),ABS(W4))) -> -0.75591966 | AH4: =IF(B4,Веса!$E$39*X4+Веса!$E$40*Y4+Веса!$E$41*Z4+Веса!$E$42*AA4+Веса!$E$43*AB4+Веса!$E$44*AC4+Веса!$E$45*AD4+Веса!$E$46*AE4+Веса!$E$47*AF4+Веса!$E$48*AG4,"") -> -0.036728954
A5: =Смена!A5 -> культиватор 0.11×3.6 | B5: =AND(Энергетика!Q5,Энергетика!R5) -> TRUE | C5: =IF(S_task>0,S_task,Смена!V5) -> 2.8145311 | D5: =3.6*Смена!Q5 -> 104.56946 | E5: =3.6*Смена!Q5*PEF_el -> 261.42364 | F5: =MIN(1,Смена!P5/C5) -> 0.26470767 | G5: =100*Энергетика!I5 -> 9.1565024 | H5: =100*Энергетика!O5 -> 40.997449 | I5: =Экономика!N5 -> 8908.8573 | J5: =Экономика!P5 -> 13190.036 | K5: =Смена!Q5*EF_grid -> 17.602525 | L5: =0 -> 0 | M5: =MIN(1,Смена!H5/C5) -> 0.24326225 | N5: =Смена!W5*LHV_D -> 309.60075 | O5: =Смена!W5*LHV_D*PEF_D -> 356.04087 | P5: =MIN(1,Смена!V5/C5) -> 1 | Q5: =100*Энергетика!K5 -> 11.050596 | R5: =100*Энергетика!P5 -> 45.92633 | S5: =Экономика!O5 -> 9938.6818 | T5: =Экономика!Q5 -> 11564.242 | U5: =Смена!W5*EF_D -> 23.112257 | V5: =Смена!W5*EF_D -> 23.112257 | W5: =MIN(1,Смена!X5/C5) -> 0.91947236 | X5: =IF(MAX(ABS(D5),ABS(N5))=0,0,-1*(D5-N5)/MAX(ABS(D5),ABS(N5))) -> 0.66224418 | Y5: =IF(MAX(ABS(E5),ABS(O5))=0,0,-1*(E5-O5)/MAX(ABS(E5),ABS(O5))) -> 0.26574821 | Z5: =IF(MAX(ABS(F5),ABS(P5))=0,0,1*(F5-P5)/MAX(ABS(F5),ABS(P5))) -> -0.73529233 | AA5: =IF(MAX(ABS(G5),ABS(Q5))=0,0,-1*(G5-Q5)/MAX(ABS(G5),ABS(Q5))) -> 0.17140196 | AB5: =IF(MAX(ABS(H5),ABS(R5))=0,0,1*(H5-R5)/MAX(ABS(H5),ABS(R5))) -> -0.10732147 | AC5: =IF(MAX(ABS(I5),ABS(S5))=0,0,-1*(I5-S5)/MAX(ABS(I5),ABS(S5))) -> 0.10361781 | AD5: =IF(MAX(ABS(J5),ABS(T5))=0,0,-1*(J5-T5)/MAX(ABS(J5),ABS(T5))) -> -0.12325924 | AE5: =IF(MAX(ABS(K5),ABS(U5))=0,0,-1*(K5-U5)/MAX(ABS(K5),ABS(U5))) -> 0.23839002 | AF5: =IF(MAX(ABS(L5),ABS(V5))=0,0,-1*(L5-V5)/MAX(ABS(L5),ABS(V5))) -> 1 | AG5: =IF(MAX(ABS(M5),ABS(W5))=0,0,1*(M5-W5)/MAX(ABS(M5),ABS(W5))) -> -0.73543277 | AH5: =IF(B5,Веса!$E$39*X5+Веса!$E$40*Y5+Веса!$E$41*Z5+Веса!$E$42*AA5+Веса!$E$43*AB5+Веса!$E$44*AC5+Веса!$E$45*AD5+Веса!$E$46*AE5+Веса!$E$47*AF5+Веса!$E$48*AG5,"") -> -0.017795183
A6: =Смена!A6 -> культиватор 0.11×4.5 | B6: =AND(Энергетика!Q6,Энергетика!R6) -> TRUE | C6: =IF(S_task>0,S_task,Смена!V6) -> 3.4248258 | D6: =3.6*Смена!Q6 -> 104.99671 | E6: =3.6*Смена!Q6*PEF_el -> 262.49179 | F6: =MIN(1,Смена!P6/C6) -> 0.26548949 | G6: =100*Энергетика!I6 -> 9.5492968 | H6: =100*Энергетика!O6 -> 24.6025 | I6: =Экономика!N6 -> 7544.3575 | J6: =Экономика!P6 -> 11052.281 | K6: =Смена!Q6*EF_grid -> 17.674447 | L6: =0 -> 0 | M6: =MIN(1,Смена!H6/C6) -> 0.19569078 | N6: =Смена!W6*LHV_D -> 286.18624 | O6: =Смена!W6*LHV_D*PEF_D -> 329.11417 | P6: =MIN(1,Смена!V6/C6) -> 1 | Q6: =100*Энергетика!K6 -> 11.561591 | R6: =100*Энергетика!P6 -> 30.740084 | S6: =Экономика!O6 -> 8456.2376 | T6: =Экономика!Q6 -> 9788.1934 | U6: =Смена!W6*EF_D -> 21.364321 | V6: =Смена!W6*EF_D -> 21.364321 | W6: =MIN(1,Смена!X6/C6) -> 0.81613845 | X6: =IF(MAX(ABS(D6),ABS(N6))=0,0,-1*(D6-N6)/MAX(ABS(D6),ABS(N6))) -> 0.63311753 | Y6: =IF(MAX(ABS(E6),ABS(O6))=0,0,-1*(E6-O6)/MAX(ABS(E6),ABS(O6))) -> 0.20242941 | Z6: =IF(MAX(ABS(F6),ABS(P6))=0,0,1*(F6-P6)/MAX(ABS(F6),ABS(P6))) -> -0.73451051 | AA6: =IF(MAX(ABS(G6),ABS(Q6))=0,0,-1*(G6-Q6)/MAX(ABS(G6),ABS(Q6))) -> 0.17404991 | AB6: =IF(MAX(ABS(H6),ABS(R6))=0,0,1*(H6-R6)/MAX(ABS(H6),ABS(R6))) -> -0.19966061 | AC6: =IF(MAX(ABS(I6),ABS(S6))=0,0,-1*(I6-S6)/MAX(ABS(I6),ABS(S6))) -> 0.1078352 | AD6: =IF(MAX(ABS(J6),ABS(T6))=0,0,-1*(J6-T6)/MAX(ABS(J6),ABS(T6))) -> -0.11437344 | AE6: =IF(MAX(ABS(K6),ABS(U6))=0,0,-1*(K6-U6)/MAX(ABS(K6),ABS(U6))) -> 0.17271197 | AF6: =IF(MAX(ABS(L6),ABS(V6))=0,0,-1*(L6-V6)/MAX(ABS(L6),ABS(V6))) -> 1 | AG6: =IF(MAX(ABS(M6),ABS(W6))=0,0,1*(M6-W6)/MAX(ABS(M6),ABS(W6))) -> -0.76022356 | AH6: =IF(B6,Веса!$E$39*X6+Веса!$E$40*Y6+Веса!$E$41*Z6+Веса!$E$42*AA6+Веса!$E$43*AB6+Веса!$E$44*AC6+Веса!$E$45*AD6+Веса!$E$46*AE6+Веса!$E$47*AF6+Веса!$E$48*AG6,"") -> -0.036188548
A7: =Смена!A7 -> культиватор 0.11×5.4 | B7: =AND(Энергетика!Q7,Энергетика!R7) -> TRUE | C7: =IF(S_task>0,S_task,Смена!V7) -> 4.0024291 | D7: =3.6*Смена!Q7 -> 106.66149 | E7: =3.6*Смена!Q7*PEF_el -> 266.65372 | F7: =MIN(1,Смена!P7/C7) -> 0.26631138 | G7: =100*Энергетика!I7 -> 10.043958 | H7: =100*Энергетика!O7 -> 6.8865962 | I7: =Экономика!N7 -> 6652.1663 | J7: =Экономика!P7 -> 9732.9746 | K7: =Смена!Q7*EF_grid -> 17.954684 | L7: =0 -> 0 | M7: =MIN(1,Смена!H7/C7) -> 0.16285377 | N7: =Смена!W7*LHV_D -> 273.10395 | O7: =Смена!W7*LHV_D*PEF_D -> 314.06954 | P7: =MIN(1,Смена!V7/C7) -> 1 | Q7: =100*Энергетика!K7 -> 12.211049 | R7: =100*Энергетика!P7 -> 14.220933 | S7: =Экономика!O7 -> 7492.2531 | T7: =Экономика!Q7 -> 8628.4727 | U7: =Смена!W7*EF_D -> 20.387704 | V7: =Смена!W7*EF_D -> 20.387704 | W7: =MIN(1,Смена!X7/C7) -> 0.7308435 | X7: =IF(MAX(ABS(D7),ABS(N7))=0,0,-1*(D7-N7)/MAX(ABS(D7),ABS(N7))) -> 0.60944728 | Y7: =IF(MAX(ABS(E7),ABS(O7))=0,0,-1*(E7-O7)/MAX(ABS(E7),ABS(O7))) -> 0.15097235 | Z7: =IF(MAX(ABS(F7),ABS(P7))=0,0,1*(F7-P7)/MAX(ABS(F7),ABS(P7))) -> -0.73368862 | AA7: =IF(MAX(ABS(G7),ABS(Q7))=0,0,-1*(G7-Q7)/MAX(ABS(G7),ABS(Q7))) -> 0.17746973 | AB7: =IF(MAX(ABS(H7),ABS(R7))=0,0,1*(H7-R7)/MAX(ABS(H7),ABS(R7))) -> -0.51574232 | AC7: =IF(MAX(ABS(I7),ABS(S7))=0,0,-1*(I7-S7)/MAX(ABS(I7),ABS(S7))) -> 0.1121274 | AD7: =IF(MAX(ABS(J7),ABS(T7))=0,0,-1*(J7-T7)/MAX(ABS(J7),ABS(T7))) -> -0.1134804 | AE7: =IF(MAX(ABS(K7),ABS(U7))=0,0,-1*(K7-U7)/MAX(ABS(K7),ABS(U7))) -> 0.11933762 | AF7: =IF(MAX(ABS(L7),ABS(V7))=0,0,-1*(L7-V7)/MAX(ABS(L7),ABS(V7))) -> 1 | AG7: =IF(MAX(ABS(M7),ABS(W7))=0,0,1*(M7-W7)/MAX(ABS(M7),ABS(W7))) -> -0.77717011 | AH7: =IF(B7,Веса!$E$39*X7+Веса!$E$40*Y7+Веса!$E$41*Z7+Веса!$E$42*AA7+Веса!$E$43*AB7+Веса!$E$44*AC7+Веса!$E$45*AD7+Веса!$E$46*AE7+Веса!$E$47*AF7+Веса!$E$48*AG7,"") -> -0.065911268
A8: =Смена!A8 -> культиватор 0.14×3.6 | B8: =AND(Энергетика!Q8,Энергетика!R8) -> FALSE | C8: =IF(S_task>0,S_task,Смена!V8) -> 2.8056835 | D8: =3.6*Смена!Q8 -> 127.32688 | E8: =3.6*Смена!Q8*PEF_el -> 318.3172 | F8: =MIN(1,Смена!P8/C8) -> 0.26554242 | G8: =100*Энергетика!I8 -> 13.090327 | H8: =100*Энергетика!O8 -> 26.474313 | I8: =Экономика!N8 -> 9197.0548 | J8: =Экономика!P8 -> 13478.233 | K8: =Смена!Q8*EF_grid -> 21.433358 | L8: =0 -> 0 | M8: =MIN(1,Смена!H8/C8) -> 0.19707741 | N8: =Смена!W8*LHV_D -> 351.94782 | O8: =Смена!W8*LHV_D*PEF_D -> 404.74 | P8: =MIN(1,Смена!V8/C8) -> 1 | Q8: =100*Энергетика!K8 -> 16.380656 | R8: =100*Энергетика!P8 -> 31.037184 | S8: =Экономика!O8 -> 10346.007 | T8: =Экономика!Q8 -> 11971.567 | U8: =Смена!W8*EF_D -> 26.273542 | V8: =Смена!W8*EF_D -> 26.273542 | W8: =MIN(1,Смена!X8/C8) -> 0.81001461 | X8: =IF(MAX(ABS(D8),ABS(N8))=0,0,-1*(D8-N8)/MAX(ABS(D8),ABS(N8))) -> 0.63822229 | Y8: =IF(MAX(ABS(E8),ABS(O8))=0,0,-1*(E8-O8)/MAX(ABS(E8),ABS(O8))) -> 0.21352671 | Z8: =IF(MAX(ABS(F8),ABS(P8))=0,0,1*(F8-P8)/MAX(ABS(F8),ABS(P8))) -> -0.73445758 | AA8: =IF(MAX(ABS(G8),ABS(Q8))=0,0,-1*(G8-Q8)/MAX(ABS(G8),ABS(Q8))) -> 0.20086676 | AB8: =IF(MAX(ABS(H8),ABS(R8))=0,0,1*(H8-R8)/MAX(ABS(H8),ABS(R8))) -> -0.14701307 | AC8: =IF(MAX(ABS(I8),ABS(S8))=0,0,-1*(I8-S8)/MAX(ABS(I8),ABS(S8))) -> 0.11105268 | AD8: =IF(MAX(ABS(J8),ABS(T8))=0,0,-1*(J8-T8)/MAX(ABS(J8),ABS(T8))) -> -0.11178516 | AE8: =IF(MAX(ABS(K8),ABS(U8))=0,0,-1*(K8-U8)/MAX(ABS(K8),ABS(U8))) -> 0.18422276 | AF8: =IF(MAX(ABS(L8),ABS(V8))=0,0,-1*(L8-V8)/MAX(ABS(L8),ABS(V8))) -> 1 | AG8: =IF(MAX(ABS(M8),ABS(W8))=0,0,1*(M8-W8)/MAX(ABS(M8),ABS(W8))) -> -0.75669895 | AH8: =IF(B8,Веса!$E$39*X8+Веса!$E$40*Y8+Веса!$E$41*Z8+Веса!$E$42*AA8+Веса!$E$43*AB8+Веса!$E$44*AC8+Веса!$E$45*AD8+Веса!$E$46*AE8+Веса!$E$47*AF8+Веса!$E$48*AG8,"")
A9: =Смена!A9 -> культиватор 0.14×4.5 | B9: =AND(Энергетика!Q9,Энергетика!R9) -> FALSE | C9: =IF(S_task>0,S_task,Смена!V9) -> 3.4108407 | D9: =3.6*Смена!Q9 -> 128.89836 | E9: =3.6*Смена!Q9*PEF_el -> 322.24591 | F9: =MIN(1,Смена!P9/C9) -> 0.26657805 | G9: =100*Энергетика!I9 -> 13.74799 | H9: =100*Энергетика!O9 -> 5.5358134 | I9: =Экономика!N9 -> 7847.0453 | J9: =Экономика!P9 -> 11484.37 | K9: =Смена!Q9*EF_grid -> 21.697891 | L9: =0 -> 0 | M9: =MIN(1,Смена!H9/C9) -> 0.15783414 | N9: =Смена!W9*LHV_D -> 331.12675 | O9: =Смена!W9*LHV_D*PEF_D -> 380.79577 | P9: =MIN(1,Смена!V9/C9) -> 1 | Q9: =100*Энергетика!K9 -> 17.32605 | R9: =100*Энергетика!P9 -> 10.988885 | S9: =Экономика!O9 -> 8888.5106 | T9: =Экономика!Q9 -> 10220.466 | U9: =Смена!W9*EF_D -> 24.719212 | V9: =Смена!W9*EF_D -> 24.719212 | W9: =MIN(1,Смена!X9/C9) -> 0.70706584 | X9: =IF(MAX(ABS(D9),ABS(N9))=0,0,-1*(D9-N9)/MAX(ABS(D9),ABS(N9))) -> 0.61072803 | Y9: =IF(MAX(ABS(E9),ABS(O9))=0,0,-1*(E9-O9)/MAX(ABS(E9),ABS(O9))) -> 0.15375659 | Z9: =IF(MAX(ABS(F9),ABS(P9))=0,0,1*(F9-P9)/MAX(ABS(F9),ABS(P9))) -> -0.73342195 | AA9: =IF(MAX(ABS(G9),ABS(Q9))=0,0,-1*(G9-Q9)/MAX(ABS(G9),ABS(Q9))) -> 0.20651333 | AB9: =IF(MAX(ABS(H9),ABS(R9))=0,0,1*(H9-R9)/MAX(ABS(H9),ABS(R9))) -> -0.49623519 | AC9: =IF(MAX(ABS(I9),ABS(S9))=0,0,-1*(I9-S9)/MAX(ABS(I9),ABS(S9))) -> 0.11716983 | AD9: =IF(MAX(ABS(J9),ABS(T9))=0,0,-1*(J9-T9)/MAX(ABS(J9),ABS(T9))) -> -0.11005427 | AE9: =IF(MAX(ABS(K9),ABS(U9))=0,0,-1*(K9-U9)/MAX(ABS(K9),ABS(U9))) -> 0.12222561 | AF9: =IF(MAX(ABS(L9),ABS(V9))=0,0,-1*(L9-V9)/MAX(ABS(L9),ABS(V9))) -> 1 | AG9: =IF(MAX(ABS(M9),ABS(W9))=0,0,1*(M9-W9)/MAX(ABS(M9),ABS(W9))) -> -0.7767759 | AH9: =IF(B9,Веса!$E$39*X9+Веса!$E$40*Y9+Веса!$E$41*Z9+Веса!$E$42*AA9+Веса!$E$43*AB9+Веса!$E$44*AC9+Веса!$E$45*AD9+Веса!$E$46*AE9+Веса!$E$47*AF9+Веса!$E$48*AG9,"")
A10: =Смена!A10 -> фреза 0.08×1.8 | B10: =AND(Энергетика!Q10,Энергетика!R10) -> TRUE | C10: =IF(S_task>0,S_task,Смена!V10) -> 1.5439367 | D10: =3.6*Смена!Q10 -> 146.52326 | E10: =3.6*Смена!Q10*PEF_el -> 366.30815 | F10: =MIN(1,Смена!P10/C10) -> 0.2891018 | G10: =100*Энергетика!I10 -> 0 | H10: =100*Энергетика!O10 -> 54.786632 | I10: =Экономика!N10 -> 14836.865 | J10: =Экономика!P10 -> 22658.42 | K10: =Смена!Q10*EF_grid -> 24.664749 | L10: =0 -> 0 | M10: =MIN(1,Смена!H10/C10) -> 0.30480835 | N10: =Смена!W10*LHV_D -> 505.57709 | O10: =Смена!W10*LHV_D*PEF_D -> 581.41365 | P10: =MIN(1,Смена!V10/C10) -> 1 | Q10: =100*Энергетика!K10 -> 0 | R10: =100*Энергетика!P10 -> 58.724663 | S10: =Экономика!O10 -> 17580.036 | T10: =Экономика!Q10 -> 20549.875 | U10: =Смена!W10*EF_D -> 37.742245 | V10: =Смена!W10*EF_D -> 37.742245 | W10: =MIN(1,Смена!X10/C10) -> 1 | X10: =IF(MAX(ABS(D10),ABS(N10))=0,0,-1*(D10-N10)/MAX(ABS(D10),ABS(N10))) -> 0.71018612 | Y10: =IF(MAX(ABS(E10),ABS(O10))=0,0,-1*(E10-O10)/MAX(ABS(E10),ABS(O10))) -> 0.36996982 | Z10: =IF(MAX(ABS(F10),ABS(P10))=0,0,1*(F10-P10)/MAX(ABS(F10),ABS(P10))) -> -0.7108982 | AA10: =IF(MAX(ABS(G10),ABS(Q10))=0,0,-1*(G10-Q10)/MAX(ABS(G10),ABS(Q10))) -> 0 | AB10: =IF(MAX(ABS(H10),ABS(R10))=0,0,1*(H10-R10)/MAX(ABS(H10),ABS(R10))) -> -0.067059231 | AC10: =IF(MAX(ABS(I10),ABS(S10))=0,0,-1*(I10-S10)/MAX(ABS(I10),ABS(S10))) -> 0.15603903 | AD10: =IF(MAX(ABS(J10),ABS(T10))=0,0,-1*(J10-T10)/MAX(ABS(J10),ABS(T10))) -> -0.093057907 | AE10: =IF(MAX(ABS(K10),ABS(U10))=0,0,-1*(K10-U10)/MAX(ABS(K10),ABS(U10))) -> 0.34649492 | AF10: =IF(MAX(ABS(L10),ABS(V10))=0,0,-1*(L10-V10)/MAX(ABS(L10),ABS(V10))) -> 1 | AG10: =IF(MAX(ABS(M10),ABS(W10))=0,0,1*(M10-W10)/MAX(ABS(M10),ABS(W10))) -> -0.69519165 | AH10: =IF(B10,Веса!$E$39*X10+Веса!$E$40*Y10+Веса!$E$41*Z10+Веса!$E$42*AA10+Веса!$E$43*AB10+Веса!$E$44*AC10+Веса!$E$45*AD10+Веса!$E$46*AE10+Веса!$E$47*AF10+Веса!$E$48*AG10,"") -> 0.0019592782
A11: =Смена!A11 -> фреза 0.08×2.7 | B11: =AND(Энергетика!Q11,Энергетика!R11) -> TRUE | C11: =IF(S_task>0,S_task,Смена!V11) -> 2.2526904 | D11: =3.6*Смена!Q11 -> 134.72306 | E11: =3.6*Смена!Q11*PEF_el -> 336.80765 | F11: =MIN(1,Смена!P11/C11) -> 0.2647969 | G11: =100*Энергетика!I11 -> 0 | H11: =100*Энергетика!O11 -> 39.932431 | I11: =Экономика!N11 -> 11179.192 | J11: =Экономика!P11 -> 16526.332 | K11: =Смена!Q11*EF_grid -> 22.678382 | L11: =0 -> 0 | M11: =MIN(1,Смена!H11/C11) -> 0.23522693 | N11: =Смена!W11*LHV_D -> 392.35728 | O11: =Смена!W11*LHV_D*PEF_D -> 451.21087 | P11: =MIN(1,Смена!V11/C11) -> 1 | Q11: =100*Энергетика!K11 -> 0 | R11: =100*Энергетика!P11 -> 45.269422 | S11: =Экономика!O11 -> 12467.827 | T11: =Экономика!Q11 -> 14498.132 | U11: =Смена!W11*EF_D -> 29.290181 | V11: =Смена!W11*EF_D -> 29.290181 | W11: =MIN(1,Смена!X11/C11) -> 0.9063062 | X11: =IF(MAX(ABS(D11),ABS(N11))=0,0,-1*(D11-N11)/MAX(ABS(D11),ABS(N11))) -> 0.65663168 | Y11: =IF(MAX(ABS(E11),ABS(O11))=0,0,-1*(E11-O11)/MAX(ABS(E11),ABS(O11))) -> 0.25354713 | Z11: =IF(MAX(ABS(F11),ABS(P11))=0,0,1*(F11-P11)/MAX(ABS(F11),ABS(P11))) -> -0.7352031 | AA11: =IF(MAX(ABS(G11),ABS(Q11))=0,0,-1*(G11-Q11)/MAX(ABS(G11),ABS(Q11))) -> 0 | AB11: =IF(MAX(ABS(H11),ABS(R11))=0,0,1*(H11-R11)/MAX(ABS(H11),ABS(R11))) -> -0.11789395 | AC11: =IF(MAX(ABS(I11),ABS(S11))=0,0,-1*(I11-S11)/MAX(ABS(I11),ABS(S11))) -> 0.10335683 | AD11: =IF(MAX(ABS(J11),ABS(T11))=0,0,-1*(J11-T11)/MAX(ABS(J11),ABS(T11))) -> -0.12272533 | AE11: =IF(MAX(ABS(K11),ABS(U11))=0,0,-1*(K11-U11)/MAX(ABS(K11),ABS(U11))) -> 0.22573433 | AF11: =IF(MAX(ABS(L11),ABS(V11))=0,0,-1*(L11-V11)/MAX(ABS(L11),ABS(V11))) -> 1 | AG11: =IF(MAX(ABS(M11),ABS(W11))=0,0,1*(M11-W11)/MAX(ABS(M11),ABS(W11))) -> -0.74045534 | AH11: =IF(B11,Веса!$E$39*X11+Веса!$E$40*Y11+Веса!$E$41*Z11+Веса!$E$42*AA11+Веса!$E$43*AB11+Веса!$E$44*AC11+Веса!$E$45*AD11+Веса!$E$46*AE11+Веса!$E$47*AF11+Веса!$E$48*AG11,"") -> -0.040806579
A12: =Смена!A12 -> фреза 0.08×3.6 | B12: =AND(Энергетика!Q12,Энергетика!R12) -> TRUE | C12: =IF(S_task>0,S_task,Смена!V12) -> 2.9246872 | D12: =3.6*Смена!Q12 -> 120.10218 | E12: =3.6*Смена!Q12*PEF_el -> 300.25544 | F12: =MIN(1,Смена!P12/C12) -> 0.26535173 | G12: =100*Энергетика!I12 -> 0 | H12: =100*Энергетика!O12 -> 27.891337 | I12: =Экономика!N12 -> 8802.1779 | J12: =Экономика!P12 -> 12912.109 | K12: =Смена!Q12*EF_grid -> 20.2172 | L12: =0 -> 0 | M12: =MIN(1,Смена!H12/C12) -> 0.20070365 | N12: =Смена!W12*LHV_D -> 328.60555 | O12: =Смена!W12*LHV_D*PEF_D -> 377.89638 | P12: =MIN(1,Смена!V12/C12) -> 1 | Q12: =100*Энергетика!K12 -> 0 | R12: =100*Энергетика!P12 -> 34.430235 | S12: =Экономика!O12 -> 9843.0547 | T12: =Экономика!Q12 -> 11403.593 | U12: =Смена!W12*EF_D -> 24.530999 | V12: =Смена!W12*EF_D -> 24.530999 | W12: =MIN(1,Смена!X12/C12) -> 0.83254414 | X12: =IF(MAX(ABS(D12),ABS(N12))=0,0,-1*(D12-N12)/MAX(ABS(D12),ABS(N12))) -> 0.63450959 | Y12: =IF(MAX(ABS(E12),ABS(O12))=0,0,-1*(E12-O12)/MAX(ABS(E12),ABS(O12))) -> 0.20545563 | Z12: =IF(MAX(ABS(F12),ABS(P12))=0,0,1*(F12-P12)/MAX(ABS(F12),ABS(P12))) -> -0.73464827 | AA12: =IF(MAX(ABS(G12),ABS(Q12))=0,0,-1*(G12-Q12)/MAX(ABS(G12),ABS(Q12))) -> 0 | AB12: =IF(MAX(ABS(H12),ABS(R12))=0,0,1*(H12-R12)/MAX(ABS(H12),ABS(R12))) -> -0.18991732 | AC12: =IF(MAX(ABS(I12),ABS(S12))=0,0,-1*(I12-S12)/MAX(ABS(I12),ABS(S12))) -> 0.10574733 | AD12: =IF(MAX(ABS(J12),ABS(T12))=0,0,-1*(J12-T12)/MAX(ABS(J12),ABS(T12))) -> -0.11682961 | AE12: =IF(MAX(ABS(K12),ABS(U12))=0,0,-1*(K12-U12)/MAX(ABS(K12),ABS(U12))) -> 0.17585095 | AF12: =IF(MAX(ABS(L12),ABS(V12))=0,0,-1*(L12-V12)/MAX(ABS(L12),ABS(V12))) -> 1 | AG12: =IF(MAX(ABS(M12),ABS(W12))=0,0,1*(M12-W12)/MAX(ABS(M12),ABS(W12))) -> -0.75892732 | AH12: =IF(B12,Веса!$E$39*X12+Веса!$E$40*Y12+Веса!$E$41*Z12+Веса!$E$42*AA12+Веса!$E$43*AB12+Веса!$E$44*AC12+Веса!$E$45*AD12+Веса!$E$46*AE12+Веса!$E$47*AF12+Веса!$E$48*AG12,"") -> -0.055269672
A13: =Смена!A13 -> фреза 0.12×1.8 | B13: =AND(Энергетика!Q13,Энергетика!R13) -> TRUE | C13: =IF(S_task>0,S_task,Смена!V13) -> 1.5394068 | D13: =3.6*Смена!Q13 -> 201.91448 | E13: =3.6*Смена!Q13*PEF_el -> 504.78621 | F13: =MIN(1,Смена!P13/C13) -> 0.26490451 | G13: =100*Энергетика!I13 -> 0 | H13: =100*Энергетика!O13 -> 39.359781 | I13: =Экономика!N13 -> 16413.811 | J13: =Экономика!P13 -> 24235.367 | K13: =Смена!Q13*EF_grid -> 33.988938 | L13: =0 -> 0 | M13: =MIN(1,Смена!H13/C13) -> 0.22916911 | N13: =Смена!W13*LHV_D -> 583.91663 | O13: =Смена!W13*LHV_D*PEF_D -> 671.50413 | P13: =MIN(1,Смена!V13/C13) -> 1 | Q13: =100*Энергетика!K13 -> 0 | R13: =100*Энергетика!P13 -> 44.378437 | S13: =Экономика!O13 -> 18333.508 | T13: =Экономика!Q13 -> 21303.347 | U13: =Смена!W13*EF_D -> 43.590434 | V13: =Смена!W13*EF_D -> 43.590434 | W13: =MIN(1,Смена!X13/C13) -> 0.89094426 | X13: =IF(MAX(ABS(D13),ABS(N13))=0,0,-1*(D13-N13)/MAX(ABS(D13),ABS(N13))) -> 0.65420666 | Y13: =IF(MAX(ABS(E13),ABS(O13))=0,0,-1*(E13-O13)/MAX(ABS(E13),ABS(O13))) -> 0.24827535 | Z13: =IF(MAX(ABS(F13),ABS(P13))=0,0,1*(F13-P13)/MAX(ABS(F13),ABS(P13))) -> -0.73509549 | AA13: =IF(MAX(ABS(G13),ABS(Q13))=0,0,-1*(G13-Q13)/MAX(ABS(G13),ABS(Q13))) -> 0 | AB13: =IF(MAX(ABS(H13),ABS(R13))=0,0,1*(H13-R13)/MAX(ABS(H13),ABS(R13))) -> -0.11308771 | AC13: =IF(MAX(ABS(I13),ABS(S13))=0,0,-1*(I13-S13)/MAX(ABS(I13),ABS(S13))) -> 0.10470976 | AD13: =IF(MAX(ABS(J13),ABS(T13))=0,0,-1*(J13-T13)/MAX(ABS(J13),ABS(T13))) -> -0.12098104 | AE13: =IF(MAX(ABS(K13),ABS(U13))=0,0,-1*(K13-U13)/MAX(ABS(K13),ABS(U13))) -> 0.22026613 | AF13: =IF(MAX(ABS(L13),ABS(V13))=0,0,-1*(L13-V13)/MAX(ABS(L13),ABS(V13))) -> 1 | AG13: =IF(MAX(ABS(M13),ABS(W13))=0,0,1*(M13-W13)/MAX(ABS(M13),ABS(W13))) -> -0.74277952 | AH13: =IF(B13,Веса!$E$39*X13+Веса!$E$40*Y13+Веса!$E$41*Z13+Веса!$E$42*AA13+Веса!$E$43*AB13+Веса!$E$44*AC13+Веса!$E$45*AD13+Веса!$E$46*AE13+Веса!$E$47*AF13+Веса!$E$48*AG13,"") -> -0.041408544
... A17: =Смена!A17 -> фреза 0.16×2.7 | B17: =AND(Энергетика!Q17,Энергетика!R17) -> FALSE | C17: =IF(S_task>0,S_task,Смена!V17) -> 2.2338523 | D17: =3.6*Смена!Q17 -> 218.05245 | E17: =3.6*Смена!Q17*PEF_el -> 545.13112 | F17: =MIN(1,Смена!P17/C17) -> 0.26702994 | G17: =100*Энергетика!I17 -> 0 | H17: =100*Энергетика!O17 -> -1.6132205 | I17: =Экономика!N17 -> 12234.466 | J17: =Экономика!P17 -> 17929.538 | K17: =Смена!Q17*EF_grid -> 36.705495 | L17: =0 -> 0 | M17: =MIN(1,Смена!H17/C17) -> 0.14160564 | N17: =Смена!W17*LHV_D -> 533.01073 | O17: =Смена!W17*LHV_D*PEF_D -> 612.96234 | P17: =MIN(1,Смена!V17/C17) -> 1 | Q17: =100*Энергетика!K17 -> 0 | R17: =100*Энергетика!P17 -> 6.6339732 | S17: =Экономика!O17 -> 13820.741 | T17: =Экономика!Q17 -> 15851.046 | U17: =Смена!W17*EF_D -> 39.790216 | V17: =Смена!W17*EF_D -> 39.790216 | W17: =MIN(1,Смена!X17/C17) -> 0.67031207 | X17: =IF(MAX(ABS(D17),ABS(N17))=0,0,-1*(D17-N17)/MAX(ABS(D17),ABS(N17))) -> 0.59090421 | Y17: =IF(MAX(ABS(E17),ABS(O17))=0,0,-1*(E17-O17)/MAX(ABS(E17),ABS(O17))) -> 0.11066132 | Z17: =IF(MAX(ABS(F17),ABS(P17))=0,0,1*(F17-P17)/MAX(ABS(F17),ABS(P17))) -> -0.73297006 | AA17: =IF(MAX(ABS(G17),ABS(Q17))=0,0,-1*(G17-Q17)/MAX(ABS(G17),ABS(Q17))) -> 0 | AB17: =IF(MAX(ABS(H17),ABS(R17))=0,0,1*(H17-R17)/MAX(ABS(H17),ABS(R17))) -> -1.2431756 | AC17: =IF(MAX(ABS(I17),ABS(S17))=0,0,-1*(I17-S17)/MAX(ABS(I17),ABS(S17))) -> 0.11477495 | AD17: =IF(MAX(ABS(J17),ABS(T17))=0,0,-1*(J17-T17)/MAX(ABS(J17),ABS(T17))) -> -0.11592557 | AE17: =IF(MAX(ABS(K17),ABS(U17))=0,0,-1*(K17-U17)/MAX(ABS(K17),ABS(U17))) -> 0.077524604 | AF17: =IF(MAX(ABS(L17),ABS(V17))=0,0,-1*(L17-V17)/MAX(ABS(L17),ABS(V17))) -> 1 | AG17: =IF(MAX(ABS(M17),ABS(W17))=0,0,1*(M17-W17)/MAX(ABS(M17),ABS(W17))) -> -0.78874669 | AH17: =IF(B17,Веса!$E$39*X17+Веса!$E$40*Y17+Веса!$E$41*Z17+Веса!$E$42*AA17+Веса!$E$43*AB17+Веса!$E$44*AC17+Веса!$E$45*AD17+Веса!$E$46*AE17+Веса!$E$47*AF17+Веса!$E$48*AG17,"")

Sheet Энтропия
A1: Альтернатива | B1: I1 | C1: I2 | D1: I3 | E1: I4 | F1: I5 | G1: I6 | H1: I7 | I1: I8 | J1: I9 | K1: I10 | L1: Допустим | N1: z I1 | O1: z I2 | P1: z I3 | Q1: z I4 | R1: z I5 | S1: z I6 | T1: z I7 | U1: z I8 | V1: z I9 | W1: z I10 | Y1: p·ln p I1 | Z1: p·ln p I2 | AA1: p·ln p I3 | AB1: p·ln p I4 | AC1: p·ln p I5 | AD1: p·ln p I6 | AE1: p·ln p I7 | AF1: p·ln p I8 | AG1: p·ln p I9 | AH1: p·ln p I10
A2: =Показатели!A2&" ЭТ" -> культиватор 0.08×3.6 ЭТ | B2: =Показатели!D2 -> 79.35943 | C2: =Показатели!E2 -> 198.39858 | D2: =Показатели!F2 -> 0.29216555 | E2: =Показатели!G2 -> 6.0506771 | F2: =Показатели!H2 -> 53.922011 | G2: =Показатели!I2 -> 8106.1761 | H2: =Показатели!J2 -> 12387.355 | I2: =Показатели!K2 -> 13.358837 | ... K2: =Показатели!M2 -> 0.30803856 | L2: =Показатели!B2 -> TRUE | N2: =IF($L2,IF(B$37>B$36,(B2-B$36)/(B$37-B$36),0)+0.000001,0) -> 1e-06 | O2: =IF($L2,IF(C$37>C$36,(C2-C$36)/(C$37-C$36),0)+0.000001,0) -> 1e-06 | P2: =IF($L2,IF(D$37>D$36,(D2-D$36)/(D$37-D$36),0)+0.000001,0) -> 0.037497594 | Q2: =IF($L2,IF(E$37>E$36,(E2-E$36)/(E$37-E$36),0)+0.000001,0) -> 0.49550937 | R2: =IF($L2,IF(F$37>F$36,(F2-F$36)/(F$37-F$36),0)+0.000001,0) -> 0.91433239 | S2: =IF($L2,IF(G$37>G$36,(G2-G$36)/(G$37-G$36),0)+0.000001,0) -> 0.13655259 | T2: =IF($L2,IF(H$37>H$36,(H2-H$36)/(H$37-H$36),0)+0.000001,0) -> 0.24937766 | U2: =IF($L2,IF(I$37>I$36,(I2-I$36)/(I$37-I$36),0)+0.000001,0) -> 1e-06 | ... W2: =IF($L2,IF(K$37>K$36,(K2-K$36)/(K$37-K$36),0)+0.000001,0) -> 0.18548993 | Y2: =IF($L2,N2/N$38*LN(N2/N$38),0) -> -1.9911482e-06 | Z2: =IF($L2,O2/O$38*LN(O2/O$38),0) -> -1.8266877e-06 | AA2: =IF($L2,P2/P$38*LN(P2/P$38),0) -> -0.016780238 | AB2: =IF($L2,Q2/Q$38*LN(Q2/Q$38),0) -> -0.16464691 | AC2: =IF($L2,R2/R$38*LN(R2/R$38),0) -> -0.17386638 | AD2: =IF($L2,S2/S$38*LN(S2/S$38),0) -> -0.061225142 | AE2: =IF($L2,T2/T$38*LN(T2/T$38),0) -> -0.094610967 | AF2: =IF($L2,U2/U$38*LN(U2/U$38),0) -> -1.8142456e-06 | ... AH2: =IF($L2,W2/W$38*LN(W2/W$38),0) -> -0.065018232
A3: =Показатели!A2&" Д" -> культиватор 0.08×3.6 Д | B3: =Показатели!N2 -> 273.77672 | C3: =Показатели!O2 -> 314.84323 | D3: =Показатели!P2 -> 1 | E3: =Показатели!Q2 -> 7.1383424 | F3: =Показатели!R2 -> 58.522725 | G3: =Показатели!S2 -> 9594.1558 | H3: =Показатели!T2 -> 11219.716 | I3: =Показатели!U2 -> 20.437928 | ... K3: =Показатели!W2 -> 1 | L3: =Показатели!B2 -> TRUE | N3: =IF($L3,IF(B$37>B$36,(B3-B$36)/(B$37-B$36),0)+0.000001,0) -> 0.33453732 | O3: =IF($L3,IF(C$37>C$36,(C3-C$36)/(C$37-C$36),0)+0.000001,0) -> 0.20749605 | P3: =IF($L3,IF(D$37>D$36,(D3-D$36)/(D$37-D$36),0)+0.000001,0) -> 1.000001 | Q3: =IF($L3,IF(E$37>E$36,(E3-E$36)/(E$37-E$36),0)+0.000001,0) -> 0.58458159 | R3: =IF($L3,IF(F$37>F$36,(F3-F$36)/(F$37-F$36),0)+0.000001,0) -> 0.99639888 | S3: =IF($L3,IF(G$37>G$36,(G3-G$36)/(G$37-G$36),0)+0.000001,0) -> 0.25373445 | T3: =IF($L3,IF(H$37>H$36,(H3-H$36)/(H$37-H$36),0)+0.000001,0) -> 0.17901046 | U3: =IF($L3,IF(I$37>I$36,(I3-I$36)/(I$37-I$36),0)+0.000001,0) -> 0.19691741 | ... W3: =IF($L3,IF(K$37>K$36,(K3-K$36)/(K$37-K$36),0)+0.000001,0) -> 1.000001 | Y3: =IF($L3,N3/N$38*LN(N3/N$38),0) -> -0.13295533 | Z3: =IF($L3,O3/O$38*LN(O3/O$38),0) -> -0.088725432 | AA3: =IF($L3,P3/P$38*LN(P3/P$38),0) -> -0.19653551 | AB3: =IF($L3,Q3/Q$38*LN(Q3/Q$38),0) -> -0.18298457 | AC3: =IF($L3,R3/R$38*LN(R3/R$38),0) -> -0.18358692 | AD3: =IF($L3,S3/S$38*LN(S3/S$38),0) -> -0.097129502 | AE3: =IF($L3,T3/T$38*LN(T3/T$38),0) -> -0.07407675 | AF3: =IF($L3,U3/U$38*LN(U3/U$38),0) -> -0.084922213 | ... AH3: =IF($L3,W3/W$38*LN(W3/W$38),0) -> -0.2085015
A4: =Показатели!A3&" ЭТ" -> культиватор 0.08×4.5 ЭТ | B4: =Показатели!D3 -> 83.924166 | C4: =Показатели!E3 -> 209.81042 | D4: =Показатели!F3 -> 0.26459019 | E4: =Показатели!G3 -> 6.2810882 | F4: =Показатели!H3 -> 41.412372 | G4: =Показатели!I3 -> 7277.4971 | H4: =Показатели!J3 -> 10785.42 | I4: =Показатели!K3 -> 14.127235 | ... K4: =Показатели!M3 -> 0.24874198 | L4: =Показатели!B3 -> TRUE | N4: =IF($L4,IF(B$37>B$36,(B4-B$36)/(B$37-B$36),0)+0.000001,0) -> 0.0078556003 | O4: =IF($L4,IF(C$37>C$36,(C4-C$36)/(C$37-C$36),0)+0.000001,0) -> 0.020335987 | P4: =IF($L4,IF(D$37>D$36,(D4-D$36)/(D$37-D$36),0)+0.000001,0) -> 1e-06 | Q4: =IF($L4,IF(E$37>E$36,(E4-E$36)/(E$37-E$36),0)+0.000001,0) -> 0.51437844 | R4: =IF($L4,IF(F$37>F$36,(F4-F$36)/(F$37-F$36),0)+0.000001,0) -> 0.69118831 | S4: =IF($L4,IF(G$37>G$36,(G4-G$36)/(G$37-G$36),0)+0.000001,0) -> 0.071292197 | T4: =IF($L4,IF(H$37>H$36,(H4-H$36)/(H$37-H$36),0)+0.000001,0) -> 0.15283784 | U4: =IF($L4,IF(I$37>I$36,(I4-I$36)/(I$37-I$36),0)+0.000001,0) -> 0.02137522 | ... W4: =IF($L4,IF(K$37>K$36,(K4-K$36)/(K$37-K$36),0)+0.000001,0) -> 0.11569166 | Y4: =IF($L4,N4/N$38*LN(N4/N$38),0) -> -0.0068143292 | Z4: =IF($L4,O4/O$38*LN(O4/O$38),0) -> -0.014093566 | AA4: =IF($L4,P4/P$38*LN(P4/P$38),0) -> -1.2524972e-06 | AB4: =IF($L4,Q4/Q$38*LN(Q4/Q$38),0) -> -0.16867694 | AC4: =IF($L4,R4/R$38*LN(R4/R$38),0) -> -0.1447221 | AD4: =IF($L4,S4/S$38*LN(S4/S$38),0) -> -0.03686786 | AE4: =IF($L4,T4/T$38*LN(T4/T$38),0) -> -0.065754721 | AF4: =IF($L4,U4/U$38*LN(U4/U$38),0) -> -0.014603002 | ... AH4: =IF($L4,W4/W$38*LN(W4/W$38),0) -> -0.045156307
A5: =Показатели!A3&" Д" -> культиватор 0.08×4.5 Д | B5: =Показатели!N3 -> 248.78045 | C5: =Показатели!O3 -> 286.09752 | D5: =Показатели!P3 -> 1 | E5: =Показатели!Q3 -> 7.4215979 | F5: =Показатели!R3 -> 47.179836 | G5: =Показатели!S3 -> 8096.4419 | H5: =Показатели!T3 -> 9428.3977 | I5: =Показатели!U3 -> 18.571911 | ... K5: =Показатели!W3 -> 0.93743074 | L5: =Показатели!B3 -> TRUE | N5: =IF($L5,IF(B$37>B$36,(B5-B$36)/(B$37-B$36),0)+0.000001,0) -> 0.29152592 | O5: =IF($L5,IF(C$37>C$36,(C5-C$36)/(C$37-C$36),0)+0.000001,0) -> 0.1562735 | P5: =IF($L5,IF(D$37>D$36,(D5-D$36)/(D$37-D$36),0)+0.000001,0) -> 1.000001 | Q5: =IF($L5,IF(E$37>E$36,(E5-E$36)/(E$37-E$36),0)+0.000001,0) -> 0.60777824 | R5: =IF($L5,IF(F$37>F$36,(F5-F$36)/(F$37-F$36),0)+0.000001,0) -> 0.79406702 | S5: =IF($L5,IF(G$37>G$36,(G5-G$36)/(G$37-G$36),0)+0.000001,0) -> 0.135786 | T5: =IF($L5,IF(H$37>H$36,(H5-H$36)/(H$37-H$36),0)+0.000001,0) -> 0.071057489 | U5: =IF($L5,IF(I$37>I$36,(I5-I$36)/(I$37-I$36),0)+0.000001,0) -> 0.14501112 | ... W5: =IF($L5,IF(K$37>K$36,(K5-K$36)/(K$37-K$36),0)+0.000001,0) -> 0.92635043 | Y5: =IF($L5,N5/N$38*LN(N5/N$38),0) -> -0.12088777 | Z5: =IF($L5,O5/O$38*LN(O5/O$38),0) -> -0.07188563 | AA5: =IF($L5,P5/P$38*LN(P5/P$38),0) -> -0.19653551 | AB5: =IF($L5,Q5/Q$38*LN(Q5/Q$38),0) -> -0.18749 | AC5: =IF($L5,R5/R$38*LN(R5/R$38),0) -> -0.15869201 | AD5: =IF($L5,S5/S$38*LN(S5/S$38),0) -> -0.060962322 | AE5: =IF($L5,T5/T$38*LN(T5/T$38),0) -> -0.036221703 | AF5: =IF($L5,U5/U$38*LN(U5/U$38),0) -> -0.067570839 | ... AH5: =IF($L5,W5/W$38*LN(W5/W$38),0) -> -0.19911935
A6: =Показатели!A4&" ЭТ" -> культиватор 0.08×5.4 ЭТ | B6: =Показатели!D4 -> 84.557098 | C6: =Показатели!E4 -> 211.39275 | D6: =Показатели!F4 -> 0.26519447 | E6: =Показатели!G4 -> 6.5676538 | F6: =Показатели!H4 -> 28.046183 | G6: =Показатели!I4 -> 6372.2387 | H6: =Показатели!J4 -> 9364.6586 | I6: =Показатели!K4 -> 14.233778 | ... K6: =Показатели!M4 -> 0.20799105 | L6: =Показатели!B4 -> TRUE | N6: =IF($L6,IF(B$37>B$36,(B6-B$36)/(B$37-B$36),0)+0.000001,0) -> 0.0089446938 | O6: =IF($L6,IF(C$37>C$36,(C6-C$36)/(C$37-C$36),0)+0.000001,0) -> 0.02315557 | P6: =IF($L6,IF(D$37>D$36,(D6-D$36)/(D$37-D$36),0)+0.000001,0) -> 0.00082269408 | Q6: =IF($L6,IF(E$37>E$36,(E6-E$36)/(E$37-E$36),0)+0.000001,0) -> 0.53784616 | R6: =IF($L6,IF(F$37>F$36,(F6-F$36)/(F$37-F$36),0)+0.000001,0) -> 0.45276527 | S6: =IF($L6,IF(G$37>G$36,(G6-G$36)/(G$37-G$36),0)+0.000001,0) -> 1e-06 | T6: =IF($L6,IF(H$37>H$36,(H6-H$36)/(H$37-H$36),0)+0.000001,0) -> 0.067216283 | U6: =IF($L6,IF(I$37>I$36,(I6-I$36)/(I$37-I$36),0)+0.000001,0) -> 0.0243389 | ... W6: =IF($L6,IF(K$37>K$36,(K6-K$36)/(K$37-K$36),0)+0.000001,0) -> 0.067723545 | Y6: =IF($L6,N6/N$38*LN(N6/N$38),0) -> -0.0076135627 | Z6: =IF($L6,O6/O$38*LN(O6/O$38),0) -> -0.015704052 | AA6: =IF($L6,P6/P$38*LN(P6/P$38),0) -> -0.00060832783 | AB6: =IF($L6,Q6/Q$38*LN(Q6/Q$38),0) -> -0.17357692 | AC6: =IF($L6,R6/R$38*LN(R6/R$38),0) -> -0.10796199 | AD6: =IF($L6,S6/S$38*LN(S6/S$38),0) -> -1.699618e-06 | AE6: =IF($L6,T6/T$38*LN(T6/T$38),0) -> -0.034651514 | AF6: =IF($L6,U6/U$38*LN(U6/U$38),0) -> -0.016269189 | ... AH6: =IF($L6,W6/W$38*LN(W6/W$38),0) -> -0.029490676
A7: =Показатели!A4&" Д" -> культиватор 0.08×5.4 Д | B7: =Показатели!N4 -> 233.68607 | C7: =Показатели!O4 -> 268.73898 | D7: =Показатели!P4 -> 1 | E7: =Показатели!Q4 -> 7.7753142 | F7: =Показатели!R4 -> 35.009772 | G7: =Показатели!S4 -> 7113.1019 | H7: =Показатели!T4 -> 8249.3215 | I7: =Показатели!U4 -> 17.445088 | ... K7: =Показатели!W4 -> 0.85214177 | L7: =Показатели!B4 -> TRUE | N7: =IF($L7,IF(B$37>B$36,(B7-B$36)/(B$37-B$36),0)+0.000001,0) -> 0.26555282 | O7: =IF($L7,IF(C$37>C$36,(C7-C$36)/(C$37-C$36),0)+0.000001,0) -> 0.12534196 | P7: =IF($L7,IF(D$37>D$36,(D7-D$36)/(D$37-D$36),0)+0.000001,0) -> 1.000001 | Q7: =IF($L7,IF(E$37>E$36,(E7-E$36)/(E$37-E$36),0)+0.000001,0) -> 0.63674515 | R7: =IF($L7,IF(F$37>F$36,(F7-F$36)/(F$37-F$36),0)+0.000001,0) -> 0.57698018 | S7: =IF($L7,IF(G$37>G$36,(G7-G$36)/(G$37-G$36),0)+0.000001,0) -> 0.058345693 | T7: =IF($L7,IF(H$37>H$36,(H7-H$36)/(H$37-H$36),0)+0.000001,0) -> 1e-06 | U7: =IF($L7,IF(I$37>I$36,(I7-I$36)/(I$37-I$36),0)+0.000001,0) -> 0.1136667 | ... W7: =IF($L7,IF(K$37>K$36,(K7-K$36)/(K$37-K$36),0)+0.000001,0) -> 0.82595638 | Y7: =IF($L7,N7/N$38*LN(N7/N$38),0) -> -0.11322207 | Z7: =IF($L7,O7/O$38*LN(O7/O$38),0) -> -0.060816444 | AA7: =IF($L7,P7/P$38*LN(P7/P$38),0) -> -0.19653551 | AB7: =IF($L7,Q7/Q$38*LN(Q7/Q$38),0) -> -0.19297176 | AC7: =IF($L7,R7/R$38*LN(R7/R$38),0) -> -0.12796938 | AD7: =IF($L7,S7/S$38*LN(S7/S$38),0) -> -0.031410035 | AE7: =IF($L7,T7/T$38*LN(T7/T$38),0) -> -1.669728e-06 | AF7: =IF($L7,U7/U$38*LN(U7/U$38),0) -> -0.056105779 | ... AH7: =IF($L7,W7/W$38*LN(W7/W$38),0) -> -0.18552644
A8: =Показатели!A5&" ЭТ" -> культиватор 0.11×3.6 ЭТ | B8: =Показатели!D5 -> 104.56946 | C8: =Показатели!E5 -> 261.42364 | D8: =Показатели!F5 -> 0.26470767 | E8: =Показатели!G5 -> 9.1565024 | F8: =Показатели!H5 -> 40.997449 | G8: =Показатели!I5 -> 8908.8573 | H8: =Показатели!J5 -> 13190.036 | I8: =Показатели!K5 -> 17.602525 | ... K8: =Показатели!M5 -> 0.24326225 | L8: =Показатели!B5 -> TRUE | N8: =IF($L8,IF(B$37>B$36,(B8-B$36)/(B$37-B$36),0)+0.000001,0) -> 0.043380217 | O8: =IF($L8,IF(C$37>C$36,(C8-C$36)/(C$37-C$36),0)+0.000001,0) -> 0.11230662 | P8: =IF($L8,IF(D$37>D$36,(D8-D$36)/(D$37-D$36),0)+0.000001,0) -> 0.00016075101 | Q8: =IF($L8,IF(E$37>E$36,(E8-E$36)/(E$37-E$36),0)+0.000001,0) -> 0.74985486 | R8: =IF($L8,IF(F$37>F$36,(F8-F$36)/(F$37-F$36),0)+0.000001,0) -> 0.683787 | S8: =IF($L8,IF(G$37>G$36,(G8-G$36)/(G$37-G$36),0)+0.000001,0) -> 0.19976561 | T8: =IF($L8,IF(H$37>H$36,(H8-H$36)/(H$37-H$36),0)+0.000001,0) -> 0.29775088 | U8: =IF($L8,IF(I$37>I$36,(I8-I$36)/(I$37-I$36),0)+0.000001,0) -> 0.11804608 | ... W8: =IF($L8,IF(K$37>K$36,(K8-K$36)/(K$37-K$36),0)+0.000001,0) -> 0.10924144 | Y8: =IF($L8,N8/N$38*LN(N8/N$38),0) -> -0.02834292 | Z8: =IF($L8,O8/O$38*LN(O8/O$38),0) -> -0.055900997 | AA8: =IF($L8,P8/P$38*LN(P8/P$38),0) -> -0.00013892556 | AB8: =IF($L8,Q8/Q$38*LN(Q8/Q$38),0) -> -0.21296573 | AC8: =IF($L8,R8/R$38*LN(R8/R$38),0) -> -0.14367824 | AD8: =IF($L8,S8/S$38*LN(S8/S$38),0) -> -0.0815255 | AE8: =IF($L8,T8/T$38*LN(T8/T$38),0) -> -0.10748193 | AF8: =IF($L8,U8/U$38*LN(U8/U$38),0) -> -0.057761154 | ... AH8: =IF($L8,W8/W$38*LN(W8/W$38),0) -> -0.043166973
A9: =Показатели!A5&" Д" -> культиватор 0.11×3.6 Д | B9: =Показатели!N5 -> 309.60075 | C9: =Показатели!O5 -> 356.04087 | D9: =Показатели!P5 -> 1 | E9: =Показатели!Q5 -> 11.050596 | F9: =Показатели!R5 -> 45.92633 | G9: =Показатели!S5 -> 9938.6818 | H9: =Показатели!T5 -> 11564.242 | I9: =Показатели!U5 -> 23.112257 | ... K9: =Показатели!W5 -> 0.91947236 | L9: =Показатели!B5 -> TRUE | N9: =IF($L9,IF(B$37>B$36,(B9-B$36)/(B$37-B$36),0)+0.000001,0) -> 0.39618019 | O9: =IF($L9,IF(C$37>C$36,(C9-C$36)/(C$37-C$36),0)+0.000001,0) -> 0.28090694 | P9: =IF($L9,IF(D$37>D$36,(D9-D$36)/(D$37-D$36),0)+0.000001,0) -> 1.000001 | Q9: =IF($L9,IF(E$37>E$36,(E9-E$36)/(E$37-E$36),0)+0.000001,0) -> 0.90496797 | R9: =IF($L9,IF(F$37>F$36,(F9-F$36)/(F$37-F$36),0)+0.000001,0) -> 0.77170726 | S9: =IF($L9,IF(G$37>G$36,(G9-G$36)/(G$37-G$36),0)+0.000001,0) -> 0.28086667 | T9: =IF($L9,IF(H$37>H$36,(H9-H$36)/(H$37-H$36),0)+0.000001,0) -> 0.19977316 | U9: =IF($L9,IF(I$37>I$36,(I9-I$36)/(I$37-I$36),0)+0.000001,0) -> 0.27130821 | ... W9: =IF($L9,IF(K$37>K$36,(K9-K$36)/(K$37-K$36),0)+0.000001,0) -> 0.90521153 | Y9: =IF($L9,N9/N$38*LN(N9/N$38),0) -> -0.14905955 | Z9: =IF($L9,O9/O$38*LN(O9/O$38),0) -> -0.1103921 | AA9: =IF($L9,P9/P$38*LN(P9/P$38),0) -> -0.19653551 | AB9: =IF($L9,Q9/Q$38*LN(Q9/Q$38),0) -> -0.2371951 | AC9: =IF($L9,R9/R$38*LN(R9/R$38),0) -> -0.15573807 | AD9: =IF($L9,S9/S$38*LN(S9/S$38),0) -> -0.10449629 | AE9: =IF($L9,T9/T$38*LN(T9/T$38),0) -> -0.080392243 | AF9: =IF($L9,U9/U$38*LN(U9/U$38),0) -> -0.10713998 | ... AH9: =IF($L9,W9/W$38*LN(W9/W$38),0) -> -0.196337
A10: =Показатели!A6&" ЭТ" -> культиватор 0.11×4.5 ЭТ | B10: =Показатели!D6 -> 104.99671 | C10: =Показатели!E6 -> 262.49179 | D10: =Показатели!F6 -> 0.26548949 | E10: =Показатели!G6 -> 9.5492968 | F10: =Показатели!H6 -> 24.6025 | G10: =Показатели!I6 -> 7544.3575 | H10: =Показатели!J6 -> 11052.281 | I10: =Показатели!K6 -> 17.674447 | ... K10: =Показатели!M6 -> 0.19569078 | L10: =Показатели!B6 -> TRUE | N10: =IF($L10,IF(B$37>B$36,(B10-B$36)/(B$37-B$36),0)+0.000001,0) -> 0.044115403 | O10: =IF($L10,IF(C$37>C$36,(C10-C$36)/(C$37-C$36),0)+0.000001,0) -> 0.11420997 | P10: =IF($L10,IF(D$37>D$36,(D10-D$36)/(D$37-D$36),0)+0.000001,0) -> 0.0012238557 | Q10: =IF($L10,IF(E$37>E$36,(E10-E$36)/(E$37-E$36),0)+0.000001,0) -> 0.78202199 | R10: =IF($L10,IF(F$37>F$36,(F10-F$36)/(F$37-F$36),0)+0.000001,0) -> 0.39133764 | S10: =IF($L10,IF(G$37>G$36,(G10-G$36)/(G$37-G$36),0)+0.000001,0) -> 0.092308073 | T10: =IF($L10,IF(H$37>H$36,(H10-H$36)/(H$37-H$36),0)+0.000001,0) -> 0.16892006 | U10: =IF($L10,IF(I$37>I$36,(I10-I$36)/(I$37-I$36),0)+0.000001,0) -> 0.12004669 | ... W10: =IF($L10,IF(K$37>K$36,(K10-K$36)/(K$37-K$36),0)+0.000001,0) -> 0.053244833 | Y10: =IF($L10,N10/N$38*LN(N10/N$38),0) -> -0.028730376 | Z10: =IF($L10,O10/O$38*LN(O10/O$38),0) -> -0.05662905 | AA10: =IF($L10,P10/P$38*LN(P10/P$38),0) -> -0.00086780716 | AB10: =IF($L10,Q10/Q$38*LN(Q10/Q$38),0) -> -0.21827448 | AC10: =IF($L10,R10/R$38*LN(R10/R$38),0) -> -0.097235261 | AD10: =IF($L10,S10/S$38*LN(S10/S$38),0) -> -0.045212454 | AE10: =IF($L10,T10/T$38*LN(T10/T$38),0) -> -0.07091886 | AF10: =IF($L10,U10/U$38*LN(U10/U$38),0) -> -0.058511198 | ... AH10: =IF($L10,W10/W$38*LN(W10/W$38),0) -> -0.02426543
A11: =Показатели!A6&" Д" -> культиватор 0.11×4.5 Д | B11: =Показатели!N6 -> 286.18624 | C11: =Показатели!O6 -> 329.11417 | D11: =Показатели!P6 -> 1 | E11: =Показатели!Q6 -> 11.561591 | F11: =Показатели!R6 -> 30.740084 | G11: =Показатели!S6 -> 8456.2376 | H11: =Показатели!T6 -> 9788.1934 | I11: =Показатели!U6 -> 21.364321 | ... K11: =Показатели!W6 -> 0.81613845 | L11: =Показатели!B6 -> TRUE | N11: =IF($L11,IF(B$37>B$36,(B11-B$36)/(B$37-B$36),0)+0.000001,0) -> 0.35589054 | O11: =IF($L11,IF(C$37>C$36,(C11-C$36)/(C$37-C$36),0)+0.000001,0) -> 0.23292573 | P11: =IF($L11,IF(D$37>D$36,(D11-D$36)/(D$37-D$36),0)+0.000001,0) -> 1.000001 | Q11: =IF($L11,IF(E$37>E$36,(E11-E$36)/(E$37-E$36),0)+0.000001,0) -> 0.94681486 | R11: =IF($L11,IF(F$37>F$36,(F11-F$36)/(F$37-F$36),0)+0.000001,0) -> 0.50081846 | S11: =IF($L11,IF(G$37>G$36,(G11-G$36)/(G$37-G$36),0)+0.000001,0) -> 0.16412075 | T11: =IF($L11,IF(H$37>H$36,(H11-H$36)/(H$37-H$36),0)+0.000001,0) -> 0.09274041 | U11: =IF($L11,IF(I$37>I$36,(I11-I$36)/(I$37-I$36),0)+0.000001,0) -> 0.22268654 | ... W11: =IF($L11,IF(K$37>K$36,(K11-K$36)/(K$37-K$36),0)+0.000001,0) -> 0.7835767 | Y11: =IF($L11,N11/N$38*LN(N11/N$38),0) -> -0.13868284 | Z11: =IF($L11,O11/O$38*LN(O11/O$38),0) -> -0.096521917 | AA11: =IF($L11,P11/P$38*LN(P11/P$38),0) -> -0.19653551 | AB11: =IF($L11,Q11/Q$38*LN(Q11/Q$38),0) -> -0.24317675 | AC11: =IF($L11,R11/R$38*LN(R11/R$38),0) -> -0.11594903 | AD11: =IF($L11,S11/S$38*LN(S11/S$38),0) -> -0.070392 | AE11: =IF($L11,T11/T$38*LN(T11/T$38),0) -> -0.044710061 | AF11: =IF($L11,U11/U$38*LN(U11/U$38),0) -> -0.092928464 | ... AH11: =IF($L11,W11/W$38*LN(W11/W$38),0) -> -0.17948634
A12: =Показатели!A7&" ЭТ" -> культиватор 0.11×5.4 ЭТ | B12: =Показатели!D7 -> 106.66149 | C12: =Показатели!E7 -> 266.65372 | D12: =Показатели!F7 -> 0.26631138 | E12: =Показатели!G7 -> 10.043958 | F12: =Показатели!H7 -> 6.8865962 | G12: =Показатели!I7 -> 6652.1663 | H12: =Показатели!J7 -> 9732.9746 | I12: =Показатели!K7 -> 17.954684 | ... K12: =Показатели!M7 -> 0.16285377 | L12: =Показатели!B7 -> TRUE | N12: =IF($L12,IF(B$37>B$36,(B12-B$36)/(B$37-B$36),0)+0.000001,0) -> 0.046980003 | O12: =IF($L12,IF(C$37>C$36,(C12-C$36)/(C$37-C$36),0)+0.000001,0) -> 0.12162621 | P12: =IF($L12,IF(D$37>D$36,(D12-D$36)/(D$37-D$36),0)+0.000001,0) -> 0.0023414557 | Q12: =IF($L12,IF(E$37>E$36,(E12-E$36)/(E$37-E$36),0)+0.000001,0) -> 0.82253127 | R12: =IF($L12,IF(F$37>F$36,(F12-F$36)/(F$37-F$36),0)+0.000001,0) -> 0.075325391 | S12: =IF($L12,IF(G$37>G$36,(G12-G$36)/(G$37-G$36),0)+0.000001,0) -> 0.022045945 | T12: =IF($L12,IF(H$37>H$36,(H12-H$36)/(H$37-H$36),0)+0.000001,0) -> 0.089412676 | U12: =IF($L12,IF(I$37>I$36,(I12-I$36)/(I$37-I$36),0)+0.000001,0) -> 0.12784195 | ... W12: =IF($L12,IF(K$37>K$36,(K12-K$36)/(K$37-K$36),0)+0.000001,0) -> 0.014592243 | Y12: =IF($L12,N12/N$38*LN(N12/N$38),0) -> -0.030225655 | Z12: =IF($L12,O12/O$38*LN(O12/O$38),0) -> -0.059431815 | AA12: =IF($L12,P12/P$38*LN(P12/P$38),0) -> -0.0015441646 | AB12: =IF($L12,Q12/Q$38*LN(Q12/Q$38),0) -> -0.22474138 | AC12: =IF($L12,R12/R$38*LN(R12/R$38),0) -> -0.027244646 | AD12: =IF($L12,S12/S$38*LN(S12/S$38),0) -> -0.01413879 | AE12: =IF($L12,T12/T$38*LN(T12/T$38),0) -> -0.043445027 | AF12: =IF($L12,U12/U$38*LN(U12/U$38),0) -> -0.061398169 | ... AH12: =IF($L12,W12/W$38*LN(W12/W$38),0) -> -0.0082424046
A13: =Показатели!A7&" Д" -> культиватор 0.11×5.4 Д | B13: =Показатели!N7 -> 273.10395 | C13: =Показатели!O7 -> 314.06954 | D13: =Показатели!P7 -> 1 | E13: =Показатели!Q7 -> 12.211049 | F13: =Показатели!R7 -> 14.220933 | G13: =Показатели!S7 -> 7492.2531 | H13: =Показатели!T7 -> 8628.4727 | I13: =Показатели!U7 -> 20.387704 | ... K13: =Показатели!W7 -> 0.7308435 | L13: =Показатели!B7 -> TRUE | N13: =IF($L13,IF(B$37>B$36,(B13-B$36)/(B$37-B$36),0)+0.000001,0) -> 0.33337967 | O13: =IF($L13,IF(C$37>C$36,(C13-C$36)/(C$37-C$36),0)+0.000001,0) -> 0.20611739 | P13: =IF($L13,IF(D$37>D$36,(D13-D$36)/(D$37-D$36),0)+0.000001,0) -> 1.000001 | Q13: =IF($L13,IF(E$37>E$36,(E13-E$36)/(E$37-E$36),0)+0.000001,0) -> 1.000001 | R13: =IF($L13,IF(F$37>F$36,(F13-F$36)/(F$37-F$36),0)+0.000001,0) -> 0.20615362 | S13: =IF($L13,IF(G$37>G$36,(G13-G$36)/(G$37-G$36),0)+0.000001,0) -> 0.088204736 | T13: =IF($L13,IF(H$37>H$36,(H13-H$36)/(H$37-H$36),0)+0.000001,0) -> 0.022850377 | U13: =IF($L13,IF(I$37>I$36,(I13-I$36)/(I$37-I$36),0)+0.000001,0) -> 0.19552035 | ... W13: =IF($L13,IF(K$37>K$36,(K13-K$36)/(K$37-K$36),0)+0.000001,0) -> 0.68317561 | Y13: =IF($L13,N13/N$38*LN(N13/N$38),0) -> -0.13264003 | Z13: =IF($L13,O13/O$38*LN(O13/O$38),0) -> -0.088292944 | AA13: =IF($L13,P13/P$38*LN(P13/P$38),0) -> -0.19653551 | AB13: =IF($L13,Q13/Q$38*LN(Q13/Q$38),0) -> -0.25046937 | AC13: =IF($L13,R13/R$38*LN(R13/R$38),0) -> -0.060302234 | AD13: =IF($L13,S13/S$38*LN(S13/S$38),0) -> -0.043627056 | AE13: =IF($L13,T13/T$38*LN(T13/T$38),0) -> -0.014339894 | AF13: =IF($L13,U13/U$38*LN(U13/U$38),0) -> -0.084477651 | ... AH13: =IF($L13,W13/W$38*LN(W13/W$38),0) -> -0.16438498
A14: =Показатели!A8&" ЭТ" -> культиватор 0.14×3.6 ЭТ | B14: =Показатели!D8 -> 127.32688 | C14: =Показатели!E8 -> 318.3172 | D14: =Показатели!F8 -> 0.26554242 | E14: =Показатели!G8 -> 13.090327 | F14: =Показатели!H8 -> 26.474313 | G14: =Показатели!I8 -> 9197.0548 | H14: =Показатели!J8 -> 13478.233 | I14: =Показатели!K8 -> 21.433358 | ... K14: =Показатели!M8 -> 0.19707741 | L14: =Показатели!B8 -> FALSE | N14: =IF($L14,IF(B$37>B$36,(B14-B$36)/(B$37-B$36),0)+0.000001,0) -> 0 | O14: =IF($L14,IF(C$37>C$36,(C14-C$36)/(C$37-C$36),0)+0.000001,0) -> 0 | P14: =IF($L14,IF(D$37>D$36,(D14-D$36)/(D$37-D$36),0)+0.000001,0) -> 0 | Q14: =IF($L14,IF(E$37>E$36,(E14-E$36)/(E$37-E$36),0)+0.000001,0) -> 0 | R14: =IF($L14,IF(F$37>F$36,(F14-F$36)/(F$37-F$36),0)+0.000001,0) -> 0 | S14: =IF($L14,IF(G$37>G$36,(G14-G$36)/(G$37-G$36),0)+0.000001,0) -> 0 | T14: =IF($L14,IF(H$37>H$36,(H14-H$36)/(H$37-H$36),0)+0.000001,0) -> 0 | U14: =IF($L14,IF(I$37>I$36,(I14-I$36)/(I$37-I$36),0)+0.000001,0) -> 0 | ... W14: =IF($L14,IF(K$37>K$36,(K14-K$36)/(K$37-K$36),0)+0.000001,0) -> 0 | Y14: =IF($L14,N14/N$38*LN(N14/N$38),0) -> 0 | Z14: =IF($L14,O14/O$38*LN(O14/O$38),0) -> 0 | AA14: =IF($L14,P14/P$38*LN(P14/P$38),0) -> 0 | AB14: =IF($L14,Q14/Q$38*LN(Q14/Q$38),0) -> 0 | AC14: =IF($L14,R14/R$38*LN(R14/R$38),0) -> 0 | AD14: =IF($L14,S14/S$38*LN(S14/S$38),0) -> 0 | AE14: =IF($L14,T14/T$38*LN(T14/T$38),0) -> 0 | AF14: =IF($L14,U14/U$38*LN(U14/U$38),0) -> 0 | ... AH14: =IF($L14,W14/W$38*LN(W14/W$38),0) -> 0
A15: =Показатели!A8&" Д" -> культиватор 0.14×3.6 Д | B15: =Показатели!N8 -> 351.94782 | C15: =Показатели!O8 -> 404.74 | D15: =Показатели!P8 -> 1 | E15: =Показатели!Q8 -> 16.380656 | F15: =Показатели!R8 -> 31.037184 | G15: =Показатели!S8 -> 10346.007 | H15: =Показатели!T8 -> 11971.567 | I15: =Показатели!U8 -> 26.273542 | ... K15: =Показатели!W8 -> 0.81001461 | L15: =Показатели!B8 -> FALSE | N15: =IF($L15,IF(B$37>B$36,(B15-B$36)/(B$37-B$36),0)+0.000001,0) -> 0 | O15: =IF($L15,IF(C$37>C$36,(C15-C$36)/(C$37-C$36),0)+0.000001,0) -> 0 | P15: =IF($L15,IF(D$37>D$36,(D15-D$36)/(D$37-D$36),0)+0.000001,0) -> 0 | Q15: =IF($L15,IF(E$37>E$36,(E15-E$36)/(E$37-E$36),0)+0.000001,0) -> 0 | R15: =IF($L15,IF(F$37>F$36,(F15-F$36)/(F$37-F$36),0)+0.000001,0) -> 0 | S15: =IF($L15,IF(G$37>G$36,(G15-G$36)/(G$37-G$36),0)+0.000001,0) -> 0 | T15: =IF($L15,IF(H$37>H$36,(H15-H$36)/(H$37-H$36),0)+0.000001,0) -> 0 | U15: =IF($L15,IF(I$37>I$36,(I15-I$36)/(I$37-I$36),0)+0.000001,0) -> 0 | ... W15: =IF($L15,IF(K$37>K$36,(K15-K$36)/(K$37-K$36),0)+0.000001,0) -> 0 | Y15: =IF($L15,N15/N$38*LN(N15/N$38),0) -> 0 | Z15: =IF($L15,O15/O$38*LN(O15/O$38),0) -> 0 | AA15: =IF($L15,P15/P$38*LN(P15/P$38),0) -> 0 | AB15: =IF($L15,Q15/Q$38*LN(Q15/Q$38),0) -> 0 | AC15: =IF($L15,R15/R$38*LN(R15/R$38),0) -> 0 | AD15: =IF($L15,S15/S$38*LN(S15/S$38),0) -> 0 | AE15: =IF($L15,T15/T$38*LN(T15/T$38),0) -> 0 | AF15: =IF($L15,U15/U$38*LN(U15/U$38),0) -> 0 | ... AH15: =IF($L15,W15/W$38*LN(W15/W$38),0) -> 0
A16: =Показатели!A9&" ЭТ" -> культиватор 0.14×4.5 ЭТ | B16: =Показатели!D9 -> 128.89836 | C16: =Показатели!E9 -> 322.24591 | D16: =Показатели!F9 -> 0.26657805 | E16: =Показатели!G9 -> 13.74799 | F16: =Показатели!H9 -> 5.5358134 | G16: =Показатели!I9 -> 7847.0453 | H16: =Показатели!J9 -> 11484.37 | I16: =Показатели!K9 -> 21.697891 | ... K16: =Показатели!M9 -> 0.15783414 | L16: =Показатели!B9 -> FALSE | N16: =IF($L16,IF(B$37>B$36,(B16-B$36)/(B$37-B$36),0)+0.000001,0) -> 0 | O16: =IF($L16,IF(C$37>C$36,(C16-C$36)/(C$37-C$36),0)+0.000001,0) -> 0 | P16: =IF($L16,IF(D$37>D$36,(D16-D$36)/(D$37-D$36),0)+0.000001,0) -> 0 | Q16: =IF($L16,IF(E$37>E$36,(E16-E$36)/(E$37-E$36),0)+0.000001,0) -> 0 | R16: =IF($L16,IF(F$37>F$36,(F16-F$36)/(F$37-F$36),0)+0.000001,0) -> 0 | S16: =IF($L16,IF(G$37>G$36,(G16-G$36)/(G$37-G$36),0)+0.000001,0) -> 0 | T16: =IF($L16,IF(H$37>H$36,(H16-H$36)/(H$37-H$36),0)+0.000001,0) -> 0 | U16: =IF($L16,IF(I$37>I$36,(I16-I$36)/(I$37-I$36),0)+0.000001,0) -> 0 | ... W16: =IF($L16,IF(K$37>K$36,(K16-K$36)/(K$37-K$36),0)+0.000001,0) -> 0 | Y16: =IF($L16,N16/N$38*LN(N16/N$38),0) -> 0 | Z16: =IF($L16,O16/O$38*LN(O16/O$38),0) -> 0 | AA16: =IF($L16,P16/P$38*LN(P16/P$38),0) -> 0 | AB16: =IF($L16,Q16/Q$38*LN(Q16/Q$38),0) -> 0 | AC16: =IF($L16,R16/R$38*LN(R16/R$38),0) -> 0 | AD16: =IF($L16,S16/S$38*LN(S16/S$38),0) -> 0 | AE16: =IF($L16,T16/T$38*LN(T16/T$38),0) -> 0 | AF16: =IF($L16,U16/U$38*LN(U16/U$38),0) -> 0 | ... AH16: =IF($L16,W16/W$38*LN(W16/W$38),0) -> 0
A17: =Показатели!A9&" Д" -> культиватор 0.14×4.5 Д | B17: =Показатели!N9 -> 331.12675 | C17: =Показатели!O9 -> 380.79577 | D17: =Показатели!P9 -> 1 | E17: =Показатели!Q9 -> 17.32605 | F17: =Показатели!R9 -> 10.988885 | G17: =Показатели!S9 -> 8888.5106 | H17: =Показатели!T9 -> 10220.466 | I17: =Показатели!U9 -> 24.719212 | ... K17: =Показатели!W9 -> 0.70706584 | L17: =Показатели!B9 -> FALSE | N17: =IF($L17,IF(B$37>B$36,(B17-B$36)/(B$37-B$36),0)+0.000001,0) -> 0 | O17: =IF($L17,IF(C$37>C$36,(C17-C$36)/(C$37-C$36),0)+0.000001,0) -> 0 | P17: =IF($L17,IF(D$37>D$36,(D17-D$36)/(D$37-D$36),0)+0.000001,0) -> 0 | Q17: =IF($L17,IF(E$37>E$36,(E17-E$36)/(E$37-E$36),0)+0.000001,0) -> 0 | R17: =IF($L17,IF(F$37>F$36,(F17-F$36)/(F$37-F$36),0)+0.000001,0) -> 0 | S17: =IF($L17,IF(G$37>G$36,(G17-G$36)/(G$37-G$36),0)+0.000001,0) -> 0 | T17: =IF($L17,IF(H$37>H$36,(H17-H$36)/(H$37-H$36),0)+0.000001,0) -> 0 | U17: =IF($L17,IF(I$37>I$36,(I17-I$36)/(I$37-I$36),0)+0.000001,0) -> 0 | ... W17: =IF($L17,IF(K$37>K$36,(K17-K$36)/(K$37-K$36),0)+0.000001,0) -> 0 | Y17: =IF($L17,N17/N$38*LN(N17/N$38),0) -> 0 | Z17: =IF($L17,O17/O$38*LN(O17/O$38),0) -> 0 | AA17: =IF($L17,P17/P$38*LN(P17/P$38),0) -> 0 | AB17: =IF($L17,Q17/Q$38*LN(Q17/Q$38),0) -> 0 | AC17: =IF($L17,R17/R$38*LN(R17/R$38),0) -> 0 | AD17: =IF($L17,S17/S$38*LN(S17/S$38),0) -> 0 | AE17: =IF($L17,T17/T$38*LN(T17/T$38),0) -> 0 | AF17: =IF($L17,U17/U$38*LN(U17/U$38),0) -> 0 | ... AH17: =IF($L17,W17/W$38*LN(W17/W$38),0) -> 0
A18: =Показатели!A10&" ЭТ" -> фреза 0.08×1.8 ЭТ | B18: =Показатели!D10 -> 146.52326 | C18: =Показатели!E10 -> 366.30815 | D18: =Показатели!F10 -> 0.2891018 | E18: =Показатели!G10 -> 0 | F18: =Показатели!H10 -> 54.786632 | G18: =Показатели!I10 -> 14836.865 | H18: =Показатели!J10 -> 22658.42 | I18: =Показатели!K10 -> 24.664749 | ... K18: =Показатели!M10 -> 0.30480835 | L18: =Показатели!B10 -> TRUE | N18: =IF($L18,IF(B$37>B$36,(B18-B$36)/(B$37-B$36),0)+0.000001,0) -> 0.11557066 | O18: =IF($L18,IF(C$37>C$36,(C18-C$36)/(C$37-C$36),0)+0.000001,0) -> 0.29920242 | P18: =IF($L18,IF(D$37>D$36,(D18-D$36)/(D$37-D$36),0)+0.000001,0) -> 0.033331545 | Q18: =IF($L18,IF(E$37>E$36,(E18-E$36)/(E$37-E$36),0)+0.000001,0) -> 1e-06 | R18: =IF($L18,IF(F$37>F$36,(F18-F$36)/(F$37-F$36),0)+0.000001,0) -> 0.92975531 | S18: =IF($L18,IF(G$37>G$36,(G18-G$36)/(G$37-G$36),0)+0.000001,0) -> 0.66660994 | T18: =IF($L18,IF(H$37>H$36,(H18-H$36)/(H$37-H$36),0)+0.000001,0) -> 0.86835873 | U18: =IF($L18,IF(I$37>I$36,(I18-I$36)/(I$37-I$36),0)+0.000001,0) -> 0.31449331 | ... W18: =IF($L18,IF(K$37>K$36,(K18-K$36)/(K$37-K$36),0)+0.000001,0) -> 0.18168765 | Y18: =IF($L18,N18/N$38*LN(N18/N$38),0) -> -0.061321116 | Z18: =IF($L18,O18/O$38*LN(O18/O$38),0) -> -0.11542452 | AA18: =IF($L18,P18/P$38*LN(P18/P$38),0) -> -0.015215965 | AB18: =IF($L18,Q18/Q$38*LN(Q18/Q$38),0) -> -1.8600974e-06 | AC18: =IF($L18,R18/R$38*LN(R18/R$38),0) -> -0.17573049 | AD18: =IF($L18,S18/S$38*LN(S18/S$38),0) -> -0.18704229 | AE18: =IF($L18,T18/T$38*LN(T18/T$38),0) -> -0.21694977 | AF18: =IF($L18,U18/U$38*LN(U18/U$38),0) -> -0.11892385 | ... AH18: =IF($L18,W18/W$38*LN(W18/W$38),0) -> -0.064002663
A19: =Показатели!A10&" Д" -> фреза 0.08×1.8 Д | B19: =Показатели!N10 -> 505.57709 | C19: =Показатели!O10 -> 581.41365 | D19: =Показатели!P10 -> 1 | E19: =Показатели!Q10 -> 0 | F19: =Показатели!R10 -> 58.724663 | G19: =Показатели!S10 -> 17580.036 | H19: =Показатели!T10 -> 20549.875 | I19: =Показатели!U10 -> 37.742245 | ... K19: =Показатели!W10 -> 1 | L19: =Показатели!B10 -> TRUE | N19: =IF($L19,IF(B$37>B$36,(B19-B$36)/(B$37-B$36),0)+0.000001,0) -> 0.73339919 | O19: =IF($L19,IF(C$37>C$36,(C19-C$36)/(C$37-C$36),0)+0.000001,0) -> 0.6825032 | P19: =IF($L19,IF(D$37>D$36,(D19-D$36)/(D$37-D$36),0)+0.000001,0) -> 1.000001 | Q19: =IF($L19,IF(E$37>E$36,(E19-E$36)/(E$37-E$36),0)+0.000001,0) -> 1e-06 | R19: =IF($L19,IF(F$37>F$36,(F19-F$36)/(F$37-F$36),0)+0.000001,0) -> 1.000001 | S19: =IF($L19,IF(G$37>G$36,(G19-G$36)/(G$37-G$36),0)+0.000001,0) -> 0.88264109 | T19: =IF($L19,IF(H$37>H$36,(H19-H$36)/(H$37-H$36),0)+0.000001,0) -> 0.74128822 | U19: =IF($L19,IF(I$37>I$36,(I19-I$36)/(I$37-I$36),0)+0.000001,0) -> 0.67826512 | ... W19: =IF($L19,IF(K$37>K$36,(K19-K$36)/(K$37-K$36),0)+0.000001,0) -> 1.000001 | Y19: =IF($L19,N19/N$38*LN(N19/N$38),0) -> -0.21935033 | Z19: =IF($L19,O19/O$38*LN(O19/O$38),0) -> -0.19897374 | AA19: =IF($L19,P19/P$38*LN(P19/P$38),0) -> -0.19653551 | AB19: =IF($L19,Q19/Q$38*LN(Q19/Q$38),0) -> -1.8600974e-06 | AC19: =IF($L19,R19/R$38*LN(R19/R$38),0) -> -0.18400265 | AD19: =IF($L19,S19/S$38*LN(S19/S$38),0) -> -0.22143915 | AE19: =IF($L19,T19/T$38*LN(T19/T$38),0) -> -0.19738083 | AF19: =IF($L19,U19/U$38*LN(U19/U$38),0) -> -0.1973421 | ... AH19: =IF($L19,W19/W$38*LN(W19/W$38),0) -> -0.2085015
A20: =Показатели!A11&" ЭТ" -> фреза 0.08×2.7 ЭТ | B20: =Показатели!D11 -> 134.72306 | C20: =Показатели!E11 -> 336.80765 | D20: =Показатели!F11 -> 0.2647969 | E20: =Показатели!G11 -> 0 | F20: =Показатели!H11 -> 39.932431 | G20: =Показатели!I11 -> 11179.192 | H20: =Показатели!J11 -> 16526.332 | I20: =Показатели!K11 -> 22.678382 | ... K20: =Показатели!M11 -> 0.23522693 | L20: =Показатели!B11 -> TRUE | N20: =IF($L20,IF(B$37>B$36,(B20-B$36)/(B$37-B$36),0)+0.000001,0) -> 0.095265907 | O20: =IF($L20,IF(C$37>C$36,(C20-C$36)/(C$37-C$36),0)+0.000001,0) -> 0.24663489 | P20: =IF($L20,IF(D$37>D$36,(D20-D$36)/(D$37-D$36),0)+0.000001,0) -> 0.00028208595 | Q20: =IF($L20,IF(E$37>E$36,(E20-E$36)/(E$37-E$36),0)+0.000001,0) -> 1e-06 | R20: =IF($L20,IF(F$37>F$36,(F20-F$36)/(F$37-F$36),0)+0.000001,0) -> 0.66478945 | S20: =IF($L20,IF(G$37>G$36,(G20-G$36)/(G$37-G$36),0)+0.000001,0) -> 0.37855974 | T20: =IF($L20,IF(H$37>H$36,(H20-H$36)/(H$37-H$36),0)+0.000001,0) -> 0.49881121 | U20: =IF($L20,IF(I$37>I$36,(I20-I$36)/(I$37-I$36),0)+0.000001,0) -> 0.25923927 | ... W20: =IF($L20,IF(K$37>K$36,(K20-K$36)/(K$37-K$36),0)+0.000001,0) -> 0.099783029 | Y20: =IF($L20,N20/N$38*LN(N20/N$38),0) -> -0.052853612 | Z20: =IF($L20,O20/O$38*LN(O20/O$38),0) -> -0.10059097 | AA20: =IF($L20,P20/P$38*LN(P20/P$38),0) -> -0.00023166187 | AB20: =IF($L20,Q20/Q$38*LN(Q20/Q$38),0) -> -1.8600974e-06 | AC20: =IF($L20,R20/R$38*LN(R20/R$38),0) -> -0.14097355 | AD20: =IF($L20,S20/S$38*LN(S20/S$38),0) -> -0.12888562 | AE20: =IF($L20,T20/T$38*LN(T20/T$38),0) -> -0.15333612 | AF20: =IF($L20,U20/U$38*LN(U20/U$38),0) -> -0.10371222 | ... AH20: =IF($L20,W20/W$38*LN(W20/W$38),0) -> -0.040191222
A21: =Показатели!A11&" Д" -> фреза 0.08×2.7 Д | B21: =Показатели!N11 -> 392.35728 | C21: =Показатели!O11 -> 451.21087 | D21: =Показатели!P11 -> 1 | E21: =Показатели!Q11 -> 0 | F21: =Показатели!R11 -> 45.269422 | G21: =Показатели!S11 -> 12467.827 | H21: =Показатели!T11 -> 14498.132 | I21: =Показатели!U11 -> 29.290181 | ... K21: =Показатели!W11 -> 0.9063062 | L21: =Показатели!B11 -> TRUE | N21: =IF($L21,IF(B$37>B$36,(B21-B$36)/(B$37-B$36),0)+0.000001,0) -> 0.53858041 | O21: =IF($L21,IF(C$37>C$36,(C21-C$36)/(C$37-C$36),0)+0.000001,0) -> 0.45049226 | P21: =IF($L21,IF(D$37>D$36,(D21-D$36)/(D$37-D$36),0)+0.000001,0) -> 1.000001 | Q21: =IF($L21,IF(E$37>E$36,(E21-E$36)/(E$37-E$36),0)+0.000001,0) -> 1e-06 | R21: =IF($L21,IF(F$37>F$36,(F21-F$36)/(F$37-F$36),0)+0.000001,0) -> 0.75998948 | S21: =IF($L21,IF(G$37>G$36,(G21-G$36)/(G$37-G$36),0)+0.000001,0) -> 0.48004275 | T21: =IF($L21,IF(H$37>H$36,(H21-H$36)/(H$37-H$36),0)+0.000001,0) -> 0.3765827 | U21: =IF($L21,IF(I$37>I$36,(I21-I$36)/(I$37-I$36),0)+0.000001,0) -> 0.44315723 | ... W21: =IF($L21,IF(K$37>K$36,(K21-K$36)/(K$37-K$36),0)+0.000001,0) -> 0.88971359 | Y21: =IF($L21,N21/N$38*LN(N21/N$38),0) -> -0.18191636 | Z21: =IF($L21,O21/O$38*LN(O21/O$38),0) -> -0.15272103 | AA21: =IF($L21,P21/P$38*LN(P21/P$38),0) -> -0.19653551 | AB21: =IF($L21,Q21/Q$38*LN(Q21/Q$38),0) -> -1.8600974e-06 | AC21: =IF($L21,R21/R$38*LN(R21/R$38),0) -> -0.15417234 | AD21: =IF($L21,S21/S$38*LN(S21/S$38),0) -> -0.15137232 | AE21: =IF($L21,T21/T$38*LN(T21/T$38),0) -> -0.1267541 | AF21: =IF($L21,U21/U$38*LN(U21/U$38),0) -> -0.15033494 | ... AH21: =IF($L21,W21/W$38*LN(W21/W$38),0) -> -0.19427074
A22: =Показатели!A12&" ЭТ" -> фреза 0.08×3.6 ЭТ | B22: =Показатели!D12 -> 120.10218 | C22: =Показатели!E12 -> 300.25544 | D22: =Показатели!F12 -> 0.26535173 | E22: =Показатели!G12 -> 0 | F22: =Показатели!H12 -> 27.891337 | G22: =Показатели!I12 -> 8802.1779 | H22: =Показатели!J12 -> 12912.109 | I22: =Показатели!K12 -> 20.2172 | ... K22: =Показатели!M12 -> 0.20070365 | L22: =Показатели!B12 -> TRUE | N22: =IF($L22,IF(B$37>B$36,(B22-B$36)/(B$37-B$36),0)+0.000001,0) -> 0.070107567 | O22: =IF($L22,IF(C$37>C$36,(C22-C$36)/(C$37-C$36),0)+0.000001,0) -> 0.18150178 | P22: =IF($L22,IF(D$37>D$36,(D22-D$36)/(D$37-D$36),0)+0.000001,0) -> 0.0010365299 | Q22: =IF($L22,IF(E$37>E$36,(E22-E$36)/(E$37-E$36),0)+0.000001,0) -> 1e-06 | R22: =IF($L22,IF(F$37>F$36,(F22-F$36)/(F$37-F$36),0)+0.000001,0) -> 0.45000316 | S22: =IF($L22,IF(G$37>G$36,(G22-G$36)/(G$37-G$36),0)+0.000001,0) -> 0.19136435 | T22: =IF($L22,IF(H$37>H$36,(H22-H$36)/(H$37-H$36),0)+0.000001,0) -> 0.28100176 | U22: =IF($L22,IF(I$37>I$36,(I22-I$36)/(I$37-I$36),0)+0.000001,0) -> 0.1907775 | ... W22: =IF($L22,IF(K$37>K$36,(K22-K$36)/(K$37-K$36),0)+0.000001,0) -> 0.059145505 | Y22: =IF($L22,N22/N$38*LN(N22/N$38),0) -> -0.041589153 | Z22: =IF($L22,O22/O$38*LN(O22/O$38),0) -> -0.080386468 | AA22: =IF($L22,P22/P$38*LN(P22/P$38),0) -> -0.00074814032 | AB22: =IF($L22,Q22/Q$38*LN(Q22/Q$38),0) -> -1.8600974e-06 | AC22: =IF($L22,R22/R$38*LN(R22/R$38),0) -> -0.10749258 | AD22: =IF($L22,S22/S$38*LN(S22/S$38),0) -> -0.078966952 | AE22: =IF($L22,T22/T$38*LN(T22/T$38),0) -> -0.10312514 | AF22: =IF($L22,U22/U$38*LN(U22/U$38),0) -> -0.082959913 | ... AH22: =IF($L22,W22/W$38*LN(W22/W$38),0) -> -0.026430554
A23: =Показатели!A12&" Д" -> фреза 0.08×3.6 Д | B23: =Показатели!N12 -> 328.60555 | C23: =Показатели!O12 -> 377.89638 | D23: =Показатели!P12 -> 1 | E23: =Показатели!Q12 -> 0 | F23: =Показатели!R12 -> 34.430235 | G23: =Показатели!S12 -> 9843.0547 | H23: =Показатели!T12 -> 11403.593 | I23: =Показатели!U12 -> 24.530999 | ... K23: =Показатели!W12 -> 0.83254414 | L23: =Показатели!B12 -> TRUE | N23: =IF($L23,IF(B$37>B$36,(B23-B$36)/(B$37-B$36),0)+0.000001,0) -> 0.42888199 | O23: =IF($L23,IF(C$37>C$36,(C23-C$36)/(C$37-C$36),0)+0.000001,0) -> 0.31985172 | P23: =IF($L23,IF(D$37>D$36,(D23-D$36)/(D$37-D$36),0)+0.000001,0) -> 1.000001 | Q23: =IF($L23,IF(E$37>E$36,(E23-E$36)/(E$37-E$36),0)+0.000001,0) -> 1e-06 | R23: =IF($L23,IF(F$37>F$36,(F23-F$36)/(F$37-F$36),0)+0.000001,0) -> 0.56664254 | S23: =IF($L23,IF(G$37>G$36,(G23-G$36)/(G$37-G$36),0)+0.000001,0) -> 0.27333582 | T23: =IF($L23,IF(H$37>H$36,(H23-H$36)/(H$37-H$36),0)+0.000001,0) -> 0.1900917 | U23: =IF($L23,IF(I$37>I$36,(I23-I$36)/(I$37-I$36),0)+0.000001,0) -> 0.31077284 | ... W23: =IF($L23,IF(K$37>K$36,(K23-K$36)/(K$37-K$36),0)+0.000001,0) -> 0.80288792 | Y23: =IF($L23,N23/N$38*LN(N23/N$38),0) -> -0.15710158 | Z23: =IF($L23,O23/O$38*LN(O23/O$38),0) -> -0.12095111 | AA23: =IF($L23,P23/P$38*LN(P23/P$38),0) -> -0.19653551 | AB23: =IF($L23,Q23/Q$38*LN(Q23/Q$38),0) -> -1.8600974e-06 | AC23: =IF($L23,R23/R$38*LN(R23/R$38),0) -> -0.12638051 | AD23: =IF($L23,S23/S$38*LN(S23/S$38),0) -> -0.10248057 | AE23: =IF($L23,T23/T$38*LN(T23/T$38),0) -> -0.077476772 | AF23: =IF($L23,U23/U$38*LN(U23/U$38),0) -> -0.11793655 | ... AH23: =IF($L23,W23/W$38*LN(W23/W$38),0) -> -0.18226199
A24: =Показатели!A13&" ЭТ" -> фреза 0.12×1.8 ЭТ | B24: =Показатели!D13 -> 201.91448 | C24: =Показатели!E13 -> 504.78621 | D24: =Показатели!F13 -> 0.26490451 | E24: =Показатели!G13 -> 0 | F24: =Показатели!H13 -> 39.359781 | G24: =Показатели!I13 -> 16413.811 | H24: =Показатели!J13 -> 24235.367 | I24: =Показатели!K13 -> 33.988938 | ... K24: =Показатели!M13 -> 0.22916911 | L24: =Показатели!B13 -> TRUE | N24: =IF($L24,IF(B$37>B$36,(B24-B$36)/(B$37-B$36),0)+0.000001,0) -> 0.21088305 | O24: =IF($L24,IF(C$37>C$36,(C24-C$36)/(C$37-C$36),0)+0.000001,0) -> 0.54595922 | P24: =IF($L24,IF(D$37>D$36,(D24-D$36)/(D$37-D$36),0)+0.000001,0) -> 0.00042840953 | Q24: =IF($L24,IF(E$37>E$36,(E24-E$36)/(E$37-E$36),0)+0.000001,0) -> 1e-06 | R24: =IF($L24,IF(F$37>F$36,(F24-F$36)/(F$37-F$36),0)+0.000001,0) -> 0.65457466 | S24: =IF($L24,IF(G$37>G$36,(G24-G$36)/(G$37-G$36),0)+0.000001,0) -> 0.79079811 | T24: =IF($L24,IF(H$37>H$36,(H24-H$36)/(H$37-H$36),0)+0.000001,0) -> 0.96339266 | U24: =IF($L24,IF(I$37>I$36,(I24-I$36)/(I$37-I$36),0)+0.000001,0) -> 0.57386078 | ... W24: =IF($L24,IF(K$37>K$36,(K24-K$36)/(K$37-K$36),0)+0.000001,0) -> 0.092652342 | Y24: =IF($L24,N24/N$38*LN(N24/N$38),0) -> -0.096003168 | Z24: =IF($L24,O24/O$38*LN(O24/O$38),0) -> -0.17309345 | AA24: =IF($L24,P24/P$38*LN(P24/P$38),0) -> -0.00033814654 | AB24: =IF($L24,Q24/Q$38*LN(Q24/Q$38),0) -> -1.8600974e-06 | AC24: =IF($L24,R24/R$38*LN(R24/R$38),0) -> -0.1395039 | AD24: =IF($L24,S24/S$38*LN(S24/S$38),0) -> -0.20759195 | AE24: =IF($L24,T24/T$38*LN(T24/T$38),0) -> -0.23030372 | AF24: =IF($L24,U24/U$38*LN(U24/U$38),0) -> -0.1778476 | ... AH24: =IF($L24,W24/W$38*LN(W24/W$38),0) -> -0.037898169
A25: =Показатели!A13&" Д" -> фреза 0.12×1.8 Д | B25: =Показатели!N13 -> 583.91663 | C25: =Показатели!O13 -> 671.50413 | D25: =Показатели!P13 -> 1 | E25: =Показатели!Q13 -> 0 | F25: =Показатели!R13 -> 44.378437 | G25: =Показатели!S13 -> 18333.508 | H25: =Показатели!T13 -> 21303.347 | I25: =Показатели!U13 -> 43.590434 | ... K25: =Показатели!W13 -> 0.89094426 | L25: =Показатели!B13 -> TRUE | N25: =IF($L25,IF(B$37>B$36,(B25-B$36)/(B$37-B$36),0)+0.000001,0) -> 0.86819905 | O25: =IF($L25,IF(C$37>C$36,(C25-C$36)/(C$37-C$36),0)+0.000001,0) -> 0.84303721 | P25: =IF($L25,IF(D$37>D$36,(D25-D$36)/(D$37-D$36),0)+0.000001,0) -> 1.000001 | Q25: =IF($L25,IF(E$37>E$36,(E25-E$36)/(E$37-E$36),0)+0.000001,0) -> 1e-06 | R25: =IF($L25,IF(F$37>F$36,(F25-F$36)/(F$37-F$36),0)+0.000001,0) -> 0.74409629 | S25: =IF($L25,IF(G$37>G$36,(G25-G$36)/(G$37-G$36),0)+0.000001,0) -> 0.94197872 | T25: =IF($L25,IF(H$37>H$36,(H25-H$36)/(H$37-H$36),0)+0.000001,0) -> 0.78669584 | U25: =IF($L25,IF(I$37>I$36,(I25-I$36)/(I$37-I$36),0)+0.000001,0) -> 0.840942 | ... W25: =IF($L25,IF(K$37>K$36,(K25-K$36)/(K$37-K$36),0)+0.000001,0) -> 0.87163098 | Y25: =IF($L25,N25/N$38*LN(N25/N$38),0) -> -0.24131366 | Z25: =IF($L25,O25/O$38*LN(O25/O$38),0) -> -0.22542375 | AA25: =IF($L25,P25/P$38*LN(P25/P$38),0) -> -0.19653551 | AB25: =IF($L25,Q25/Q$38*LN(Q25/Q$38),0) -> -1.8600974e-06 | AC25: =IF($L25,R25/R$38*LN(R25/R$38),0) -> -0.15202881 | AD25: =IF($L25,S25/S$38*LN(S25/S$38),0) -> -0.22984038 | AE25: =IF($L25,T25/T$38*LN(T25/T$38),0) -> -0.2046149 | AF25: =IF($L25,U25/U$38*LN(U25/U$38),0) -> -0.22416301 | ... AH25: =IF($L25,W25/W$38*LN(W25/W$38),0) -> -0.19183108
A26: =Показатели!A14&" ЭТ" -> фреза 0.12×2.7 ЭТ | B26: =Показатели!D14 -> 176.90447 | C26: =Показатели!E14 -> 442.26118 | D26: =Показатели!F14 -> 0.26592258 | E26: =Показатели!G14 -> 0 | F26: =Показатели!H14 -> 18.901985 | G26: =Показатели!I14 -> 11713.373 | H26: =Показатели!J14 -> 17130.659 | I26: =Показатели!K14 -> 29.778919 | ... K26: =Показатели!M14 -> 0.17605734 | L26: =Показатели!B14 -> TRUE | N26: =IF($L26,IF(B$37>B$36,(B26-B$36)/(B$37-B$36),0)+0.000001,0) -> 0.167848 | O26: =IF($L26,IF(C$37>C$36,(C26-C$36)/(C$37-C$36),0)+0.000001,0) -> 0.43454462 | P26: =IF($L26,IF(D$37>D$36,(D26-D$36)/(D$37-D$36),0)+0.000001,0) -> 0.001812766 | Q26: =IF($L26,IF(E$37>E$36,(E26-E$36)/(E$37-E$36),0)+0.000001,0) -> 1e-06 | R26: =IF($L26,IF(F$37>F$36,(F26-F$36)/(F$37-F$36),0)+0.000001,0) -> 0.28965315 | S26: =IF($L26,IF(G$37>G$36,(G26-G$36)/(G$37-G$36),0)+0.000001,0) -> 0.42062771 | T26: =IF($L26,IF(H$37>H$36,(H26-H$36)/(H$37-H$36),0)+0.000001,0) -> 0.53523074 | U26: =IF($L26,IF(I$37>I$36,(I26-I$36)/(I$37-I$36),0)+0.000001,0) -> 0.45675227 | ... W26: =IF($L26,IF(K$37>K$36,(K26-K$36)/(K$37-K$36),0)+0.000001,0) -> 0.030134219 | Y26: =IF($L26,N26/N$38*LN(N26/N$38),0) -> -0.081211549 | Z26: =IF($L26,O26/O$38*LN(O26/O$38),0) -> -0.14910445 | AA26: =IF($L26,P26/P$38*LN(P26/P$38),0) -> -0.0012309584 | AB26: =IF($L26,Q26/Q$38*LN(Q26/Q$38),0) -> -1.8600974e-06 | AC26: =IF($L26,R26/R$38*LN(R26/R$38),0) -> -0.077958435 | AD26: =IF($L26,S26/S$38*LN(S26/S$38),0) -> -0.13851795 | AE26: =IF($L26,T26/T$38*LN(T26/T$38),0) -> -0.16061514 | AF26: =IF($L26,U26/U$38*LN(U26/U$38),0) -> -0.15338112 | ... AH26: =IF($L26,W26/W$38*LN(W26/W$38),0) -> -0.01517916
A27: =Показатели!A14&" Д" -> фреза 0.12×2.7 Д | B27: =Показатели!N14 -> 463.55608 | C27: =Показатели!O14 -> 533.0895 | D27: =Показатели!P14 -> 1 | E27: =Показатели!Q14 -> 0 | F27: =Показатели!R14 -> 25.712123 | G27: =Показатели!S14 -> 13152.67 | H27: =Показатели!T14 -> 15182.975 | I27: =Показатели!U14 -> 34.605301 | ... K27: =Показатели!W14 -> 0.76872325 | L27: =Показатели!B14 -> TRUE | N27: =IF($L27,IF(B$37>B$36,(B27-B$36)/(B$37-B$36),0)+0.000001,0) -> 0.6610931 | O27: =IF($L27,IF(C$37>C$36,(C27-C$36)/(C$37-C$36),0)+0.000001,0) -> 0.59639342 | P27: =IF($L27,IF(D$37>D$36,(D27-D$36)/(D$37-D$36),0)+0.000001,0) -> 1.000001 | Q27: =IF($L27,IF(E$37>E$36,(E27-E$36)/(E$37-E$36),0)+0.000001,0) -> 1e-06 | R27: =IF($L27,IF(F$37>F$36,(F27-F$36)/(F$37-F$36),0)+0.000001,0) -> 0.41113085 | S27: =IF($L27,IF(G$37>G$36,(G27-G$36)/(G$37-G$36),0)+0.000001,0) -> 0.5339757 | T27: =IF($L27,IF(H$37>H$36,(H27-H$36)/(H$37-H$36),0)+0.000001,0) -> 0.41785443 | U27: =IF($L27,IF(I$37>I$36,(I27-I$36)/(I$37-I$36),0)+0.000001,0) -> 0.59100592 | ... W27: =IF($L27,IF(K$37>K$36,(K27-K$36)/(K$37-K$36),0)+0.000001,0) -> 0.72776406 | Y27: =IF($L27,N27/N$38*LN(N27/N$38),0) -> -0.20632153 | Z27: =IF($L27,O27/O$38*LN(O27/O$38),0) -> -0.18306147 | AA27: =IF($L27,P27/P$38*LN(P27/P$38),0) -> -0.19653551 | AB27: =IF($L27,Q27/Q$38*LN(Q27/Q$38),0) -> -1.8600974e-06 | AC27: =IF($L27,R27/R$38*LN(R27/R$38),0) -> -0.10075936 | AD27: =IF($L27,S27/S$38*LN(S27/S$38),0) -> -0.16236268 | AE27: =IF($L27,T27/T$38*LN(T27/T$38),0) -> -0.13613359 | AF27: =IF($L27,U27/U$38*LN(U27/U$38),0) -> -0.18118728 | ... AH27: =IF($L27,W27/W$38*LN(W27/W$38),0) -> -0.17123505
A28: =Показатели!A15&" ЭТ" -> фреза 0.12×3.6 ЭТ | B28: =Показатели!D15 -> 158.05184 | C28: =Показатели!E15 -> 395.12959 | D28: =Показатели!F15 -> 0.26667584 | E28: =Показатели!G15 -> 0 | F28: =Показатели!H15 -> 2.6638495 | G28: =Показатели!I15 -> 9282.7682 | H28: =Показатели!J15 -> 13592.512 | I28: =Показатели!K15 -> 26.605392 | ... K28: =Показатели!M15 -> 0.1504579 | L28: =Показатели!B15 -> TRUE | N28: =IF($L28,IF(B$37>B$36,(B28-B$36)/(B$37-B$36),0)+0.000001,0) -> 0.13540803 | O28: =IF($L28,IF(C$37>C$36,(C28-C$36)/(C$37-C$36),0)+0.000001,0) -> 0.35055991 | P28: =IF($L28,IF(D$37>D$36,(D28-D$36)/(D$37-D$36),0)+0.000001,0) -> 0.0028370402 | Q28: =IF($L28,IF(E$37>E$36,(E28-E$36)/(E$37-E$36),0)+0.000001,0) -> 1e-06 | R28: =IF($L28,IF(F$37>F$36,(F28-F$36)/(F$37-F$36),0)+0.000001,0) -> 1e-06 | S28: =IF($L28,IF(G$37>G$36,(G28-G$36)/(G$37-G$36),0)+0.000001,0) -> 0.22921195 | T28: =IF($L28,IF(H$37>H$36,(H28-H$36)/(H$37-H$36),0)+0.000001,0) -> 0.32200594 | U28: =IF($L28,IF(I$37>I$36,(I28-I$36)/(I$37-I$36),0)+0.000001,0) -> 0.36847546 | ... W28: =IF($L28,IF(K$37>K$36,(K28-K$36)/(K$37-K$36),0)+0.000001,0) -> 1e-06 | Y28: =IF($L28,N28/N$38*LN(N28/N$38),0) -> -0.069159287 | Z28: =IF($L28,O28/O$38*LN(O28/O$38),0) -> -0.12889076 | AA28: =IF($L28,P28/P$38*LN(P28/P$38),0) -> -0.0018293657 | AB28: =IF($L28,Q28/Q$38*LN(Q28/Q$38),0) -> -1.8600974e-06 | AC28: =IF($L28,R28/R$38*LN(R28/R$38),0) -> -1.1333218e-06 | AD28: =IF($L28,S28/S$38*LN(S28/S$38),0) -> -0.090207601 | AE28: =IF($L28,T28/T$38*LN(T28/T$38),0) -> -0.11361905 | AF28: =IF($L28,U28/U$38*LN(U28/U$38),0) -> -0.13271488 | ... AH28: =IF($L28,W28/W$38*LN(W28/W$38),0) -> -1.3731114e-06
A29: =Показатели!A15&" Д" -> фреза 0.12×3.6 Д | B29: =Показатели!N15 -> 392.6616 | C29: =Показатели!O15 -> 451.56085 | D29: =Показатели!P15 -> 1 | E29: =Показатели!Q15 -> 0 | F29: =Показатели!R15 -> 10.96989 | G29: =Показатели!S15 -> 10459.196 | H29: =Показатели!T15 -> 12019.734 | I29: =Показатели!U15 -> 29.3129 | ... K29: =Показатели!W15 -> 0.69875244 | L29: =Показатели!B15 -> TRUE | N29: =IF($L29,IF(B$37>B$36,(B29-B$36)/(B$37-B$36),0)+0.000001,0) -> 0.53910407 | O29: =IF($L29,IF(C$37>C$36,(C29-C$36)/(C$37-C$36),0)+0.000001,0) -> 0.45111589 | P29: =IF($L29,IF(D$37>D$36,(D29-D$36)/(D$37-D$36),0)+0.000001,0) -> 1.000001 | Q29: =IF($L29,IF(E$37>E$36,(E29-E$36)/(E$37-E$36),0)+0.000001,0) -> 1e-06 | R29: =IF($L29,IF(F$37>F$36,(F29-F$36)/(F$37-F$36),0)+0.000001,0) -> 0.14816226 | S29: =IF($L29,IF(G$37>G$36,(G29-G$36)/(G$37-G$36),0)+0.000001,0) -> 0.32185836 | T29: =IF($L29,IF(H$37>H$36,(H29-H$36)/(H$37-H$36),0)+0.000001,0) -> 0.22722316 | U29: =IF($L29,IF(I$37>I$36,(I29-I$36)/(I$37-I$36),0)+0.000001,0) -> 0.44378918 | ... W29: =IF($L29,IF(K$37>K$36,(K29-K$36)/(K$37-K$36),0)+0.000001,0) -> 0.64540108 | Y29: =IF($L29,N29/N$38*LN(N29/N$38),0) -> -0.1820276 | Z29: =IF($L29,O29/O$38*LN(O29/O$38),0) -> -0.15286113 | AA29: =IF($L29,P29/P$38*LN(P29/P$38),0) -> -0.19653551 | AB29: =IF($L29,Q29/Q$38*LN(Q29/Q$38),0) -> -1.8600974e-06 | AC29: =IF($L29,R29/R$38*LN(R29/R$38),0) -> -0.046701979 | AD29: =IF($L29,S29/S$38*LN(S29/S$38),0) -> -0.11510735 | AE29: =IF($L29,T29/T$38*LN(T29/T$38),0) -> -0.088400888 | AF29: =IF($L29,U29/U$38*LN(U29/U$38),0) -> -0.15047757 | ... AH29: =IF($L29,W29/W$38*LN(W29/W$38),0) -> -0.1583903
A30: =Показатели!A16&" ЭТ" -> фреза 0.16×1.8 ЭТ | B30: =Показатели!D16 -> 247.29421 | C30: =Показатели!E16 -> 618.23553 | D30: =Показатели!F16 -> 0.26573216 | E30: =Показатели!G16 -> 0 | F30: =Показатели!H16 -> 24.276424 | G30: =Показатели!I16 -> 16988.495 | H30: =Показатели!J16 -> 24842.827 | I30: =Показатели!K16 -> 41.627859 | ... K30: =Показатели!M16 -> 0.1846786 | L30: =Показатели!B16 -> TRUE | N30: =IF($L30,IF(B$37>B$36,(B30-B$36)/(B$37-B$36),0)+0.000001,0) -> 0.28896853 | O30: =IF($L30,IF(C$37>C$36,(C30-C$36)/(C$37-C$36),0)+0.000001,0) -> 0.74811683 | P30: =IF($L30,IF(D$37>D$36,(D30-D$36)/(D$37-D$36),0)+0.000001,0) -> 0.0015538407 | Q30: =IF($L30,IF(E$37>E$36,(E30-E$36)/(E$37-E$36),0)+0.000001,0) -> 1e-06 | R30: =IF($L30,IF(F$37>F$36,(F30-F$36)/(F$37-F$36),0)+0.000001,0) -> 0.38552117 | S30: =IF($L30,IF(G$37>G$36,(G30-G$36)/(G$37-G$36),0)+0.000001,0) -> 0.83605579 | T30: =IF($L30,IF(H$37>H$36,(H30-H$36)/(H$37-H$36),0)+0.000001,0) -> 1.000001 | U30: =IF($L30,IF(I$37>I$36,(I30-I$36)/(I$37-I$36),0)+0.000001,0) -> 0.78634979 | ... W30: =IF($L30,IF(K$37>K$36,(K30-K$36)/(K$37-K$36),0)+0.000001,0) -> 0.040282344 | Y30: =IF($L30,N30/N$38*LN(N30/N$38),0) -> -0.12014629 | Z30: =IF($L30,O30/O$38*LN(O30/O$38),0) -> -0.21025485 | AA30: =IF($L30,P30/P$38*LN(P30/P$38),0) -> -0.0010734398 | AB30: =IF($L30,Q30/Q$38*LN(Q30/Q$38),0) -> -1.8600974e-06 | AC30: =IF($L30,R30/R$38*LN(R30/R$38),0) -> -0.096186736 | AD30: =IF($L30,S30/S$38*LN(S30/S$38),0) -> -0.21454889 | AE30: =IF($L30,T30/T$38*LN(T30/T$38),0) -> -0.23518254 | AF30: =IF($L30,U30/U$38*LN(U30/U$38),0) -> -0.21559864 | ... AH30: =IF($L30,W30/W$38*LN(W30/W$38),0) -> -0.019305351
A31: =Показатели!A16&" Д" -> фреза 0.16×1.8 Д | B31: =Показатели!N16 -> 660.51393 | C31: =Показатели!O16 -> 759.59102 | D31: =Показатели!P16 -> 1 | E31: =Показатели!Q16 -> 0 | F31: =Показатели!R16 -> 30.351643 | G31: =Показатели!S16 -> 19070.277 | H31: =Показатели!T16 -> 22040.116 | I31: =Показатели!U16 -> 49.308561 | ... K31: =Показатели!W16 -> 0.78883551 | L31: =Показатели!B16 -> TRUE | N31: =IF($L31,IF(B$37>B$36,(B31-B$36)/(B$37-B$36),0)+0.000001,0) -> 1.000001 | O31: =IF($L31,IF(C$37>C$36,(C31-C$36)/(C$37-C$36),0)+0.000001,0) -> 1.000001 | P31: =IF($L31,IF(D$37>D$36,(D31-D$36)/(D$37-D$36),0)+0.000001,0) -> 1.000001 | Q31: =IF($L31,IF(E$37>E$36,(E31-E$36)/(E$37-E$36),0)+0.000001,0) -> 1e-06 | R31: =IF($L31,IF(F$37>F$36,(F31-F$36)/(F$37-F$36),0)+0.000001,0) -> 0.49388955 | S31: =IF($L31,IF(G$37>G$36,(G31-G$36)/(G$37-G$36),0)+0.000001,0) -> 1.000001 | T31: =IF($L31,IF(H$37>H$36,(H31-H$36)/(H$37-H$36),0)+0.000001,0) -> 0.83109689 | U31: =IF($L31,IF(I$37>I$36,(I31-I$36)/(I$37-I$36),0)+0.000001,0) -> 1.000001 | ... W31: =IF($L31,IF(K$37>K$36,(K31-K$36)/(K$37-K$36),0)+0.000001,0) -> 0.75143829 | Y31: =IF($L31,N31/N$38*LN(N31/N$38),0) -> -0.26024014 | Z31: =IF($L31,O31/O$38*LN(O31/O$38),0) -> -0.24788265 | AA31: =IF($L31,P31/P$38*LN(P31/P$38),0) -> -0.19653551 | AB31: =IF($L31,Q31/Q$38*LN(Q31/Q$38),0) -> -1.8600974e-06 | AC31: =IF($L31,R31/R$38*LN(R31/R$38),0) -> -0.11481766 | AD31: =IF($L31,S31/S$38*LN(S31/S$38),0) -> -0.23767247 | AE31: =IF($L31,T31/T$38*LN(T31/T$38),0) -> -0.21142521 | AF31: =IF($L31,U31/U$38*LN(U31/U$38),0) -> -0.24690911 | ... AH31: =IF($L31,W31/W$38*LN(W31/W$38),0) -> -0.17477755
A32: =Показатели!A17&" ЭТ" -> фреза 0.16×2.7 ЭТ | B32: =Показатели!D17 -> 218.05245 | C32: =Показатели!E17 -> 545.13112 | D32: =Показатели!F17 -> 0.26702994 | E32: =Показатели!G17 -> 0 | F32: =Показатели!H17 -> -1.6132205 | G32: =Показатели!I17 -> 12234.466 | H32: =Показатели!J17 -> 17929.538 | I32: =Показатели!K17 -> 36.705495 | ... K32: =Показатели!M17 -> 0.14160564 | L32: =Показатели!B17 -> FALSE | N32: =IF($L32,IF(B$37>B$36,(B32-B$36)/(B$37-B$36),0)+0.000001,0) -> 0 | O32: =IF($L32,IF(C$37>C$36,(C32-C$36)/(C$37-C$36),0)+0.000001,0) -> 0 | P32: =IF($L32,IF(D$37>D$36,(D32-D$36)/(D$37-D$36),0)+0.000001,0) -> 0 | Q32: =IF($L32,IF(E$37>E$36,(E32-E$36)/(E$37-E$36),0)+0.000001,0) -> 0 | R32: =IF($L32,IF(F$37>F$36,(F32-F$36)/(F$37-F$36),0)+0.000001,0) -> 0 | S32: =IF($L32,IF(G$37>G$36,(G32-G$36)/(G$37-G$36),0)+0.000001,0) -> 0 | T32: =IF($L32,IF(H$37>H$36,(H32-H$36)/(H$37-H$36),0)+0.000001,0) -> 0 | U32: =IF($L32,IF(I$37>I$36,(I32-I$36)/(I$37-I$36),0)+0.000001,0) -> 0 | ... W32: =IF($L32,IF(K$37>K$36,(K32-K$36)/(K$37-K$36),0)+0.000001,0) -> 0 | Y32: =IF($L32,N32/N$38*LN(N32/N$38),0) -> 0 | Z32: =IF($L32,O32/O$38*LN(O32/O$38),0) -> 0 | AA32: =IF($L32,P32/P$38*LN(P32/P$38),0) -> 0 | AB32: =IF($L32,Q32/Q$38*LN(Q32/Q$38),0) -> 0 | AC32: =IF($L32,R32/R$38*LN(R32/R$38),0) -> 0 | AD32: =IF($L32,S32/S$38*LN(S32/S$38),0) -> 0 | AE32: =IF($L32,T32/T$38*LN(T32/T$38),0) -> 0 | AF32: =IF($L32,U32/U$38*LN(U32/U$38),0) -> 0 | ... AH32: =IF($L32,W32/W$38*LN(W32/W$38),0) -> 0
A33: =Показатели!A17&" Д" -> фреза 0.16×2.7 Д | B33: =Показатели!N17 -> 533.01073 | C33: =Показатели!O17 -> 612.96234 | D33: =Показатели!P17 -> 1 | E33: =Показатели!Q17 -> 0 | F33: =Показатели!R17 -> 6.6339732 | G33: =Показатели!S17 -> 13820.741 | H33: =Показатели!T17 -> 15851.046 | I33: =Показатели!U17 -> 39.790216 | ... K33: =Показатели!W17 -> 0.67031207 | L33: =Показатели!B17 -> FALSE | N33: =IF($L33,IF(B$37>B$36,(B33-B$36)/(B$37-B$36),0)+0.000001,0) -> 0 | O33: =IF($L33,IF(C$37>C$36,(C33-C$36)/(C$37-C$36),0)+0.000001,0) -> 0 | P33: =IF($L33,IF(D$37>D$36,(D33-D$36)/(D$37-D$36),0)+0.000001,0) -> 0 | Q33: =IF($L33,IF(E$37>E$36,(E33-E$36)/(E$37-E$36),0)+0.000001,0) -> 0 | R33: =IF($L33,IF(F$37>F$36,(F33-F$36)/(F$37-F$36),0)+0.000001,0) -> 0 | S33: =IF($L33,IF(G$37>G$36,(G33-G$36)/(G$37-G$36),0)+0.000001,0) -> 0 | T33: =IF($L33,IF(H$37>H$36,(H33-H$36)/(H$37-H$36),0)+0.000001,0) -> 0 | U33: =IF($L33,IF(I$37>I$36,(I33-I$36)/(I$37-I$36),0)+0.000001,0) -> 0 | ... W33: =IF($L33,IF(K$37>K$36,(K33-K$36)/(K$37-K$36),0)+0.000001,0) -> 0 | Y33: =IF($L33,N33/N$38*LN(N33/N$38),0) -> 0 | Z33: =IF($L33,O33/O$38*LN(O33/O$38),0) -> 0 | AA33: =IF($L33,P33/P$38*LN(P33/P$38),0) -> 0 | AB33: =IF($L33,Q33/Q$38*LN(Q33/Q$38),0) -> 0 | AC33: =IF($L33,R33/R$38*LN(R33/R$38),0) -> 0 | AD33: =IF($L33,S33/S$38*LN(S33/S$38),0) -> 0 | AE33: =IF($L33,T33/T$38*LN(T33/T$38),0) -> 0 | AF33: =IF($L33,U33/U$38*LN(U33/U$38),0) -> 0 | ... AH33: =IF($L33,W33/W$38*LN(W33/W$38),0) -> 0
A35: m (допустимых) | B35: =COUNTIF(L2:L33,TRUE()) -> 26
A36: min | B36: =_xlfn.MINIFS(B2:B33,$L$2:$L$33,TRUE()) -> 79.35943 | C36: =_xlfn.MINIFS(C2:C33,$L$2:$L$33,TRUE()) -> 198.39858 | D36: =_xlfn.MINIFS(D2:D33,$L$2:$L$33,TRUE()) -> 0.26459019 | E36: =_xlfn.MINIFS(E2:E33,$L$2:$L$33,TRUE()) -> 0 | F36: =_xlfn.MINIFS(F2:F33,$L$2:$L$33,TRUE()) -> 2.6638495 | G36: =_xlfn.MINIFS(G2:G33,$L$2:$L$33,TRUE()) -> 6372.2387 | H36: =_xlfn.MINIFS(H2:H33,$L$2:$L$33,TRUE()) -> 8249.3215 | I36: =_xlfn.MINIFS(I2:I33,$L$2:$L$33,TRUE()) -> 13.358837 | ... K36: =_xlfn.MINIFS(K2:K33,$L$2:$L$33,TRUE()) -> 0.1504579
A37: max | B37: =_xlfn.MAXIFS(B2:B33,$L$2:$L$33,TRUE()) -> 660.51393 | C37: =_xlfn.MAXIFS(C2:C33,$L$2:$L$33,TRUE()) -> 759.59102 | D37: =_xlfn.MAXIFS(D2:D33,$L$2:$L$33,TRUE()) -> 1 | E37: =_xlfn.MAXIFS(E2:E33,$L$2:$L$33,TRUE()) -> 12.211049 | F37: =_xlfn.MAXIFS(F2:F33,$L$2:$L$33,TRUE()) -> 58.724663 | G37: =_xlfn.MAXIFS(G2:G33,$L$2:$L$33,TRUE()) -> 19070.277 | H37: =_xlfn.MAXIFS(H2:H33,$L$2:$L$33,TRUE()) -> 24842.827 | I37: =_xlfn.MAXIFS(I2:I33,$L$2:$L$33,TRUE()) -> 49.308561 | ... K37: =_xlfn.MAXIFS(K2:K33,$L$2:$L$33,TRUE()) -> 1
A38: Σ z | B38: =SUM(N2:N33) -> 7.981654 | C38: =SUM(O2:O33) -> 8.7506113 | D38: =SUM(P2:P33) -> 13.083343 | E38: =SUM(Q2:Q33) -> 8.5830449 | F38: =SUM(R2:R33) -> 14.553071 | G38: =SUM(S2:S33) -> 9.4500847 | H38: =SUM(T2:T33) -> 9.6305833 | I38: =SUM(U2:U33) -> 8.8146418 | ... K38: =SUM(W2:W33) -> 11.862778 | N38: =SUM(N2:N33) -> 7.981654 | O38: =SUM(O2:O33) -> 8.7506113 | P38: =SUM(P2:P33) -> 13.083343 | Q38: =SUM(Q2:Q33) -> 8.5830449 | R38: =SUM(R2:R33) -> 14.553071 | S38: =SUM(S2:S33) -> 9.4500847 | T38: =SUM(T2:T33) -> 9.6305833 | U38: =SUM(U2:U33) -> 8.8146418 | ... W38: =SUM(W2:W33) -> 11.862778
A39: Энтропия E | B39: =-SUM(Y2:Y33)/LN($B$35) -> 0.87773084 | C39: =-SUM(Z2:Z33)/LN($B$35) -> 0.90789701 | D39: =-SUM(AA2:AA33)/LN($B$35) -> 0.79665228 | E39: =-SUM(AB2:AB33)/LN($B$35) -> 0.75418144 | F39: =-SUM(AC2:AC33)/LN($B$35) -> 0.95566732 | G39: =-SUM(AD2:AD33)/LN($B$35) -> 0.89408794 | H39: =-SUM(AE2:AE33)/LN($B$35) -> 0.89681907 | I39: =-SUM(AF2:AF33)/LN($B$35) -> 0.90702599 | ... K39: =-SUM(AH2:AH33)/LN($B$35) -> 0.86951762
A40: Энтропийный вес | B40: =(1-B39)/(10-SUM($B$39:$K$39)) -> 0.089237252 | C40: =(1-C39)/(10-SUM($B$39:$K$39)) -> 0.067220688 | D40: =(1-D39)/(10-SUM($B$39:$K$39)) -> 0.14841184 | E40: =(1-E39)/(10-SUM($B$39:$K$39)) -> 0.17940887 | F40: =(1-F39)/(10-SUM($B$39:$K$39)) -> 0.03235588 | G40: =(1-G39)/(10-SUM($B$39:$K$39)) -> 0.077299136 | H40: =(1-H39)/(10-SUM($B$39:$K$39)) -> 0.075305843 | I40: =(1-I39)/(10-SUM($B$39:$K$39)) -> 0.067856399 | ... K40: =(1-K39)/(10-SUM($B$39:$K$39)) -> 0.095231611

Sheet Устойчивость
A1: Сценарий | B1: Машина | C1: a, м | D1: v, км/ч | E1: I среднее | F1: I 5 % | G1: I 95 % | H1: P(I>0) | I1: P(C_сов ЭТ < Д) | K1: Значения получены программой src/analysis.py (1000 испытаний Монте-Карло: параметры — равномерно в диапазонах листа «Исходные», веса — распределение Дирихле с параметром 50·w). S1 — полная смена, S2 — задание 0,5 га.
A2: S1 | B2: культиватор | C2: 0.08 | D2: 3.6 | E2: 0.023 | F2: -0.1145 | G2: 0.1527 | H2: 0.606 | I2: 0.162
A3: S1 | B3: культиватор | C3: 0.08 | D3: 4.5 | E3: -0.0096 | F3: -0.1425 | G3: 0.1201 | H3: 0.457 | I3: 0.102
A4: S1 | B4: культиватор | C4: 0.08 | D4: 5.4 | E4: -0.0334 | F4: -0.1713 | G4: 0.1006 | H4: 0.341 | I4: 0.049
A5: S1 | B5: культиватор | C5: 0.11 | D5: 3.6 | E5: -0.0079 | F5: -0.1401 | G5: 0.123 | H5: 0.458 | I5: 0.1
A6: S1 | B6: культиватор | C6: 0.11 | D6: 4.5 | E6: -0.0332 | F6: -0.1711 | G6: 0.1015 | H6: 0.337 | I6: 0.05
A7: S1 | B7: культиватор | C7: 0.11 | D7: 5.4 | E7: -0.0593 | F7: -0.1981 | G7: 0.0786 | H7: 0.237 | I7: 0.053
A8: S1 | B8: культиватор | C8: 0.14 | D8: 3.6 | E8: -0.0237 | F8: -0.1622 | G8: 0.1102 | H8: 0.387 | I8: 0.058
A9: S1 | B9: культиватор | C9: 0.14 | D9: 4.5 | E9: -0.0498 | F9: -0.1905 | G9: 0.0893 | H9: 0.278 | I9: 0.062
A10: S1 | B10: фреза | C10: 0.08 | D10: 1.8 | E10: 0.0061 | F10: -0.1282 | G10: 0.1393 | H10: 0.531 | I10: 0.169
A11: S1 | B11: фреза | C11: 0.08 | D11: 2.7 | E11: -0.0331 | F11: -0.1666 | G11: 0.0982 | H11: 0.336 | I11: 0.085
A12: S1 | B12: фреза | C12: 0.08 | D12: 3.6 | E12: -0.0523 | F12: -0.1886 | G12: 0.0814 | H12: 0.256 | I12: 0.047
A13: S1 | B13: фреза | C13: 0.12 | D13: 1.8 | E13: -0.0352 | F13: -0.1689 | G13: 0.0976 | H13: 0.325 | I13: 0.074
... A33: S2 | B33: фреза | C33: 0.16 | D33: 2.7 | E33: 0.0288 | F33: -0.0961 | G33: 0.1474 | H33: 0.639 | I33: 0.048
A36: Параметр | B36: SRC S1 | C36: SRC S2
A37: EF_grid | B37: -0.1544 | C37: -0.2241
A38: PEF_el | B38: -0.0669 | C38: -0.1162
A39: T_year_h | B39: 0.1121 | C39: 0.1471
A40: bat_usd_kWh | B40: -0.0135 | C40: 0.0005
A41: c_D | B41: 0.0391 | C41: 0.0813
A42: c_el | B42: -0.0216 | C42: -0.0086
A43: eta_bat | B43: 0.0213 | C43: 0.0389
A44: eta_ch | B44: 0.0913 | C44: 0.1415
A45: eta_ep | B45: 0.0651 | C45: 0.1085
A46: eta_tr | B46: 0.0287 | C46: 0.0314
A47: k_D | B47: 0.1925 | C47: 0.2042
A48: k_RM_ET | B48: 0.025 | C48: 0.0079
... A51: r_disc | B51: -0.0672 | C51: -0.1007
